Workbook

Sheet prod_$_data
A1: main_id | B1: facility_group_id | C1: facility_name | D1: facility_group_name | E1: province | F1: facility_type | G1: mining_processing_type | H1: archetypes | I1: biosphere_data? | J1: technosphere_data? | K1: land_data? | L1: commodities | M1: Main_product | N1: ore_processed_t | O1: concentrate_dore_mass_t | P1: tailings_mass_t | Q1: Au_t | R1: Ag_t | S1: Cu_t | T1: Ni_t | U1: Co_t | V1: Mo_t | W1: Zn_t | X1: Pb_t | Y1: Fe_t | Z1: Pt_t | AA1: Pd_t | AB1: U_t | AC1: Nb_t | AD1: Au_conc_t | AE1: Ag_conc_t | AF1: Cu_conc_t | AG1: Ni_conc_t | AH1: Co_conc_t | AI1: Mo_conc_t | AJ1: Zn_conc_t | AK1: Pb_conc_t | AL1: Fe_conc_t | AM1: Pt_conc_t | AN1: Pd_conc_t | AO1: U_conc_t | AP1: Nb_conc_t | AQ1: Au_$ | AR1: Ag_$ | AS1: Cu_$ | AT1: Ni_$ | AU1: Co_$ | AV1: Mo_$ | AW1: Zn_$ | AX1: Pb_$ | AY1: Fe_$ | AZ1: Pt_$ | BA1: U_$ | BB1: N_$ | BC1: Sum | BD1: %Au | BE1: %Cu | BF1: Main_product
A2: QC-MAIN-089f3c60 | C2: Bloom Lake | E2: Quebec | F2: mining | G2: Open-pit | H2: Magnetite concentrator | I2: NPRI+GHG+Land | L2: Iron | M2: Fe | N2: =prod_table_raw!N11 -> 11187000 | O2: =SUM(AD2:AP2) -> 0 | P2: =N2-O2 -> 11187000 | AF2: =S2/(concentrate_grade!$F$4/100) -> 0 | AG2: =T2/(concentrate_grade!$F$6/100) -> 0 | AQ2: =Q2*prices!$C$4 -> 0 | AR2: =R2*prices!$C$11 -> 0 | AS2: =S2*prices!$C$3 -> 0 | AT2: =T2*prices!$C$8 -> 0 | AU2: =U2*prices!$C$2 -> 0 | AV2: =V2*prices!$C$7 -> 0 | AW2: =W2*prices!$C$13 -> 0 | AX2: =X2*prices!$C$6 -> 0 | AY2: =Y2*prices!$C$5 -> 0 | AZ2: =Z2*prices!$C$9 -> 0 | BA2: =AB2*prices!$C$12 -> 0 | BB2: =AC2*prices!$C$14 -> 0 | BC2: =SUM(AQ2:AZ2) -> 0 | BD2: =AQ2/BC2 -> #DIV/0! | BE2: =AS2/BC2 -> #DIV/0! | BF2: Fe
A3: BC-MAIN-857b7b89 | C3: Brucejack | E3: British Columbia | F3: mining | G3: Underground, concentrator | I3: NPRI+GHG+Water | J3: Energy | L3: Gold, silver | M3: Au | N3: =prod_table_raw!N13 -> 166000 | O3: =SUM(AD3:AP3) -> 0 | P3: =N3-O3 -> 166000 | Q3: =prod_table_raw!N14 -> 0.9020015 | AF3: =S3/(concentrate_grade!$F$4/100) -> 0 | AG3: =T3/(concentrate_grade!$F$6/100) -> 0 | AQ3: =Q3*prices!$C$4 -> 46717.485 | AR3: =R3*prices!$C$11 -> 0 | AS3: =S3*prices!$C$3 -> 0 | AT3: =T3*prices!$C$8 -> 0 | AU3: =U3*prices!$C$2 -> 0 | AV3: =V3*prices!$C$7 -> 0 | AW3: =W3*prices!$C$13 -> 0 | AX3: =X3*prices!$C$6 -> 0 | AY3: =Y3*prices!$C$5 -> 0 | AZ3: =Z3*prices!$C$9 -> 0 | BA3: =AB3*prices!$C$12 -> 0 | BB3: =AC3*prices!$C$14 -> 0 | BC3: =SUM(AQ3:AZ3) -> 46717.485 | BD3: =AQ3/BC3 -> 1 | BE3: =AS3/BC3 -> 0 | BF3: Au
A4: QC-MAIN-de3d8b7b | C4: Canadian Electrolytic Zinc Limited (CEZinc) | E4: Quebec | F4: manufacturing | G4: Refinery | L4: Lead, zinc | M4: Zn (Pb) | O4: =SUM(AD4:AP4) -> 0 | P4: =N4-O4 -> 0 | W4: =prod_table_raw!N16 -> 752600 | X4: =prod_table_raw!N15 -> 244600 | AF4: =S4/(concentrate_grade!$F$4/100) -> 0 | AG4: =T4/(concentrate_grade!$F$6/100) -> 0 | AQ4: =Q4*prices!$C$4 -> 0 | AR4: =R4*prices!$C$11 -> 0 | AS4: =S4*prices!$C$3 -> 0 | AT4: =T4*prices!$C$8 -> 0 | AU4: =U4*prices!$C$2 -> 0 | AV4: =V4*prices!$C$7 -> 0 | AW4: =W4*prices!$C$13 -> 1941192.1 | AX4: =X4*prices!$C$6 -> 504507.94 | AY4: =Y4*prices!$C$5 -> 0 | AZ4: =Z4*prices!$C$9 -> 0 | BA4: =AB4*prices!$C$12 -> 0 | BB4: =AC4*prices!$C$14 -> 0 | BC4: =SUM(AQ4:AZ4) -> 2445700.1 | BD4: =AQ4/BC4 -> 0 | BE4: =AS4/BC4 -> 0 | BF4: Zn (Pb)
A5: QC-MAIN-e7e6a960 | C5: Canadian Malartic | E5: Quebec | F5: mining | G5: Open-pit, concentrator | H5: Mixed free-miling-refactory | I5: NPRI+GHG+Land | J5: Energy | L5: Gold, silver | M5: Au (Ag) | N5: =prod_table_raw!N17 -> 17332900 | O5: =SUM(AD5:AP5) -> 0 | P5: =N5-O5 -> 17332900 | Q5: =prod_table_raw!N18 -> 18.785114 | R5: =prod_table_raw!N19 -> 9.6731885 | AF5: =S5/(concentrate_grade!$F$4/100) -> 0 | AG5: =T5/(concentrate_grade!$F$6/100) -> 0 | AQ5: =Q5*prices!$C$4 -> 972939.96 | AR5: =R5*prices!$C$11 -> 6501.6402 | AS5: =S5*prices!$C$3 -> 0 | AT5: =T5*prices!$C$8 -> 0 | AU5: =U5*prices!$C$2 -> 0 | AV5: =V5*prices!$C$7 -> 0 | AW5: =W5*prices!$C$13 -> 0 | AX5: =X5*prices!$C$6 -> 0 | AY5: =Y5*prices!$C$5 -> 0 | AZ5: =Z5*prices!$C$9 -> 0 | BA5: =AB5*prices!$C$12 -> 0 | BB5: =AC5*prices!$C$14 -> 0 | BC5: =SUM(AQ5:AZ5) -> 979441.6 | BD5: =AQ5/BC5 -> 0.99336189 | BE5: =AS5/BC5 -> 0 | BF5: Au (Ag)
A6: NL-MAIN-dd723db4 | C6: Carol Lake | E6: Newfoundland and Labrador | F6: mining | G6: Open-pit, concentrator | H6: Fe concentrator + pellet plant | I6: NPRI+GHG+Land | J6: Energy | L6: Iron | M6: Fe | N6: =prod_table_raw!N21 -> 16478000 | O6: =SUM(AD6:AP6) -> 0 | P6: =N6-O6 -> 16478000 | AF6: =S6/(concentrate_grade!$F$4/100) -> 0 | AG6: =T6/(concentrate_grade!$F$6/100) -> 0 | AQ6: =Q6*prices!$C$4 -> 0 | AR6: =R6*prices!$C$11 -> 0 | AS6: =S6*prices!$C$3 -> 0 | AT6: =T6*prices!$C$8 -> 0 | AU6: =U6*prices!$C$2 -> 0 | AV6: =V6*prices!$C$7 -> 0 | AW6: =W6*prices!$C$13 -> 0 | AX6: =X6*prices!$C$6 -> 0 | AY6: =Y6*prices!$C$5 -> 0 | AZ6: =Z6*prices!$C$9 -> 0 | BA6: =AB6*prices!$C$12 -> 0 | BB6: =AC6*prices!$C$14 -> 0 | BC6: =SUM(AQ6:AZ6) -> 0 | BD6: =AQ6/BC6 -> #DIV/0! | BE6: =AS6/BC6 -> #DIV/0! | BF6: Fe
A7: QC-MAIN-b86f7d07 | C7: Casa Berardi | E7: Quebec | F7: mining | G7: Open-pit, underground, concentrator | H7: Free-miling | I7: NPRI+GHG+Land | J7: Energy | L7: Gold, silver | M7: Au | N7: =prod_table_raw!N24 -> 1361450 | O7: =SUM(AD7:AP7) -> 0 | P7: =N7-O7 -> 1361450 | Q7: =prod_table_raw!N22 -> 2.6935631 | R7: =prod_table_raw!N23 -> 0.7527047 | AF7: =S7/(concentrate_grade!$F$4/100) -> 0 | AG7: =T7/(concentrate_grade!$F$6/100) -> 0 | AQ7: =Q7*prices!$C$4 -> 139508.08 | AR7: =R7*prices!$C$11 -> 505.91541 | AS7: =S7*prices!$C$3 -> 0 | AT7: =T7*prices!$C$8 -> 0 | AU7: =U7*prices!$C$2 -> 0 | AV7: =V7*prices!$C$7 -> 0 | AW7: =W7*prices!$C$13 -> 0 | AX7: =X7*prices!$C$6 -> 0 | AY7: =Y7*prices!$C$5 -> 0 | AZ7: =Z7*prices!$C$9 -> 0 | BA7: =AB7*prices!$C$12 -> 0 | BB7: =AC7*prices!$C$14 -> 0 | BC7: =SUM(AQ7:AZ7) -> 140013.99 | BD7: =AQ7/BC7 -> 0.99638668 | BE7: =AS7/BC7 -> 0 | BF7: Au
A8: SK-MAIN-91cf5448 | C8: Cigar Lake | E8: Saskatchewan | F8: mining | G8: Underground | H8: High-grade U acid-leach mills | I8: NPRI+GHG+Land | L8: Uranium | M8: U | N8: =prod_table_raw!#REF! -> #REF! | O8: =SUM(AD8:AP8) -> 0 | P8: =N8-O8 -> #REF! | AB8: =prod_table_raw!#REF! -> #REF! | AF8: =S8/(concentrate_grade!$F$4/100) -> 0 | AG8: =T8/(concentrate_grade!$F$6/100) -> 0 | AQ8: =Q8*prices!$C$4 -> 0 | AR8: =R8*prices!$C$11 -> 0 | AS8: =S8*prices!$C$3 -> 0 | AT8: =T8*prices!$C$8 -> 0 | AU8: =U8*prices!$C$2 -> 0 | AV8: =V8*prices!$C$7 -> 0 | AW8: =W8*prices!$C$13 -> 0 | AX8: =X8*prices!$C$6 -> 0 | AY8: =Y8*prices!$C$5 -> 0 | AZ8: =Z8*prices!$C$9 -> 0 | BA8: =AB8*prices!$C$12 -> #REF! | BB8: =AC8*prices!$C$14 -> 0 | BC8: =SUM(AQ8:AZ8) -> 0 | BD8: =AQ8/BC8 -> #DIV/0! | BE8: =AS8/BC8 -> #DIV/0! | BF8: U
A9: ON-MAIN-f080c409 | B9: GRP-dc07540b | C9: Copper Cliff Complex (mine) | D9: Sudbury Operation | E9: Ontario | F9: mining | G9: Underground | H9: Ni-Cu Porphyry sulfide, flotation-based | I9: NPRI+Land | L9: Nickel, copper, platinum group metals, gold, silver, cobalt, selenium, tellurium | M9: Ni+Cu | N9: =prod_table_raw!N30 -> 748000 | O9: =SUM(AD9:AP9) -> 88353.75 | P9: =N9-O9 -> 659646.25 | S9: =prod_table_raw!N29 -> 10098 | T9: =prod_table_raw!N28 -> 8751 | AF9: =S9/(concentrate_grade!$F$4/100) -> 33660 | AG9: =T9/(concentrate_grade!$F$6/100) -> 54693.75 | AQ9: =Q9*prices!$C$4 -> 0 | AR9: =R9*prices!$C$11 -> 0 | AS9: =S9*prices!$C$3 -> 69676.2 | AT9: =T9*prices!$C$8 -> 136428.09 | AU9: =U9*prices!$C$2 -> 0 | AV9: =V9*prices!$C$7 -> 0 | AW9: =W9*prices!$C$13 -> 0 | AX9: =X9*prices!$C$6 -> 0 | AY9: =Y9*prices!$C$5 -> 0 | AZ9: =Z9*prices!$C$9 -> 0 | BA9: =AB9*prices!$C$12 -> 0 | BB9: =AC9*prices!$C$14 -> 0 | BC9: =SUM(AQ9:AZ9) -> 206104.29 | BD9: =AQ9/BC9 -> 0 | BE9: =AS9/BC9 -> 0.33806283 | BF9: Ni+Cu
A10: ON-MAIN-63b394c3 | B10: GRP-dc07540b | C10: Copper Cliff Complex (refinery) | D10: Sudbury Operation | E10: Ontario | F10: manufacturing | G10: Smelter, refinery, plant | H10: Cu-Ni smelter and refinery | I10: NPRI+GHG | L10: Nickel (oxide sinter, pellets, powder, sulfide), copper cathodes, gold, silver, selenium cake, tellurium dioxide cake, platinum group metals (in residues), liquid sulfur dioxide, sulfuric acid | M10: Ni+Cu | O10: =SUM(AD10:AP10) -> 431750 | P10: =N10-O10 -> -431750 | S10: =prod_table_raw!N31 -> 57900 | T10: =prod_table_raw!N32 -> 38200 | AF10: =S10/(concentrate_grade!$F$4/100) -> 193000 | AG10: =T10/(concentrate_grade!$F$6/100) -> 238750 | AQ10: =Q10*prices!$C$4 -> 0 | AR10: =R10*prices!$C$11 -> 0 | AS10: =S10*prices!$C$3 -> 399510 | AT10: =T10*prices!$C$8 -> 595538 | AU10: =U10*prices!$C$2 -> 0 | AV10: =V10*prices!$C$7 -> 0 | AW10: =W10*prices!$C$13 -> 0 | AX10: =X10*prices!$C$6 -> 0 | AY10: =Y10*prices!$C$5 -> 0 | AZ10: =Z10*prices!$C$9 -> 0 | BA10: =AB10*prices!$C$12 -> 0 | BB10: =AC10*prices!$C$14 -> 0 | BC10: =SUM(AQ10:AZ10) -> 995048 | BD10: =AQ10/BC10 -> 0 | BE10: =AS10/BC10 -> 0.40149822 | BF10: Ni+Cu
A11: BC-MAIN-599152a0 | C11: Copper Mountain | E11: British Columbia | F11: mining | G11: Open-pit, concentrator | H11: Cu-Au Porphyry sulfide, flotation-based | I11: NPRI+GHG+Land | J11: Energy | L11: Copper, gold, silver | M11: Cu (Au, Ag) | N11: =prod_table_raw!N36 -> 6862152 | O11: =SUM(AD11:AP11) -> 63500 | P11: =N11-O11 -> 6798652 | Q11: =prod_table_raw!N35 -> 0.27520377 | R11: =prod_table_raw!N38 -> 6.7893342 | S11: =prod_table_raw!N39 -> 19050 | AF11: =S11/(concentrate_grade!$F$4/100) -> 63500 | AG11: =T11/(concentrate_grade!$F$6/100) -> 0 | AQ11: =Q11*prices!$C$4 -> 14253.666 | AR11: =R11*prices!$C$11 -> 4563.3152 | AS11: =S11*prices!$C$3 -> 131445 | AT11: =T11*prices!$C$8 -> 0 | AU11: =U11*prices!$C$2 -> 0 | AV11: =V11*prices!$C$7 -> 0 | AW11: =W11*prices!$C$13 -> 0 | AX11: =X11*prices!$C$6 -> 0 | AY11: =Y11*prices!$C$5 -> 0 | AZ11: =Z11*prices!$C$9 -> 0 | BA11: =AB11*prices!$C$12 -> 0 | BB11: =AC11*prices!$C$14 -> 0 | BC11: =SUM(AQ11:AZ11) -> 150261.98 | BD11: =AQ11/BC11 -> 0.094858765 | BE11: =AS11/BC11 -> 0.87477217 | BF11: Cu (Au, Ag)
A12: ON-MAIN-52224e1e | B12: GRP-dc07540b | C12: Creighton | D12: Sudbury Operation | E12: Ontario | F12: mining | G12: Underground | H12: Ni-Cu Porphyry sulfide, flotation-based | I12: NPRI+land | L12: Nickel, copper, platinum group metals, gold, silver, cobalt, selenium, tellurium | M12: Ni+Cu | N12: =prod_table_raw!N44 -> 433000 | O12: =SUM(AD12:AP12) -> 102220 | P12: =N12-O12 -> 330780 | S12: =prod_table_raw!N43 -> 9396 | T12: =prod_table_raw!N42 -> 11344 | AF12: =S12/(concentrate_grade!$F$4/100) -> 31320 | AG12: =T12/(concentrate_grade!$F$6/100) -> 70900 | AQ12: =Q12*prices!$C$4 -> 0 | AR12: =R12*prices!$C$11 -> 0 | AS12: =S12*prices!$C$3 -> 64832.4 | AT12: =T12*prices!$C$8 -> 176852.96 | AU12: =U12*prices!$C$2 -> 0 | AV12: =V12*prices!$C$7 -> 0 | AW12: =W12*prices!$C$13 -> 0 | AX12: =X12*prices!$C$6 -> 0 | AY12: =Y12*prices!$C$5 -> 0 | AZ12: =Z12*prices!$C$9 -> 0 | BA12: =AB12*prices!$C$12 -> 0 | BB12: =AC12*prices!$C$14 -> 0 | BC12: =SUM(AQ12:AZ12) -> 241685.36 | BD12: =AQ12/BC12 -> 0 | BE12: =AS12/BC12 -> 0.26825125 | BF12: Ni+Cu
A13: ON-MAIN-aeafbb59 | C13: Detour Lake | E13: Ontario | F13: mining | G13: Open-pit, concentrator | H13: Free-miling | I13: NPRI+GHG+Land | J13: Energy | L13: Gold | M13: Au (Ag) | N13: =prod_table_raw!N48 -> 25434854 | O13: =SUM(AD13:AP13) -> 0 | P13: =N13-O13 -> 25434854 | Q13: =prod_table_raw!N49 -> 21.070942 | R13: =prod_table_raw!N50 -> 2.4571765 | AF13: =S13/(concentrate_grade!$F$4/100) -> 0 | AG13: =T13/(concentrate_grade!$F$6/100) -> 0 | AQ13: =Q13*prices!$C$4 -> 1091330.1 | AR13: =R13*prices!$C$11 -> 1651.542 | AS13: =S13*prices!$C$3 -> 0 | AT13: =T13*prices!$C$8 -> 0 | AU13: =U13*prices!$C$2 -> 0 | AV13: =V13*prices!$C$7 -> 0 | AW13: =W13*prices!$C$13 -> 0 | AX13: =X13*prices!$C$6 -> 0 | AY13: =Y13*prices!$C$5 -> 0 | AZ13: =Z13*prices!$C$9 -> 0 | BA13: =AB13*prices!$C$12 -> 0 | BB13: =AC13*prices!$C$14 -> 0 | BC13: =SUM(AQ13:AZ13) -> 1092981.7 | BD13: =AQ13/BC13 -> 0.99848896 | BE13: =AS13/BC13 -> 0 | BF13: Au (Ag)
A14: ON-MAIN-cb85213a | C14: Eagle River | E14: Ontario | F14: mining | G14: Underground, concentrator | H14: Free-miling | I14: NPRI+GHG | J14: Energy | L14: Gold | M14: Au | N14: =prod_table_raw!N55 -> 222627 | O14: =SUM(AD14:AP14) -> 0 | P14: =N14-O14 -> 222627 | Q14: =prod_table_raw!N55 -> 222627 | AF14: =S14/(concentrate_grade!$F$4/100) -> 0 | AG14: =T14/(concentrate_grade!$F$6/100) -> 0 | AQ14: =Q14*prices!$C$4 -> 1.153055e+10 | AR14: =R14*prices!$C$11 -> 0 | AS14: =S14*prices!$C$3 -> 0 | AT14: =T14*prices!$C$8 -> 0 | AU14: =U14*prices!$C$2 -> 0 | AV14: =V14*prices!$C$7 -> 0 | AW14: =W14*prices!$C$13 -> 0 | AX14: =X14*prices!$C$6 -> 0 | AY14: =Y14*prices!$C$5 -> 0 | AZ14: =Z14*prices!$C$9 -> 0 | BA14: =AB14*prices!$C$12 -> 0 | BB14: =AC14*prices!$C$14 -> 0 | BC14: =SUM(AQ14:AZ14) -> 1.153055e+10 | BD14: =AQ14/BC14 -> 1 | BE14: =AS14/BC14 -> 0 | BF14: Au
A15: QC-MAIN-6dc537e6 | C15: Éléonore | E15: Quebec | F15: mining | G15: Underground, concentrator | H15: Free-miling | I15: NPRI+GHG | J15: Energy and materials | L15: Gold, silver | M15: Au (Ag) | N15: =prod_table_raw!N62 -> 1661000 | O15: =SUM(AD15:AP15) -> 0 | P15: =N15-O15 -> 1661000 | Q15: =prod_table_raw!N59 -> 7.216012 | R15: =prod_table_raw!N60 -> 0.36810992 | AF15: =S15/(concentrate_grade!$F$4/100) -> 0 | AG15: =T15/(concentrate_grade!$F$6/100) -> 0 | AQ15: =Q15*prices!$C$4 -> 373739.88 | AR15: =R15*prices!$C$11 -> 247.41772 | AS15: =S15*prices!$C$3 -> 0 | AT15: =T15*prices!$C$8 -> 0 | AU15: =U15*prices!$C$2 -> 0 | AV15: =V15*prices!$C$7 -> 0 | AW15: =W15*prices!$C$13 -> 0 | AX15: =X15*prices!$C$6 -> 0 | AY15: =Y15*prices!$C$5 -> 0 | AZ15: =Z15*prices!$C$9 -> 0 | BA15: =AB15*prices!$C$12 -> 0 | BB15: =AC15*prices!$C$14 -> 0 | BC15: =SUM(AQ15:AZ15) -> 373987.3 | BD15: =AQ15/BC15 -> 0.99933843 | BE15: =AS15/BC15 -> 0 | BF15: Au (Ag)
A16: BC-MAIN-4724f4ba | C16: Elk | E16: British Columbia | F16: mining | G16: Open-pit | H16: Free-miling | I16: Land | L16: Gold | M16: Au | N16: =prod_table_raw!N64 -> 33245 | O16: =SUM(AD16:AP16) -> 0 | P16: =N16-O16 -> 33245 | Q16: =prod_table_raw!N65 -> 0.12180131 | AF16: =S16/(concentrate_grade!$F$4/100) -> 0 | AG16: =T16/(concentrate_grade!$F$6/100) -> 0 | AQ16: =Q16*prices!$C$4 -> 6308.4715 | AR16: =R16*prices!$C$11 -> 0 | AS16: =S16*prices!$C$3 -> 0 | AT16: =T16*prices!$C$8 -> 0 | AU16: =U16*prices!$C$2 -> 0 | AV16: =V16*prices!$C$7 -> 0 | AW16: =W16*prices!$C$13 -> 0 | AX16: =X16*prices!$C$6 -> 0 | AY16: =Y16*prices!$C$5 -> 0 | AZ16: =Z16*prices!$C$9 -> 0 | BA16: =AB16*prices!$C$12 -> 0 | BB16: =AC16*prices!$C$14 -> 0 | BC16: =SUM(AQ16:AZ16) -> 6308.4715 | BD16: =AQ16/BC16 -> 1 | BE16: =AS16/BC16 -> 0 | BF16: Au
A17: ON-MAIN-4e0734b5 | C17: Fox Complex | E17: Ontario | F17: mining | G17: Open-pit, underground, concentrator | H17: Free-miling | I17: NPRI+land | L17: Gold | M17: Au | N17: =prod_table_raw!N70 -> 457000 | O17: =SUM(AD17:AP17) -> 0 | P17: =N17-O17 -> 457000 | Q17: =prod_table_raw!N71 -> 1.3809954 | R17: =prod_table_raw!N72 -> 0.0435449 | AF17: =S17/(concentrate_grade!$F$4/100) -> 0 | AG17: =T17/(concentrate_grade!$F$6/100) -> 0 | AQ17: =Q17*prices!$C$4 -> 71526.081 | AR17: =R17*prices!$C$11 -> 29.267834 | AS17: =S17*prices!$C$3 -> 0 | AT17: =T17*prices!$C$8 -> 0 | AU17: =U17*prices!$C$2 -> 0 | AV17: =V17*prices!$C$7 -> 0 | AW17: =W17*prices!$C$13 -> 0 | AX17: =X17*prices!$C$6 -> 0 | AY17: =Y17*prices!$C$5 -> 0 | AZ17: =Z17*prices!$C$9 -> 0 | BA17: =AB17*prices!$C$12 -> 0 | BB17: =AC17*prices!$C$14 -> 0 | BC17: =SUM(AQ17:AZ17) -> 71555.349 | BD17: =AQ17/BC17 -> 0.99959098 | BE17: =AS17/BC17 -> 0 | BF17: Au
A18: ON-MAIN-206041d1 | B18: GRP-de097f20 | C18: Fraser | D18: Integrated Nickel Operations | E18: Ontario | F18: mining | G18: Underground | H18: Ni-Cu Porphyry sulfide, flotation-based | I18: Land | L18: Nickel, copper, platinum group metals, gold, cobalt, silver | M18: Ni+Cu | N18: =prod_table_raw!N73 -> 553033 | O18: =SUM(AD18:AP18) -> 0 | P18: =N18-O18 -> 553033 | AF18: =S18/(concentrate_grade!$F$4/100) -> 0 | AG18: =T18/(concentrate_grade!$F$6/100) -> 0 | AQ18: =Q18*prices!$C$4 -> 0 | AR18: =R18*prices!$C$11 -> 0 | AS18: =S18*prices!$C$3 -> 0 | AT18: =T18*prices!$C$8 -> 0 | AU18: =U18*prices!$C$2 -> 0 | AV18: =V18*prices!$C$7 -> 0 | AW18: =W18*prices!$C$13 -> 0 | AX18: =X18*prices!$C$6 -> 0 | AY18: =Y18*prices!$C$5 -> 0 | AZ18: =Z18*prices!$C$9 -> 0 | BA18: =AB18*prices!$C$12 -> 0 | BB18: =AC18*prices!$C$14 -> 0 | BC18: =SUM(AQ18:AZ18) -> 0 | BD18: =AQ18/BC18 -> #DIV/0! | BE18: =AS18/BC18 -> #DIV/0! | BF18: Ni+Cu
A19: ON-MAIN-48fe2205 | B19: GRP-dc07540b | C19: Garson | D19: Sudbury Operation | E19: Ontario | F19: mining | G19: Underground | H19: Ni-Cu Porphyry sulfide, flotation-based | I19: NPRI+Land | L19: Nickel, copper, platinum group metals, gold, silver, cobalt, selenium, tellurium | M19: Ni+Cu | N19: =prod_table_raw!N76 -> 616000 | O19: =SUM(AD19:AP19) -> 74505.833 | P19: =N19-O19 -> 541494.17 | S19: =prod_table_raw!N75 -> 7453 | T19: =prod_table_raw!N74 -> 7946 | AF19: =S19/(concentrate_grade!$F$4/100) -> 24843.333 | AG19: =T19/(concentrate_grade!$F$6/100) -> 49662.5 | AQ19: =Q19*prices!$C$4 -> 0 | AR19: =R19*prices!$C$11 -> 0 | AS19: =S19*prices!$C$3 -> 51425.7 | AT19: =T19*prices!$C$8 -> 123878.14 | AU19: =U19*prices!$C$2 -> 0 | AV19: =V19*prices!$C$7 -> 0 | AW19: =W19*prices!$C$13 -> 0 | AX19: =X19*prices!$C$6 -> 0 | AY19: =Y19*prices!$C$5 -> 0 | AZ19: =Z19*prices!$C$9 -> 0 | BA19: =AB19*prices!$C$12 -> 0 | BB19: =AC19*prices!$C$14 -> 0 | BC19: =SUM(AQ19:AZ19) -> 175303.84 | BD19: =AQ19/BC19 -> 0 | BE19: =AS19/BC19 -> 0.29335182 | BF19: Ni+Cu
A20: BC-MAIN-6b4800fe | C20: Gibraltar | E20: British Columbia | F20: mining | G20: Open-pit, concentrator | H20: Cu-Mo Porphyry sulfide, flotation-based | I20: NPRI+GHG+Water+Land | J20: Energy | L20: Copper, molybdenum, silver | M20: Cu (Mo) | N20: =prod_table_raw!N80 -> 30000000 | O20: =SUM(AD20:AP20) -> 185367.93 | P20: =N20-O20 -> 29814632 | S20: =prod_table_raw!N82 -> 55610.379 | V20: =prod_table_raw!N81 -> 545.21758 | AF20: =S20/(concentrate_grade!$F$4/100) -> 185367.93 | AG20: =T20/(concentrate_grade!$F$6/100) -> 0 | AQ20: =Q20*prices!$C$4 -> 0 | AR20: =R20*prices!$C$11 -> 0 | AS20: =S20*prices!$C$3 -> 383711.62 | AT20: =T20*prices!$C$8 -> 0 | AU20: =U20*prices!$C$2 -> 0 | AV20: =V20*prices!$C$7 -> 15942.162 | AW20: =W20*prices!$C$13 -> 0 | AX20: =X20*prices!$C$6 -> 0 | AY20: =Y20*prices!$C$5 -> 0 | AZ20: =Z20*prices!$C$9 -> 0 | BA20: =AB20*prices!$C$12 -> 0 | BB20: =AC20*prices!$C$14 -> 0 | BC20: =SUM(AQ20:AZ20) -> 399653.78 | BD20: =AQ20/BC20 -> 0 | BE20: =AS20/BC20 -> 0.96011007 | BF20: Cu (Mo)
A21: QC-MAIN-c0660aec | C21: Goldex | E21: Quebec | F21: mining | G21: Underground, concentrator | H21: Free-miling | I21: NPRI+GHG+Land | J21: Energy | L21: Gold, silver | M21: Au (Cu, Ag) | N21: =prod_table_raw!N86 -> 2886927.3 | O21: =SUM(AD21:AP21) -> 130.12253 | P21: =N21-O21 -> 2886797.2 | Q21: =prod_table_raw!N87 -> 4.3850513 | S21: =prod_table_raw!N85 -> 39.036758 | AF21: =S21/(concentrate_grade!$F$4/100) -> 130.12253 | AG21: =T21/(concentrate_grade!$F$6/100) -> 0 | AQ21: =Q21*prices!$C$4 -> 227115.55 | AR21: =R21*prices!$C$11 -> 0 | AS21: =S21*prices!$C$3 -> 269.35363 | AT21: =T21*prices!$C$8 -> 0 | AU21: =U21*prices!$C$2 -> 0 | AV21: =V21*prices!$C$7 -> 0 | AW21: =W21*prices!$C$13 -> 0 | AX21: =X21*prices!$C$6 -> 0 | AY21: =Y21*prices!$C$5 -> 0 | AZ21: =Z21*prices!$C$9 -> 0 | BA21: =AB21*prices!$C$12 -> 0 | BB21: =AC21*prices!$C$14 -> 0 | BC21: =SUM(AQ21:AZ21) -> 227384.91 | BD21: =AQ21/BC21 -> 0.99881543 | BE21: =AS21/BC21 -> 0.0011845713 | BF21: Au (Cu, Ag)
A22: ON-MAIN-6e9be24e | C22: Hemlo (Williams) | E22: Ontario | F22: mining | G22: Open-pit, underground, concentrator | I22: NPRI+GHG+Land | J22: Energy | L22: Gold | M22: Au | N22: =prod_table_raw!N91 -> 1266009 | O22: =SUM(AD22:AP22) -> 0 | P22: =N22-O22 -> 1266009 | Q22: =prod_table_raw!N91 -> 1266009 | AF22: =S22/(concentrate_grade!$F$4/100) -> 0 | AG22: =T22/(concentrate_grade!$F$6/100) -> 0 | AQ22: =Q22*prices!$C$4 -> 6.5570575e+10 | AR22: =R22*prices!$C$11 -> 0 | AS22: =S22*prices!$C$3 -> 0 | AT22: =T22*prices!$C$8 -> 0 | AU22: =U22*prices!$C$2 -> 0 | AV22: =V22*prices!$C$7 -> 0 | AW22: =W22*prices!$C$13 -> 0 | AX22: =X22*prices!$C$6 -> 0 | AY22: =Y22*prices!$C$5 -> 0 | AZ22: =Z22*prices!$C$9 -> 0 | BA22: =AB22*prices!$C$12 -> 0 | BB22: =AC22*prices!$C$14 -> 0 | BC22: =SUM(AQ22:AZ22) -> 6.5570575e+10 | BD22: =AQ22/BC22 -> 1 | BE22: =AS22/BC22 -> 0 | BF22: Au
A23: BC-MAIN-bf503b6b | C23: Highland Valley | E23: British Columbia | F23: mining | G23: Open-pit, concentrator | H23: Cu-Mo Porphyry sulfide, flotation-based | I23: NPRI+GHG+Water+Land | L23: Copper, silver, molybdenum | M23: Cu (Mo) | N23: =prod_table_raw!N93 -> 17408000 | O23: =SUM(AD23:AP23) -> 341333.33 | P23: =N23-O23 -> 17066667 | S23: =prod_table_raw!N95 -> 102400 | V23: =prod_table_raw!N94 -> 900 | AF23: =S23/(concentrate_grade!$F$4/100) -> 341333.33 | AG23: =T23/(concentrate_grade!$F$6/100) -> 0 | AQ23: =Q23*prices!$C$4 -> 0 | AR23: =R23*prices!$C$11 -> 0 | AS23: =S23*prices!$C$3 -> 706560 | AT23: =T23*prices!$C$8 -> 0 | AU23: =U23*prices!$C$2 -> 0 | AV23: =V23*prices!$C$7 -> 26316 | AW23: =W23*prices!$C$13 -> 0 | AX23: =X23*prices!$C$6 -> 0 | AY23: =Y23*prices!$C$5 -> 0 | AZ23: =Z23*prices!$C$9 -> 0 | BA23: =AB23*prices!$C$12 -> 0 | BB23: =AC23*prices!$C$14 -> 0 | BC23: =SUM(AQ23:AZ23) -> 732876 | BD23: =AQ23/BC23 -> 0 | BE23: =AS23/BC23 -> 0.96409215 | BF23: Cu (Mo)
A24: QC-MAIN-30c1828c | B24: GRP-b48ec279 | C24: Horne | D24: CCR | E24: Quebec | F24: manufacturing | G24: Smelter | I24: NPRI+GHG | L24: Copper anodes, precious metals, sulfuric acid | M24: Cu | O24: =SUM(AD24:AP24) -> 0 | P24: =N24-O24 -> 0 | AF24: =S24/(concentrate_grade!$F$4/100) -> 0 | AG24: =T24/(concentrate_grade!$F$6/100) -> 0 | AQ24: =Q24*prices!$C$4 -> 0 | AR24: =R24*prices!$C$11 -> 0 | AS24: =S24*prices!$C$3 -> 0 | AT24: =T24*prices!$C$8 -> 0 | AU24: =U24*prices!$C$2 -> 0 | AV24: =V24*prices!$C$7 -> 0 | AW24: =W24*prices!$C$13 -> 0 | AX24: =X24*prices!$C$6 -> 0 | AY24: =Y24*prices!$C$5 -> 0 | AZ24: =Z24*prices!$C$9 -> 0 | BA24: =AB24*prices!$C$12 -> 0 | BB24: =AC24*prices!$C$14 -> 0 | BC24: =SUM(AQ24:AZ24) -> 0 | BD24: =AQ24/BC24 -> #DIV/0! | BE24: =AS24/BC24 -> #DIV/0! | BF24: Cu
A25: ON-MAIN-687b8c8d | C25: Island | E25: Ontario | F25: mining | G25: Underground, concentrator | H25: Free-miling | I25: NPRI+GHG | J25: Energy | L25: Gold | M25: Au | N25: =prod_table_raw!N105 -> 439008 | O25: =SUM(AD25:AP25) -> 0 | P25: =N25-O25 -> 439008 | Q25: =prod_table_raw!N103 -> 4.0869999 | AF25: =S25/(concentrate_grade!$F$4/100) -> 0 | AG25: =T25/(concentrate_grade!$F$6/100) -> 0 | AQ25: =Q25*prices!$C$4 -> 211678.54 | AR25: =R25*prices!$C$11 -> 0 | AS25: =S25*prices!$C$3 -> 0 | AT25: =T25*prices!$C$8 -> 0 | AU25: =U25*prices!$C$2 -> 0 | AV25: =V25*prices!$C$7 -> 0 | AW25: =W25*prices!$C$13 -> 0 | AX25: =X25*prices!$C$6 -> 0 | AY25: =Y25*prices!$C$5 -> 0 | AZ25: =Z25*prices!$C$9 -> 0 | BA25: =AB25*prices!$C$12 -> 0 | BB25: =AC25*prices!$C$14 -> 0 | BC25: =SUM(AQ25:AZ25) -> 211678.54 | BD25: =AQ25/BC25 -> 1 | BE25: =AS25/BC25 -> 0 | BF25: Au
A26: YT-MAIN-44857446 | C26: Keno Hill Silver District | E26: Yukon | F26: mining | G26: Underground, concentrator | H26: High-grade polymetallic Pb-Zn-Ag | J26: Energy | L26: Silver, zinc, lead | M26: Ag (Zn) | N26: =prod_table_raw!N110 -> 127307 | O26: =SUM(AD26:AP26) -> 0 | P26: =N26-O26 -> 127307 | R26: =prod_table_raw!N109 -> 46.735404 | W26: =prod_table_raw!N112 -> 1339 | X26: =prod_table_raw!N111 -> 1225 | AF26: =S26/(concentrate_grade!$F$4/100) -> 0 | AG26: =T26/(concentrate_grade!$F$6/100) -> 0 | AQ26: =Q26*prices!$C$4 -> 0 | AR26: =R26*prices!$C$11 -> 31412.267 | AS26: =S26*prices!$C$3 -> 0 | AT26: =T26*prices!$C$8 -> 0 | AU26: =U26*prices!$C$2 -> 0 | AV26: =V26*prices!$C$7 -> 0 | AW26: =W26*prices!$C$13 -> 3453.7022 | AX26: =X26*prices!$C$6 -> 2526.6649 | AY26: =Y26*prices!$C$5 -> 0 | AZ26: =Z26*prices!$C$9 -> 0 | BA26: =AB26*prices!$C$12 -> 0 | BB26: =AC26*prices!$C$14 -> 0 | BC26: =SUM(AQ26:AZ26) -> 37392.634 | BD26: =AQ26/BC26 -> 0 | BE26: =AS26/BC26 -> 0 | BF26: Ag (Zn)
B27: GRP-21eee27d | C27: Key Lake + McArthur River | E27: Saskatchewan | F27: mining | G27: Underground, Concentrator | H27: High-grade U acid-leach mills | L27: Uranium | M27: U | N27: =prod_table_raw!N153 -> 98408.871 | O27: =SUM(AD27:AP27) -> 0 | P27: =N27-O27 -> 98408.871 | AB27: =prod_table_raw!N152 -> 6123.492 | AF27: =S27/(concentrate_grade!$F$4/100) -> 0 | AG27: =T27/(concentrate_grade!$F$6/100) -> 0 | AQ27: =Q27*prices!$C$4 -> 0 | AR27: =R27*prices!$C$11 -> 0 | AS27: =S27*prices!$C$3 -> 0 | AT27: =T27*prices!$C$8 -> 0 | AU27: =U27*prices!$C$2 -> 0 | AV27: =V27*prices!$C$7 -> 0 | AW27: =W27*prices!$C$13 -> 0 | AX27: =X27*prices!$C$6 -> 0 | AY27: =Y27*prices!$C$5 -> 0 | AZ27: =Z27*prices!$C$9 -> 0 | BA27: =AB27*prices!$C$12 -> 1051.4036 | BB27: =AC27*prices!$C$14 -> 0 | BC27: =SUM(AQ27:AZ27) -> 0 | BD27: =AQ27/BC27 -> #DIV/0! | BE27: =AS27/BC27 -> #DIV/0! | BF27: U
A28: ON-MAIN-f8313ebd | C28: Kidd Creek | E28: Ontario | F28: mining | G28: Underground, concentrator | H28: Cu-Zn Porphyry sulfide, flotation-based | I28: NPRI+Land | L28: Copper, zinc, silver, selenium, indium | M28: Cu (Zn, Ag) | N28: =prod_table_raw!N116 -> 1340000 | O28: =SUM(AD28:AP28) -> 75333.333 | P28: =N28-O28 -> 1264666.7 | R28: =prod_table_raw!N115 -> 42.860623 | S28: =prod_table_raw!N113 -> 22600 | W28: =prod_table_raw!N114 -> 38600 | AF28: =S28/(concentrate_grade!$F$4/100) -> 75333.333 | AG28: =T28/(concentrate_grade!$F$6/100) -> 0 | AQ28: =Q28*prices!$C$4 -> 0 | AR28: =R28*prices!$C$11 -> 28807.911 | AS28: =S28*prices!$C$3 -> 155940 | AT28: =T28*prices!$C$8 -> 0 | AU28: =U28*prices!$C$2 -> 0 | AV28: =V28*prices!$C$7 -> 0 | AW28: =W28*prices!$C$13 -> 99561.541 | AX28: =X28*prices!$C$6 -> 0 | AY28: =Y28*prices!$C$5 -> 0 | AZ28: =Z28*prices!$C$9 -> 0 | BA28: =AB28*prices!$C$12 -> 0 | BB28: =AC28*prices!$C$14 -> 0 | BC28: =SUM(AQ28:AZ28) -> 284309.45 | BD28: =AQ28/BC28 -> 0 | BE28: =AS28/BC28 -> 0.54848687 | BF28: Cu (Zn, Ag)
A29: QC-MAIN-9de9bb0d | C29: Kiena | E29: Quebec | F29: mining | G29: Open-pit, concentrator | H29: Free-miling | I29: Land | J29: Energy | L29: Gold, silver | M29: Au (Ag) | N29: =prod_table_raw!N120 -> 191148 | O29: =SUM(AD29:AP29) -> 0 | P29: =N29-O29 -> 191148 | Q29: =prod_table_raw!N119 -> 1.1053251 | R29: =prod_table_raw!N121 -> 0.090448978 | AF29: =S29/(concentrate_grade!$F$4/100) -> 0 | AG29: =T29/(concentrate_grade!$F$6/100) -> 0 | AQ29: =Q29*prices!$C$4 -> 57248.251 | AR29: =R29*prices!$C$11 -> 60.793472 | AS29: =S29*prices!$C$3 -> 0 | AT29: =T29*prices!$C$8 -> 0 | AU29: =U29*prices!$C$2 -> 0 | AV29: =V29*prices!$C$7 -> 0 | AW29: =W29*prices!$C$13 -> 0 | AX29: =X29*prices!$C$6 -> 0 | AY29: =Y29*prices!$C$5 -> 0 | AZ29: =Z29*prices!$C$9 -> 0 | BA29: =AB29*prices!$C$12 -> 0 | BB29: =AC29*prices!$C$14 -> 0 | BC29: =SUM(AQ29:AZ29) -> 57309.045 | BD29: =AQ29/BC29 -> 0.9989392 | BE29: =AS29/BC29 -> 0 | BF29: Au (Ag)
A30: ON-MAIN-a3c56a83 | C30: Lac des Iles | E30: Ontario | F30: mining | G30: Open-pit, underground, concentrator | H30: Porphyry sulfide, flotation-based | I30: GHG | J30: Energy | L30: Platinum group metals, gold, nickel, copper, cobalt | M30: Pt | N30: =prod_table_raw!N124 -> 3798000 | O30: =SUM(AD30:AP30) -> 0 | P30: =N30-O30 -> 3798000 | Q30: =prod_table_raw!N125 -> 0.59407685 | Z30: =prod_table_raw!N127 -> 0.6780563 | AA30: =prod_table_raw!N126 -> 0.7775875 | AF30: =S30/(concentrate_grade!$F$4/100) -> 0 | AG30: =T30/(concentrate_grade!$F$6/100) -> 0 | AQ30: =Q30*prices!$C$4 -> 30769.102 | AR30: =R30*prices!$C$11 -> 0 | AS30: =S30*prices!$C$3 -> 0 | AT30: =T30*prices!$C$8 -> 0 | AU30: =U30*prices!$C$2 -> 0 | AV30: =V30*prices!$C$7 -> 0 | AW30: =W30*prices!$C$13 -> 0 | AX30: =X30*prices!$C$6 -> 0 | AY30: =Y30*prices!$C$5 -> 0 | AZ30: =Z30*prices!$C$9 -> 34878.396 | BA30: =AB30*prices!$C$12 -> 0 | BB30: =AC30*prices!$C$14 -> 0 | BC30: =SUM(AQ30:AZ30) -> 65647.498 | BD30: =AQ30/BC30 -> 0.46870183 | BE30: =AS30/BC30 -> 0 | BF30: Pt
A31: QC-MAIN-f9e41c2a | C31: Lamaque | E31: Quebec | F31: mining | G31: Underground, concentrator | H31: Free-miling | I31: Land | J31: Energy | L31: Gold, silver | M31: Au (Ag) | N31: =prod_table_raw!N134 -> 838419 | O31: =SUM(AD31:AP31) -> 0 | P31: =N31-O31 -> 838419 | Q31: =prod_table_raw!N133 -> 5.5074656 | R31: =prod_table_raw!N135 -> 2.2666987 | AF31: =S31/(concentrate_grade!$F$4/100) -> 0 | AG31: =T31/(concentrate_grade!$F$6/100) -> 0 | AQ31: =Q31*prices!$C$4 -> 285248.91 | AR31: =R31*prices!$C$11 -> 1523.5162 | AS31: =S31*prices!$C$3 -> 0 | AT31: =T31*prices!$C$8 -> 0 | AU31: =U31*prices!$C$2 -> 0 | AV31: =V31*prices!$C$7 -> 0 | AW31: =W31*prices!$C$13 -> 0 | AX31: =X31*prices!$C$6 -> 0 | AY31: =Y31*prices!$C$5 -> 0 | AZ31: =Z31*prices!$C$9 -> 0 | BA31: =AB31*prices!$C$12 -> 0 | BB31: =AC31*prices!$C$14 -> 0 | BC31: =SUM(AQ31:AZ31) -> 286772.43 | BD31: =AQ31/BC31 -> 0.99468737 | BE31: =AS31/BC31 -> 0 | BF31: Au (Ag)
A32: QC-MAIN-e51eda66 | C32: LaRonde | E32: Quebec | F32: mining | G32: Underground, concentrator | H32: Cu-Mo Porphyry sulfide, flotation-based | I32: NPRI+GHG+Land | J32: Energy | L32: Gold, zinc, copper, silver, cadmium | M32: Au (Zn, Cu, Ag) | N32: =prod_table_raw!N139 -> 1501500 | O32: =SUM(AD32:AP32) -> 8593.2013 | P32: =N32-O32 -> 1492906.8 | Q32: =prod_table_raw!N138 -> 7.3401461 | R32: =prod_table_raw!N135 -> 2.2666987 | S32: =prod_table_raw!N137 -> 2577.9604 | W32: =prod_table_raw!N136 -> 7702.4385 | AF32: =S32/(concentrate_grade!$F$4/100) -> 8593.2013 | AG32: =T32/(concentrate_grade!$F$6/100) -> 0 | AQ32: =Q32*prices!$C$4 -> 380169.18 | AR32: =R32*prices!$C$11 -> 1523.5162 | AS32: =S32*prices!$C$3 -> 17787.927 | AT32: =T32*prices!$C$8 -> 0 | AU32: =U32*prices!$C$2 -> 0 | AV32: =V32*prices!$C$7 -> 0 | AW32: =W32*prices!$C$13 -> 19867.012 | AX32: =X32*prices!$C$6 -> 0 | AY32: =Y32*prices!$C$5 -> 0 | AZ32: =Z32*prices!$C$9 -> 0 | BA32: =AB32*prices!$C$12 -> 0 | BB32: =AC32*prices!$C$14 -> 0 | BC32: =SUM(AQ32:AZ32) -> 419347.63 | BD32: =AQ32/BC32 -> 0.90657285 | BE32: =AS32/BC32 -> 0.042418093 | BF32: Au (Zn, Cu, Ag)
A33: NL-MAIN-d9036091 | C33: Long Harbour | E33: Newfoundland and Labrador | F33: manufacturing | G33: Refinery | H33: Ni hydrometallurgical refinery | I33: NPRI+GHG | L33: Nickel | M33: Ni | O33: =SUM(AD33:AP33) -> 173125 | P33: =N33-O33 -> -173125 | T33: =prod_table_raw!N145 -> 27700 | AF33: =S33/(concentrate_grade!$F$4/100) -> 0 | AG33: =T33/(concentrate_grade!$F$6/100) -> 173125 | AQ33: =Q33*prices!$C$4 -> 0 | AR33: =R33*prices!$C$11 -> 0 | AS33: =S33*prices!$C$3 -> 0 | AT33: =T33*prices!$C$8 -> 431843 | AU33: =U33*prices!$C$2 -> 0 | AV33: =V33*prices!$C$7 -> 0 | AW33: =W33*prices!$C$13 -> 0 | AX33: =X33*prices!$C$6 -> 0 | AY33: =Y33*prices!$C$5 -> 0 | AZ33: =Z33*prices!$C$9 -> 0 | BA33: =AB33*prices!$C$12 -> 0 | BB33: =AC33*prices!$C$14 -> 0 | BC33: =SUM(AQ33:AZ33) -> 431843 | BD33: =AQ33/BC33 -> 0 | BE33: =AS33/BC33 -> 0 | BF33: Ni
A34: ON-MAIN-1f126a43 | C34: Macassa | E34: Ontario | F34: mining | G34: Underground, concentrator | I34: NPRI+GHG+Land | J34: Energy | L34: Gold, silver | M34: Au | N34: =prod_table_raw!N146 -> 441588 | O34: =SUM(AD34:AP34) -> 0 | P34: =N34-O34 -> 441588 | Q34: =prod_table_raw!N147 -> 7.1082384 | AF34: =S34/(concentrate_grade!$F$4/100) -> 0 | AG34: =T34/(concentrate_grade!$F$6/100) -> 0 | AQ34: =Q34*prices!$C$4 -> 368157.95 | AR34: =R34*prices!$C$11 -> 0 | AS34: =S34*prices!$C$3 -> 0 | AT34: =T34*prices!$C$8 -> 0 | AU34: =U34*prices!$C$2 -> 0 | AV34: =V34*prices!$C$7 -> 0 | AW34: =W34*prices!$C$13 -> 0 | AX34: =X34*prices!$C$6 -> 0 | AY34: =Y34*prices!$C$5 -> 0 | AZ34: =Z34*prices!$C$9 -> 0 | BA34: =AB34*prices!$C$12 -> 0 | BB34: =AC34*prices!$C$14 -> 0 | BC34: =SUM(AQ34:AZ34) -> 368157.95 | BD34: =AQ34/BC34 -> 1 | BE34: =AS34/BC34 -> 0 | BF34: Au
A35: ON-MAIN-8825d90d | C35: Magino | E35: Ontario | F35: mining | G35: Open-pit, concentrator | H35: Free-miling | I35: NPRI+Land | L35: Gold, silver | M35: Au | N35: =prod_table_raw!N150 -> 1165551 | O35: =SUM(AD35:AP35) -> 0 | P35: =N35-O35 -> 1165551 | Q35: =prod_table_raw!N148 -> 1.0264155 | AF35: =S35/(concentrate_grade!$F$4/100) -> 0 | AG35: =T35/(concentrate_grade!$F$6/100) -> 0 | AQ35: =Q35*prices!$C$4 -> 53161.277 | AR35: =R35*prices!$C$11 -> 0 | AS35: =S35*prices!$C$3 -> 0 | AT35: =T35*prices!$C$8 -> 0 | AU35: =U35*prices!$C$2 -> 0 | AV35: =V35*prices!$C$7 -> 0 | AW35: =W35*prices!$C$13 -> 0 | AX35: =X35*prices!$C$6 -> 0 | AY35: =Y35*prices!$C$5 -> 0 | AZ35: =Z35*prices!$C$9 -> 0 | BA35: =AB35*prices!$C$12 -> 0 | BB35: =AC35*prices!$C$14 -> 0 | BC35: =SUM(AQ35:AZ35) -> 53161.277 | BD35: =AQ35/BC35 -> 1 | BE35: =AS35/BC35 -> 0 | BF35: Au
A36: NU-MAIN-5154702a | C36: Mary River | E36: Nunavut | F36: mining | G36: Open-pit | H36: Direct Shipping Ore | I36: GHG | L36: Iron ore | M36: U | N36: =prod_table_raw!N151 -> 5600000 | O36: =SUM(AD36:AP36) -> 0 | P36: =N36-O36 -> 5600000 | AF36: =S36/(concentrate_grade!$F$4/100) -> 0 | AG36: =T36/(concentrate_grade!$F$6/100) -> 0 | AQ36: =Q36*prices!$C$4 -> 0 | AR36: =R36*prices!$C$11 -> 0 | AS36: =S36*prices!$C$3 -> 0 | AT36: =T36*prices!$C$8 -> 0 | AU36: =U36*prices!$C$2 -> 0 | AV36: =V36*prices!$C$7 -> 0 | AW36: =W36*prices!$C$13 -> 0 | AX36: =X36*prices!$C$6 -> 0 | AY36: =Y36*prices!$C$5 -> 0 | AZ36: =Z36*prices!$C$9 -> 0 | BA36: =AB36*prices!$C$12 -> 0 | BB36: =AC36*prices!$C$14 -> 0 | BC36: =SUM(AQ36:AZ36) -> 0 | BD36: =AQ36/BC36 -> #DIV/0! | BE36: =AS36/BC36 -> #DIV/0! | BF36: U
A37: SK-MAIN-60ba74c4 | C37: McClean Lake | E37: Saskatchewan | F37: mining | G37: Concentrator | H37: High-grade U acid-leach mills | I37: NPRI+GHG+Land | L37: Uranium | M37: U | O37: =SUM(AD37:AP37) -> 0 | P37: =N37-O37 -> 0 | AB37: =prod_table_raw!N155 -> 8164.656 | AF37: =S37/(concentrate_grade!$F$4/100) -> 0 | AG37: =T37/(concentrate_grade!$F$6/100) -> 0 | AQ37: =Q37*prices!$C$4 -> 0 | AR37: =R37*prices!$C$11 -> 0 | AS37: =S37*prices!$C$3 -> 0 | AT37: =T37*prices!$C$8 -> 0 | AU37: =U37*prices!$C$2 -> 0 | AV37: =V37*prices!$C$7 -> 0 | AW37: =W37*prices!$C$13 -> 0 | AX37: =X37*prices!$C$6 -> 0 | AY37: =Y37*prices!$C$5 -> 0 | AZ37: =Z37*prices!$C$9 -> 0 | BA37: =AB37*prices!$C$12 -> 1401.8714 | BB37: =AC37*prices!$C$14 -> 0 | BC37: =SUM(AQ37:AZ37) -> 0 | BD37: =AQ37/BC37 -> #DIV/0! | BE37: =AS37/BC37 -> #DIV/0! | BF37: U
A38: ON-MAIN-7001a391 | C38: McCreedy West | E38: Ontario | F38: mining | G38: Underground | H38: Porphyry sulfide, flotation-based | I38: NPRI+Land | L38: Copper, nickel, platinum group metals, gold, silver, cobalt | M38: PGMs+Cu+Ni | N38: =prod_table_raw!N157 -> 317660 | O38: =SUM(AD38:AP38) -> 0 | P38: =N38-O38 -> 317660 | AF38: =S38/(concentrate_grade!$F$4/100) -> 0 | AG38: =T38/(concentrate_grade!$F$6/100) -> 0 | AQ38: =Q38*prices!$C$4 -> 0 | AR38: =R38*prices!$C$11 -> 0 | AS38: =S38*prices!$C$3 -> 0 | AT38: =T38*prices!$C$8 -> 0 | AU38: =U38*prices!$C$2 -> 0 | AV38: =V38*prices!$C$7 -> 0 | AW38: =W38*prices!$C$13 -> 0 | AX38: =X38*prices!$C$6 -> 0 | AY38: =Y38*prices!$C$5 -> 0 | AZ38: =Z38*prices!$C$9 -> 0 | BA38: =AB38*prices!$C$12 -> 0 | BB38: =AC38*prices!$C$14 -> 0 | BC38: =SUM(AQ38:AZ38) -> 0 | BD38: =AQ38/BC38 -> #DIV/0! | BE38: =AS38/BC38 -> #DIV/0! | BF38: PGMs+Cu+Ni
A39: NU-MAIN-8b0264c9 | C39: Meliadine | E39: Nunavut | F39: mining | G39: Open-pit, underground, concentrator | H39: Free-miling | I39: NPRI+GHG+Land | J39: Energy | L39: Gold | M39: Au (Ag) | N39: =prod_table_raw!N163 -> 1918143 | O39: =SUM(AD39:AP39) -> 0 | P39: =N39-O39 -> 1918143 | Q39: =prod_table_raw!N164 -> 11.32606 | R39: =prod_table_raw!N165 -> 0.8397945 | AF39: =S39/(concentrate_grade!$F$4/100) -> 0 | AG39: =T39/(concentrate_grade!$F$6/100) -> 0 | AQ39: =Q39*prices!$C$4 -> 586612.13 | AR39: =R39*prices!$C$11 -> 564.45108 | AS39: =S39*prices!$C$3 -> 0 | AT39: =T39*prices!$C$8 -> 0 | AU39: =U39*prices!$C$2 -> 0 | AV39: =V39*prices!$C$7 -> 0 | AW39: =W39*prices!$C$13 -> 0 | AX39: =X39*prices!$C$6 -> 0 | AY39: =Y39*prices!$C$5 -> 0 | AZ39: =Z39*prices!$C$9 -> 0 | BA39: =AB39*prices!$C$12 -> 0 | BB39: =AC39*prices!$C$14 -> 0 | BC39: =SUM(AQ39:AZ39) -> 587176.58 | BD39: =AQ39/BC39 -> 0.9990387 | BE39: =AS39/BC39 -> 0 | BF39: Au (Ag)
A40: BC-MAIN-ed23117f | C40: Mount Milligan | E40: British Columbia | F40: mining | G40: Open-pit, concentrator | H40: Cu-Au Porphyry sulfide, flotation-based | I40: NPRI+GHG+Water+Land | J40: Energy | L40: Copper, gold, silver | M40: Cu+Au | N40: =prod_table_raw!N175 -> 21680000 | O40: =SUM(AD40:AP40) -> 93533.694 | P40: =N40-O40 -> 21586466 | Q40: =prod_table_raw!N173 -> 4.8021005 | S40: =prod_table_raw!N171 -> 28060.108 | AF40: =S40/(concentrate_grade!$F$4/100) -> 93533.694 | AG40: =T40/(concentrate_grade!$F$6/100) -> 0 | AQ40: =Q40*prices!$C$4 -> 248715.84 | AR40: =R40*prices!$C$11 -> 0 | AS40: =S40*prices!$C$3 -> 193614.75 | AT40: =T40*prices!$C$8 -> 0 | AU40: =U40*prices!$C$2 -> 0 | AV40: =V40*prices!$C$7 -> 0 | AW40: =W40*prices!$C$13 -> 0 | AX40: =X40*prices!$C$6 -> 0 | AY40: =Y40*prices!$C$5 -> 0 | AZ40: =Z40*prices!$C$9 -> 0 | BA40: =AB40*prices!$C$12 -> 0 | BB40: =AC40*prices!$C$14 -> 0 | BC40: =SUM(AQ40:AZ40) -> 442330.59 | BD40: =AQ40/BC40 -> 0.56228497 | BE40: =AS40/BC40 -> 0.43771503 | BF40: Cu+Au
A41: BC-MAIN-3f490561 | C41: Mount Polley | E41: British Columbia | F41: mining | G41: Open-pit, concentrator | H41: Cu-Au Porphyry sulfide, flotation-based | I41: NPRI+GHG+Land | L41: Gold, copper, silver | M41: Cu+Au | N41: =prod_table_raw!N179 -> 5948239 | O41: =SUM(AD41:AP41) -> 45578.436 | P41: =N41-O41 -> 5902660.6 | Q41: =prod_table_raw!N178 -> 1.3011838 | S41: =prod_table_raw!N180 -> 13673.531 | AF41: =S41/(concentrate_grade!$F$4/100) -> 45578.436 | AG41: =T41/(concentrate_grade!$F$6/100) -> 0 | AQ41: =Q41*prices!$C$4 -> 67392.389 | AR41: =R41*prices!$C$11 -> 0 | AS41: =S41*prices!$C$3 -> 94347.363 | AT41: =T41*prices!$C$8 -> 0 | AU41: =U41*prices!$C$2 -> 0 | AV41: =V41*prices!$C$7 -> 0 | AW41: =W41*prices!$C$13 -> 0 | AX41: =X41*prices!$C$6 -> 0 | AY41: =Y41*prices!$C$5 -> 0 | AZ41: =Z41*prices!$C$9 -> 0 | BA41: =AB41*prices!$C$12 -> 0 | BB41: =AC41*prices!$C$14 -> 0 | BC41: =SUM(AQ41:AZ41) -> 161739.75 | BD41: =AQ41/BC41 -> 0.41667177 | BE41: =AS41/BC41 -> 0.58332823 | BF41: Cu+Au
A42: ON-MAIN-fefeaee4 | C42: Musselwhite | E42: Ontario | F42: mining | G42: Underground, concentrator | H42: Free-miling | I42: NPRI+GHG+Land | J42: Energy and materials | L42: Gold, silver | M42: Au | N42: =prod_table_raw!N183 -> 1028000 | O42: =SUM(AD42:AP42) -> 0 | P42: =N42-O42 -> 1028000 | Q42: =prod_table_raw!N184 -> 5.59863 | AF42: =S42/(concentrate_grade!$F$4/100) -> 0 | AG42: =T42/(concentrate_grade!$F$6/100) -> 0 | AQ42: =Q42*prices!$C$4 -> 289970.6 | AR42: =R42*prices!$C$11 -> 0 | AS42: =S42*prices!$C$3 -> 0 | AT42: =T42*prices!$C$8 -> 0 | AU42: =U42*prices!$C$2 -> 0 | AV42: =V42*prices!$C$7 -> 0 | AW42: =W42*prices!$C$13 -> 0 | AX42: =X42*prices!$C$6 -> 0 | AY42: =Y42*prices!$C$5 -> 0 | AZ42: =Z42*prices!$C$9 -> 0 | BA42: =AB42*prices!$C$12 -> 0 | BB42: =AC42*prices!$C$14 -> 0 | BC42: =SUM(AQ42:AZ42) -> 289970.6 | BD42: =AQ42/BC42 -> 1 | BE42: =AS42/BC42 -> 0 | BF42: Au
A43: BC-MAIN-aa76f6f2 | C43: New Afton | E43: British Columbia | F43: mining | G43: Underground, concentrator | H43: Cu-Au Porphyry sulfide, flotation-based | I43: NPRI+GHG+Water+Land | J43: Energy and materials | L43: Gold, copper, silver | M43: Cu+Au | N43: =prod_table_raw!N189 -> 3065000 | O43: =SUM(AD43:AP43) -> 71667.536 | P43: =N43-O43 -> 2993332.5 | Q43: =prod_table_raw!N187 -> 2.0974023 | S43: =prod_table_raw!N190 -> 21500.261 | AF43: =S43/(concentrate_grade!$F$4/100) -> 71667.536 | AG43: =T43/(concentrate_grade!$F$6/100) -> 0 | AQ43: =Q43*prices!$C$4 -> 108631.04 | AR43: =R43*prices!$C$11 -> 0 | AS43: =S43*prices!$C$3 -> 148351.8 | AT43: =T43*prices!$C$8 -> 0 | AU43: =U43*prices!$C$2 -> 0 | AV43: =V43*prices!$C$7 -> 0 | AW43: =W43*prices!$C$13 -> 0 | AX43: =X43*prices!$C$6 -> 0 | AY43: =Y43*prices!$C$5 -> 0 | AZ43: =Z43*prices!$C$9 -> 0 | BA43: =AB43*prices!$C$12 -> 0 | BB43: =AC43*prices!$C$14 -> 0 | BC43: =SUM(AQ43:AZ43) -> 256982.84 | BD43: =AQ43/BC43 -> 0.4227171 | BE43: =AS43/BC43 -> 0.5772829 | BF43: Cu+Au
A44: ON-MAIN-fcb287a4 | B44: GRP-de097f20 | C44: Nickel Rim South | D44: Integrated Nickel Operations | E44: Ontario | F44: mining | G44: Underground | H44: Ni-Cu Porphyry sulfide, flotation-based | I44: NPRI+Land | L44: Nickel, copper, cobalt, platinum group metals, gold | M44: Ni+Cu | N44: =prod_table_raw!N194 -> 320160 | O44: =SUM(AD44:AP44) -> 0 | P44: =N44-O44 -> 320160 | AF44: =S44/(concentrate_grade!$F$4/100) -> 0 | AG44: =T44/(concentrate_grade!$F$6/100) -> 0 | AQ44: =Q44*prices!$C$4 -> 0 | AR44: =R44*prices!$C$11 -> 0 | AS44: =S44*prices!$C$3 -> 0 | AT44: =T44*prices!$C$8 -> 0 | AU44: =U44*prices!$C$2 -> 0 | AV44: =V44*prices!$C$7 -> 0 | AW44: =W44*prices!$C$13 -> 0 | AX44: =X44*prices!$C$6 -> 0 | AY44: =Y44*prices!$C$5 -> 0 | AZ44: =Z44*prices!$C$9 -> 0 | BA44: =AB44*prices!$C$12 -> 0 | BB44: =AC44*prices!$C$14 -> 0 | BC44: =SUM(AQ44:AZ44) -> 0 | BD44: =AQ44/BC44 -> #DIV/0! | BE44: =AS44/BC44 -> #DIV/0! | BF44: Ni+Cu
A45: QC-MAIN-a555d9b9 | C45: Niobec | E45: Quebec | F45: mining | G45: Underground, concentrator | I45: NPRI+GHG+Land | L45: Niobium | M45: Nb | N45: =prod_table_raw!N195 -> 2200000 | O45: =SUM(AD45:AP45) -> 0 | P45: =N45-O45 -> 2200000 | AC45: =prod_table_raw!N196 -> 6568.95 | AF45: =S45/(concentrate_grade!$F$4/100) -> 0 | AG45: =T45/(concentrate_grade!$F$6/100) -> 0 | AQ45: =Q45*prices!$C$4 -> 0 | AR45: =R45*prices!$C$11 -> 0 | AS45: =S45*prices!$C$3 -> 0 | AT45: =T45*prices!$C$8 -> 0 | AU45: =U45*prices!$C$2 -> 0 | AV45: =V45*prices!$C$7 -> 0 | AW45: =W45*prices!$C$13 -> 0 | AX45: =X45*prices!$C$6 -> 0 | AY45: =Y45*prices!$C$5 -> 0 | AZ45: =Z45*prices!$C$9 -> 0 | BA45: =AB45*prices!$C$12 -> 0 | BB45: =AC45*prices!$C$14 -> 517501.88 | BC45: =SUM(AQ45:AZ45) -> 0 | BD45: =AQ45/BC45 -> #DIV/0! | BE45: =AS45/BC45 -> #DIV/0! | BF45: Nb
A46: QC-MAIN-649d2873 | C46: Niobec Converter | E46: Quebec | F46: manufacturing | G46: Convertor | L46: Ferroniobium | M46: Nb | O46: =SUM(AD46:AP46) -> 0 | P46: =N46-O46 -> 0 | AC46: =prod_table_raw!N197 -> 11700 | AF46: =S46/(concentrate_grade!$F$4/100) -> 0 | AG46: =T46/(concentrate_grade!$F$6/100) -> 0 | AQ46: =Q46*prices!$C$4 -> 0 | AR46: =R46*prices!$C$11 -> 0 | AS46: =S46*prices!$C$3 -> 0 | AT46: =T46*prices!$C$8 -> 0 | AU46: =U46*prices!$C$2 -> 0 | AV46: =V46*prices!$C$7 -> 0 | AW46: =W46*prices!$C$13 -> 0 | AX46: =X46*prices!$C$6 -> 0 | AY46: =Y46*prices!$C$5 -> 0 | AZ46: =Z46*prices!$C$9 -> 0 | BA46: =AB46*prices!$C$12 -> 0 | BB46: =AC46*prices!$C$14 -> 921726 | BC46: =SUM(AQ46:AZ46) -> 0 | BD46: =AQ46/BC46 -> #DIV/0! | BE46: =AS46/BC46 -> #DIV/0! | BF46: Nb
A47: QC-MAIN-5ce331b8 | C47: Nunavik Nickel | E47: Quebec | F47: mining | G47: Open-pit, underground, concentrator | H47: Ni-Cu Porphyry sulfide, flotation-based | I47: GHG | L47: Nickel, copper, platinum group metals, cobalt | M47: Ni+Cu | N47: =prod_table_raw!N202 -> 6835294.1 | O47: =SUM(AD47:AP47) -> 499545 | P47: =N47-O47 -> 6335749.1 | S47: =prod_table_raw!N200 -> 40926 | T47: =prod_table_raw!N201 -> 58100 | AF47: =S47/(concentrate_grade!$F$4/100) -> 136420 | AG47: =T47/(concentrate_grade!$F$6/100) -> 363125 | AQ47: =Q47*prices!$C$4 -> 0 | AR47: =R47*prices!$C$11 -> 0 | AS47: =S47*prices!$C$3 -> 282389.4 | AT47: =T47*prices!$C$8 -> 905779 | AU47: =U47*prices!$C$2 -> 0 | AV47: =V47*prices!$C$7 -> 0 | AW47: =W47*prices!$C$13 -> 0 | AX47: =X47*prices!$C$6 -> 0 | AY47: =Y47*prices!$C$5 -> 0 | AZ47: =Z47*prices!$C$9 -> 0 | BA47: =AB47*prices!$C$12 -> 0 | BB47: =AC47*prices!$C$14 -> 0 | BC47: =SUM(AQ47:AZ47) -> 1188168.4 | BD47: =AQ47/BC47 -> 0 | BE47: =AS47/BC47 -> 0.23766783 | BF47: Ni+Cu
A48: QC-MAIN-a97821c0 | C48: Raglan | E48: Quebec | F48: mining | G48: Underground, concentrator | H48: Ni-Cu Porphyry sulfide, flotation-based | I48: NPRI+GHG+Land | L48: Nickel, platinum group metals, copper, cobalt, gold, silver | M48: Ni+PGM+Cu (Co) | N48: =prod_table_raw!N207 -> 1500000 | O48: =SUM(AD48:AP48) -> 169743.33 | P48: =N48-O48 -> 1330256.7 | S48: =prod_table_raw!N203 -> 5488 | T48: =prod_table_raw!N204 -> 24232 | U48: =prod_table_raw!N205 -> 498 | Z48: =prod_table_raw!N206 -> 4.4160749 | AF48: =S48/(concentrate_grade!$F$4/100) -> 18293.333 | AG48: =T48/(concentrate_grade!$F$6/100) -> 151450 | AQ48: =Q48*prices!$C$4 -> 0 | AR48: =R48*prices!$C$11 -> 0 | AS48: =S48*prices!$C$3 -> 37867.2 | AT48: =T48*prices!$C$8 -> 377776.88 | AU48: =U48*prices!$C$2 -> 4650.876 | AV48: =V48*prices!$C$7 -> 0 | AW48: =W48*prices!$C$13 -> 0 | AX48: =X48*prices!$C$6 -> 0 | AY48: =Y48*prices!$C$5 -> 0 | AZ48: =Z48*prices!$C$9 -> 227157.55 | BA48: =AB48*prices!$C$12 -> 0 | BB48: =AC48*prices!$C$14 -> 0 | BC48: =SUM(AQ48:AZ48) -> 647452.51 | BD48: =AQ48/BC48 -> 0 | BE48: =AS48/BC48 -> 0.058486452 | BF48: Ni+PGM+Cu (Co)
A49: ON-MAIN-0aadf28f | C49: Rainy River | E49: Ontario | F49: mining | G49: Open-pit, underground, concentrator | H49: Free-miling | I49: NPRI+GHG+Land | J49: Energy and materials | L49: Gold, silver | M49: Au | N49: =prod_table_raw!N211 -> 8764000 | O49: =SUM(AD49:AP49) -> 0 | P49: =N49-O49 -> 8764000 | Q49: =prod_table_raw!N212 -> 7.8923576 | AF49: =S49/(concentrate_grade!$F$4/100) -> 0 | AG49: =T49/(concentrate_grade!$F$6/100) -> 0 | AQ49: =Q49*prices!$C$4 -> 408769.94 | AR49: =R49*prices!$C$11 -> 0 | AS49: =S49*prices!$C$3 -> 0 | AT49: =T49*prices!$C$8 -> 0 | AU49: =U49*prices!$C$2 -> 0 | AV49: =V49*prices!$C$7 -> 0 | AW49: =W49*prices!$C$13 -> 0 | AX49: =X49*prices!$C$6 -> 0 | AY49: =Y49*prices!$C$5 -> 0 | AZ49: =Z49*prices!$C$9 -> 0 | BA49: =AB49*prices!$C$12 -> 0 | BB49: =AC49*prices!$C$14 -> 0 | BC49: =SUM(AQ49:AZ49) -> 408769.94 | BD49: =AQ49/BC49 -> 1 | BE49: =AS49/BC49 -> 0 | BF49: Au
A50: BC-MAIN-8eb8be0d | C50: Red Chris | E50: British Columbia | F50: mining | G50: Open-pit, concentrator | H50: Mixed free-miling-refactory | I50: NPRI+GHG+Water+Land | J50: Energy | L50: Gold, copper, silver | M50: Cu+Au | N50: =prod_table_raw!N215 -> 1139000 | O50: =SUM(AD50:AP50) -> 13333.333 | P50: =N50-O50 -> 1125666.7 | Q50: =prod_table_raw!N214 -> 0.1555175 | S50: =prod_table_raw!N217 -> 4000 | AF50: =S50/(concentrate_grade!$F$4/100) -> 13333.333 | AG50: =T50/(concentrate_grade!$F$6/100) -> 0 | AQ50: =Q50*prices!$C$4 -> 8054.7389 | AR50: =R50*prices!$C$11 -> 0 | AS50: =S50*prices!$C$3 -> 27600 | AT50: =T50*prices!$C$8 -> 0 | AU50: =U50*prices!$C$2 -> 0 | AV50: =V50*prices!$C$7 -> 0 | AW50: =W50*prices!$C$13 -> 0 | AX50: =X50*prices!$C$6 -> 0 | AY50: =Y50*prices!$C$5 -> 0 | AZ50: =Z50*prices!$C$9 -> 0 | BA50: =AB50*prices!$C$12 -> 0 | BB50: =AC50*prices!$C$14 -> 0 | BC50: =SUM(AQ50:AZ50) -> 35654.739 | BD50: =AQ50/BC50 -> 0.22590935 | BE50: =AS50/BC50 -> 0.77409065 | BF50: Cu+Au
A51: ON-MAIN-7f050560 | C51: Red Lake | E51: Ontario | F51: mining | G51: Underground, concentrator | H51: Mixed free-miling-refactory | I51: NPRI+GHG+Land | J51: Energy | L51: Gold, silver | M51: Au | N51: =prod_table_raw!N222 -> 841000 | O51: =SUM(AD51:AP51) -> 0 | P51: =N51-O51 -> 841000 | Q51: =prod_table_raw!N223 -> 3.5053645 | AF51: =S51/(concentrate_grade!$F$4/100) -> 0 | AG51: =T51/(concentrate_grade!$F$6/100) -> 0 | AQ51: =Q51*prices!$C$4 -> 181553.81 | AR51: =R51*prices!$C$11 -> 0 | AS51: =S51*prices!$C$3 -> 0 | AT51: =T51*prices!$C$8 -> 0 | AU51: =U51*prices!$C$2 -> 0 | AV51: =V51*prices!$C$7 -> 0 | AW51: =W51*prices!$C$13 -> 0 | AX51: =X51*prices!$C$6 -> 0 | AY51: =Y51*prices!$C$5 -> 0 | AZ51: =Z51*prices!$C$9 -> 0 | BA51: =AB51*prices!$C$12 -> 0 | BB51: =AC51*prices!$C$14 -> 0 | BC51: =SUM(AQ51:AZ51) -> 181553.81 | BD51: =AQ51/BC51 -> 1 | BE51: =AS51/BC51 -> 0 | BF51: Au
A52: NL-MAIN-b64bae7a | C52: Scully | E52: Newfoundland and Labrador | F52: mining | G52: Open-pit, concentrator | H52: Fe concentrator | I52: NPRI+GHG+Land | J52: Energy | L52: Iron | M52: Fe | N52: =prod_table_raw!N226 -> 3560000 | O52: =SUM(AD52:AP52) -> 0 | P52: =N52-O52 -> 3560000 | AF52: =S52/(concentrate_grade!$F$4/100) -> 0 | AG52: =T52/(concentrate_grade!$F$6/100) -> 0 | AQ52: =Q52*prices!$C$4 -> 0 | AR52: =R52*prices!$C$11 -> 0 | AS52: =S52*prices!$C$3 -> 0 | AT52: =T52*prices!$C$8 -> 0 | AU52: =U52*prices!$C$2 -> 0 | AV52: =V52*prices!$C$7 -> 0 | AW52: =W52*prices!$C$13 -> 0 | AX52: =X52*prices!$C$6 -> 0 | AY52: =Y52*prices!$C$5 -> 0 | AZ52: =Z52*prices!$C$9 -> 0 | BA52: =AB52*prices!$C$12 -> 0 | BB52: =AC52*prices!$C$14 -> 0 | BC52: =SUM(AQ52:AZ52) -> 0 | BD52: =AQ52/BC52 -> #DIV/0! | BE52: =AS52/BC52 -> #DIV/0! | BF52: Fe
A53: ON-MAIN-ed85ac94 | B53: GRP-de097f20 | C53: Strathcona | D53: Integrated Nickel Operations | E53: Ontario | F53: mining | G53: Concentrator | H53: Ni-Cu Porphyry sulfide, flotation-based | I53: NPRI+GHG+Land | L53: Nickel, copper, platinum group metals, gold, silver, cobalt, selenium, tellurium | M53: Ni+Cu | N53: =prod_table_raw!N239 -> 1025997 | O53: =SUM(AD53:AP53) -> 70909.167 | P53: =N53-O53 -> 955087.83 | S53: =prod_table_raw!N237 -> 7154 | T53: =prod_table_raw!N238 -> 7530 | AF53: =S53/(concentrate_grade!$F$4/100) -> 23846.667 | AG53: =T53/(concentrate_grade!$F$6/100) -> 47062.5 | AQ53: =Q53*prices!$C$4 -> 0 | AR53: =R53*prices!$C$11 -> 0 | AS53: =S53*prices!$C$3 -> 49362.6 | AT53: =T53*prices!$C$8 -> 117392.7 | AU53: =U53*prices!$C$2 -> 0 | AV53: =V53*prices!$C$7 -> 0 | AW53: =W53*prices!$C$13 -> 0 | AX53: =X53*prices!$C$6 -> 0 | AY53: =Y53*prices!$C$5 -> 0 | AZ53: =Z53*prices!$C$9 -> 0 | BA53: =AB53*prices!$C$12 -> 0 | BB53: =AC53*prices!$C$14 -> 0 | BC53: =SUM(AQ53:AZ53) -> 166755.3 | BD53: =AQ53/BC53 -> 0 | BE53: =AS53/BC53 -> 0.29601818 | BF53: Ni+Cu
A54: ON-MAIN-40ce0593 | B54: GRP-de097f20 | C54: Sudbury | D54: Integrated Nickel Operations | E54: Ontario | F54: manufacturing | G54: Smelter, plant | H54: Ni-Cu smelter | I54: NPRI+GHG | L54: Nickel-copper matte containing cobalt, gold, silver, platinum group metals | M54: Ni+Cu | O54: =SUM(AD54:AP54) -> 434802.08 | P54: =N54-O54 -> -434802.08 | S54: =prod_table_raw!N241 -> 13720 | T54: =prod_table_raw!N240 -> 62251 | AF54: =S54/(concentrate_grade!$F$4/100) -> 45733.333 | AG54: =T54/(concentrate_grade!$F$6/100) -> 389068.75 | AQ54: =Q54*prices!$C$4 -> 0 | AR54: =R54*prices!$C$11 -> 0 | AS54: =S54*prices!$C$3 -> 94668 | AT54: =T54*prices!$C$8 -> 970493.09 | AU54: =U54*prices!$C$2 -> 0 | AV54: =V54*prices!$C$7 -> 0 | AW54: =W54*prices!$C$13 -> 0 | AX54: =X54*prices!$C$6 -> 0 | AY54: =Y54*prices!$C$5 -> 0 | AZ54: =Z54*prices!$C$9 -> 0 | BA54: =AB54*prices!$C$12 -> 0 | BB54: =AC54*prices!$C$14 -> 0 | BC54: =SUM(AQ54:AZ54) -> 1065161.1 | BD54: =AQ54/BC54 -> 0 | BE54: =AS54/BC54 -> 0.088876698 | BF54: Ni+Cu
A55: ON-MAIN-f4fc3276 | C55: Sugar Zone | E55: Ontario | F55: mining | G55: Underground, concentrator | L55: Gold | M55: Au | N55: =prod_table_raw!N244 -> 234671 | O55: =SUM(AD55:AP55) -> 0 | P55: =N55-O55 -> 234671 | Q55: =prod_table_raw!N245 -> 1.2024302 | AF55: =S55/(concentrate_grade!$F$4/100) -> 0 | AG55: =T55/(concentrate_grade!$F$6/100) -> 0 | AQ55: =Q55*prices!$C$4 -> 62277.63 | AR55: =R55*prices!$C$11 -> 0 | AS55: =S55*prices!$C$3 -> 0 | AT55: =T55*prices!$C$8 -> 0 | AU55: =U55*prices!$C$2 -> 0 | AV55: =V55*prices!$C$7 -> 0 | AW55: =W55*prices!$C$13 -> 0 | AX55: =X55*prices!$C$6 -> 0 | AY55: =Y55*prices!$C$5 -> 0 | AZ55: =Z55*prices!$C$9 -> 0 | BA55: =AB55*prices!$C$12 -> 0 | BB55: =AC55*prices!$C$14 -> 0 | BC55: =SUM(AQ55:AZ55) -> 62277.63 | BD55: =AQ55/BC55 -> 1 | BE55: =AS55/BC55 -> 0 | BF55: Au
A56: AB-MAIN-d3a4aba9 | C56: The Cobalt Refinery Company Inc. | E56: Alberta | F56: manufacturing | G56: Refinery | H56: Co hydrometallurgical refinery | I56: NPRI+GHG | L56: Nickel, cobalt, copper sulfide, ammonium sulfate | M56: Ni+Co | O56: =SUM(AD56:AP56) -> 201675 | P56: =N56-O56 -> -201675 | T56: =prod_table_raw!N247 -> 32268 | U56: =prod_table_raw!N246 -> 3368 | AF56: =S56/(concentrate_grade!$F$4/100) -> 0 | AG56: =T56/(concentrate_grade!$F$6/100) -> 201675 | AQ56: =Q56*prices!$C$4 -> 0 | AR56: =R56*prices!$C$11 -> 0 | AS56: =S56*prices!$C$3 -> 0 | AT56: =T56*prices!$C$8 -> 503058.12 | AU56: =U56*prices!$C$2 -> 31454.117 | AV56: =V56*prices!$C$7 -> 0 | AW56: =W56*prices!$C$13 -> 0 | AX56: =X56*prices!$C$6 -> 0 | AY56: =Y56*prices!$C$5 -> 0 | AZ56: =Z56*prices!$C$9 -> 0 | BA56: =AB56*prices!$C$12 -> 0 | BB56: =AC56*prices!$C$14 -> 0 | BC56: =SUM(AQ56:AZ56) -> 534512.24 | BD56: =AQ56/BC56 -> 0 | BE56: =AS56/BC56 -> 0 | BF56: Ni+Co
A57: MB-MAIN-e0a6250e | C57: Thompson (T-1 and T-3) | E57: Manitoba | F57: mining | G57: Open-pit, underground, concentrator | H57: Ni-Cu Porphyry sulfide, flotation-based | I57: GHG+Land | L57: Nickel, cobalt, copper, platinum group metals, gold, silver | M57: Ni+Cu | N57: =prod_table_raw!N250 -> 464705.88 | O57: =SUM(AD57:AP57) -> 65041.667 | P57: =N57-O57 -> 399664.22 | S57: =prod_table_raw!N248 -> 4700 | T57: =prod_table_raw!N249 -> 7900 | AF57: =S57/(concentrate_grade!$F$4/100) -> 15666.667 | AG57: =T57/(concentrate_grade!$F$6/100) -> 49375 | AQ57: =Q57*prices!$C$4 -> 0 | AR57: =R57*prices!$C$11 -> 0 | AS57: =S57*prices!$C$3 -> 32430 | AT57: =T57*prices!$C$8 -> 123161 | AU57: =U57*prices!$C$2 -> 0 | AV57: =V57*prices!$C$7 -> 0 | AW57: =W57*prices!$C$13 -> 0 | AX57: =X57*prices!$C$6 -> 0 | AY57: =Y57*prices!$C$5 -> 0 | AZ57: =Z57*prices!$C$9 -> 0 | BA57: =AB57*prices!$C$12 -> 0 | BB57: =AC57*prices!$C$14 -> 0 | BC57: =SUM(AQ57:AZ57) -> 155591 | BD57: =AQ57/BC57 -> 0 | BE57: =AS57/BC57 -> 0.20843108 | BF57: Ni+Cu
A58: ON-MAIN-28f3f0fc | B58: GRP-dc07540b | C58: Totten | D58: Sudbury Operation | E58: Ontario | F58: mining | G58: Underground | H58: Ni-Cu Porphyry sulfide, flotation-based | I58: NPRI | L58: Nickel, copper, platinum group metals, gold, silver, cobalt | M58: Ni+Cu | N58: =prod_table_raw!N259 -> 414000 | O58: =SUM(AD58:AP58) -> 65530.833 | P58: =N58-O58 -> 348469.17 | S58: =prod_table_raw!N258 -> 7783 | T58: =prod_table_raw!N257 -> 6334 | AF58: =S58/(concentrate_grade!$F$4/100) -> 25943.333 | AG58: =T58/(concentrate_grade!$F$6/100) -> 39587.5 | AQ58: =Q58*prices!$C$4 -> 0 | AR58: =R58*prices!$C$11 -> 0 | AS58: =S58*prices!$C$3 -> 53702.7 | AT58: =T58*prices!$C$8 -> 98747.06 | AU58: =U58*prices!$C$2 -> 0 | AV58: =V58*prices!$C$7 -> 0 | AW58: =W58*prices!$C$13 -> 0 | AX58: =X58*prices!$C$6 -> 0 | AY58: =Y58*prices!$C$5 -> 0 | AZ58: =Z58*prices!$C$9 -> 0 | BA58: =AB58*prices!$C$12 -> 0 | BB58: =AC58*prices!$C$14 -> 0 | BC58: =SUM(AQ58:AZ58) -> 152449.76 | BD58: =AQ58/BC58 -> 0 | BE58: =AS58/BC58 -> 0.3522649 | BF58: Ni+Cu
A59: BC-MAIN-3bb6b7cd | C59: Trail | E59: British Columbia | F59: manufacturing | G59: Refinery | H59: Zn refinery | I59: NPRI+GHG+Water | L59: Zinc, lead, bismuth, cadmium, indium, germanium, precious metals, liquid sulfur dioxide, sulfuric acid | M59: Zn (Pb) | O59: =SUM(AD59:AP59) -> 0 | P59: =N59-O59 -> 0 | W59: =prod_table_raw!N262 -> 256000 | AF59: =S59/(concentrate_grade!$F$4/100) -> 0 | AG59: =T59/(concentrate_grade!$F$6/100) -> 0 | AQ59: =Q59*prices!$C$4 -> 0 | AR59: =R59*prices!$C$11 -> 0 | AS59: =S59*prices!$C$3 -> 0 | AT59: =T59*prices!$C$8 -> 0 | AU59: =U59*prices!$C$2 -> 0 | AV59: =V59*prices!$C$7 -> 0 | AW59: =W59*prices!$C$13 -> 660304.52 | AX59: =X59*prices!$C$6 -> 0 | AY59: =Y59*prices!$C$5 -> 0 | AZ59: =Z59*prices!$C$9 -> 0 | BA59: =AB59*prices!$C$12 -> 0 | BB59: =AC59*prices!$C$14 -> 0 | BC59: =SUM(AQ59:AZ59) -> 660304.52 | BD59: =AQ59/BC59 -> 0 | BE59: =AS59/BC59 -> 0 | BF59: Zn (Pb)
A60: NL-MAIN-2d8801d6 | C60: Voisey’s Bay | E60: Newfoundland and Labrador | F60: mining | G60: Open-pit, underground, concentrator | H60: Ni-Cu Porphyry sulfide, flotation-based | I60: NPRI+GHG+Land | L60: Nickel, copper, cobalt | M60: Ni+Cu | N60: =prod_table_raw!N268 -> 794117.65 | O60: =SUM(AD60:AP60) -> 116375 | P60: =N60-O60 -> 677742.65 | S60: =prod_table_raw!N266 -> 9600 | T60: =prod_table_raw!N267 -> 13500 | AF60: =S60/(concentrate_grade!$F$4/100) -> 32000 | AG60: =T60/(concentrate_grade!$F$6/100) -> 84375 | AQ60: =Q60*prices!$C$4 -> 0 | AR60: =R60*prices!$C$11 -> 0 | AS60: =S60*prices!$C$3 -> 66240 | AT60: =T60*prices!$C$8 -> 210465 | AU60: =U60*prices!$C$2 -> 0 | AV60: =V60*prices!$C$7 -> 0 | AW60: =W60*prices!$C$13 -> 0 | AX60: =X60*prices!$C$6 -> 0 | AY60: =Y60*prices!$C$5 -> 0 | AZ60: =Z60*prices!$C$9 -> 0 | BA60: =AB60*prices!$C$12 -> 0 | BB60: =AC60*prices!$C$14 -> 0 | BC60: =SUM(AQ60:AZ60) -> 276705 | BD60: =AQ60/BC60 -> 0 | BE60: =AS60/BC60 -> 0.23938852 | BF60: Ni+Cu
A61: QC-MAIN-02884fb5 | C61: Westwood-Doyon | E61: Quebec | F61: mining | G61: Underground, concentrator | H61: Free-miling | I61: GHG+Land | J61: Energy and materials | L61: Gold, silver | M61: Au (Ag) | N61: =prod_table_raw!N271 -> 1034000 | O61: =SUM(AD61:AP61) -> 0 | P61: =N61-O61 -> 1034000 | Q61: =prod_table_raw!N273 -> 2.8926255 | R61: =prod_table_raw!N274 -> 1.143178 | AF61: =S61/(concentrate_grade!$F$4/100) -> 0 | AG61: =T61/(concentrate_grade!$F$6/100) -> 0 | AQ61: =Q61*prices!$C$4 -> 149818.14 | AR61: =R61*prices!$C$11 -> 768.36426 | AS61: =S61*prices!$C$3 -> 0 | AT61: =T61*prices!$C$8 -> 0 | AU61: =U61*prices!$C$2 -> 0 | AV61: =V61*prices!$C$7 -> 0 | AW61: =W61*prices!$C$13 -> 0 | AX61: =X61*prices!$C$6 -> 0 | AY61: =Y61*prices!$C$5 -> 0 | AZ61: =Z61*prices!$C$9 -> 0 | BA61: =AB61*prices!$C$12 -> 0 | BB61: =AC61*prices!$C$14 -> 0 | BC61: =SUM(AQ61:AZ61) -> 150586.51 | BD61: =AQ61/BC61 -> 0.99489752 | BE61: =AS61/BC61 -> 0 | BF61: Au (Ag)
A62: ON-MAIN-7607a50e | C62: Young-Davidson | E62: Ontario | F62: mining | G62: Underground, concentrator | H62: Free-miling | I62: NPRI+GHG+Land | J62: Energy | L62: Gold | M62: Au | N62: =prod_table_raw!N277 -> 2878047 | O62: =SUM(AD62:AP62) -> 0 | P62: =N62-O62 -> 2878047 | Q62: =prod_table_raw!N275 -> 5.7572578 | AF62: =S62/(concentrate_grade!$F$4/100) -> 0 | AG62: =T62/(concentrate_grade!$F$6/100) -> 0 | AQ62: =Q62*prices!$C$4 -> 298186.43 | AR62: =R62*prices!$C$11 -> 0 | AS62: =S62*prices!$C$3 -> 0 | AT62: =T62*prices!$C$8 -> 0 | AU62: =U62*prices!$C$2 -> 0 | AV62: =V62*prices!$C$7 -> 0 | AW62: =W62*prices!$C$13 -> 0 | AX62: =X62*prices!$C$6 -> 0 | AY62: =Y62*prices!$C$5 -> 0 | AZ62: =Z62*prices!$C$9 -> 0 | BA62: =AB62*prices!$C$12 -> 0 | BB62: =AC62*prices!$C$14 -> 0 | BC62: =SUM(AQ62:AZ62) -> 298186.43 | BD62: =AQ62/BC62 -> 1 | BE62: =AS62/BC62 -> 0 | BF62: Au
B63: GRP-0a2c0d69 | D63: Meadowbank complex | E63: Nunavut | F63: mining | G63: Open-pit, underground | H63: Free-miling | I63: NPRI+GHG+Land | J63: Energy | L63: Gold | M63: Au (Ag) | N63: =prod_table_raw!N160 -> 3842649 | O63: =SUM(AD63:AP63) -> 0 | P63: =N63-O63 -> 3842649 | Q63: =prod_table_raw!N161 -> 13.426312 | R63: =prod_table_raw!N162 -> 3.8879375 | AF63: =S63/(concentrate_grade!$F$4/100) -> 0 | AG63: =T63/(concentrate_grade!$F$6/100) -> 0 | AQ63: =Q63*prices!$C$4 -> 695390.78 | AR63: =R63*prices!$C$11 -> 2613.1994 | AS63: =S63*prices!$C$3 -> 0 | AT63: =T63*prices!$C$8 -> 0 | AU63: =U63*prices!$C$2 -> 0 | AV63: =V63*prices!$C$7 -> 0 | AW63: =W63*prices!$C$13 -> 0 | AX63: =X63*prices!$C$6 -> 0 | AY63: =Y63*prices!$C$5 -> 0 | AZ63: =Z63*prices!$C$9 -> 0 | BA63: =AB63*prices!$C$12 -> 0 | BB63: =AC63*prices!$C$14 -> 0 | BC63: =SUM(AQ63:AZ63) -> 698003.98 | BD63: =AQ63/BC63 -> 0.99625618 | BE63: =AS63/BC63 -> 0 | BF63: Au (Ag)
B64: GRP-0d911886 | D64: Porcupine complex | E64: Ontario | F64: mining | G64: Open-pit, underground | H64: Free-miling | I64: NPRI+GHG+Land | J64: Energy and materials | L64: Gold | M64: Au | N64: =prod_table_raw!N101 -> 2911000 | O64: =SUM(AD64:AP64) -> 0 | P64: =N64-O64 -> 2911000 | Q64: =prod_table_raw!N100 -> 8.08691 | AF64: =S64/(concentrate_grade!$F$4/100) -> 0 | AG64: =T64/(concentrate_grade!$F$6/100) -> 0 | AQ64: =Q64*prices!$C$4 -> 418846.42 | AR64: =R64*prices!$C$11 -> 0 | AS64: =S64*prices!$C$3 -> 0 | AT64: =T64*prices!$C$8 -> 0 | AU64: =U64*prices!$C$2 -> 0 | AV64: =V64*prices!$C$7 -> 0 | AW64: =W64*prices!$C$13 -> 0 | AX64: =X64*prices!$C$6 -> 0 | AY64: =Y64*prices!$C$5 -> 0 | AZ64: =Z64*prices!$C$9 -> 0 | BA64: =AB64*prices!$C$12 -> 0 | BB64: =AC64*prices!$C$14 -> 0 | BC64: =SUM(AQ64:AZ64) -> 418846.42 | BD64: =AQ64/BC64 -> 1 | BE64: =AS64/BC64 -> 0 | BF64: Au
B65: GRP-147b3123 | D65: Timmins Operation | E65: Ontario | F65: mining | G65: Underground, concentrator | H65: Free-miling | I65: NPRI+GHG+Land | J65: Energy | L65: Gold | M65: Au | N65: =prod_table_raw!N254 -> 1574000 | O65: =SUM(AD65:AP65) -> 0 | P65: =N65-O65 -> 1574000 | Q65: =prod_table_raw!N231 -> 1.2054783 | AF65: =S65/(concentrate_grade!$F$4/100) -> 0 | AG65: =T65/(concentrate_grade!$F$6/100) -> 0 | AQ65: =Q65*prices!$C$4 -> 62435.503 | AR65: =R65*prices!$C$11 -> 0 | AS65: =S65*prices!$C$3 -> 0 | AT65: =T65*prices!$C$8 -> 0 | AU65: =U65*prices!$C$2 -> 0 | AV65: =V65*prices!$C$7 -> 0 | AW65: =W65*prices!$C$13 -> 0 | AX65: =X65*prices!$C$6 -> 0 | AY65: =Y65*prices!$C$5 -> 0 | AZ65: =Z65*prices!$C$9 -> 0 | BA65: =AB65*prices!$C$12 -> 0 | BB65: =AC65*prices!$C$14 -> 0 | BC65: =SUM(AQ65:AZ65) -> 62435.503 | BD65: =AQ65/BC65 -> 1 | BE65: =AS65/BC65 -> 0 | BF65: Au
B66: GRP-14bfbb82 | D66: Seabee Gold Operation | E66: Saskatchewan | F66: mining | G66: Underground, concentrator | H66: Free-miling | I66: NPRI+GHG+Land | J66: Energy | L66: Gold | M66: Au | N66: =prod_table_raw!N229 -> 122000 | O66: =SUM(AD66:AP66) -> 0 | P66: =N66-O66 -> 122000 | AF66: =S66/(concentrate_grade!$F$4/100) -> 0 | AG66: =T66/(concentrate_grade!$F$6/100) -> 0 | AQ66: =Q66*prices!$C$4 -> 0 | AR66: =R66*prices!$C$11 -> 0 | AS66: =S66*prices!$C$3 -> 0 | AT66: =T66*prices!$C$8 -> 0 | AU66: =U66*prices!$C$2 -> 0 | AV66: =V66*prices!$C$7 -> 0 | AW66: =W66*prices!$C$13 -> 0 | AX66: =X66*prices!$C$6 -> 0 | AY66: =Y66*prices!$C$5 -> 0 | AZ66: =Z66*prices!$C$9 -> 0 | BA66: =AB66*prices!$C$12 -> 0 | BB66: =AC66*prices!$C$14 -> 0 | BC66: =SUM(AQ66:AZ66) -> 0 | BD66: =AQ66/BC66 -> #DIV/0! | BE66: =AS66/BC66 -> #DIV/0! | BF66: Au
B67: GRP-a13779f8 | D67: Snow Lake | E67: Manitoba | F67: mining | G67: Underground, concentrator | H67: Free-miling | I67: NPRI+Land | J67: Energy | L67: Gold, zinc, copper, silver | M67: Au (Zn, Cu, Ag) | N67: =prod_table_raw!N193+prod_table_raw!N130 -> 2123641 | O67: =SUM(AD67:AP67) -> 40513.333 | P67: =N67-O67 -> 2083127.7 | Q67: =prod_table_raw!N232 -> 5.8276451 | R67: =prod_table_raw!N233 -> 26.491566 | S67: =prod_table_raw!N235 -> 12154 | W67: =prod_table_raw!N234 -> 34642 | AF67: =S67/(concentrate_grade!$F$4/100) -> 40513.333 | AG67: =T67/(concentrate_grade!$F$6/100) -> 0 | AQ67: =Q67*prices!$C$4 -> 301832.01 | AR67: =R67*prices!$C$11 -> 17805.776 | AS67: =S67*prices!$C$3 -> 83862.6 | AT67: =T67*prices!$C$8 -> 0 | AU67: =U67*prices!$C$2 -> 0 | AV67: =V67*prices!$C$7 -> 0 | AW67: =W67*prices!$C$13 -> 89352.614 | AX67: =X67*prices!$C$6 -> 0 | AY67: =Y67*prices!$C$5 -> 0 | AZ67: =Z67*prices!$C$9 -> 0 | BA67: =AB67*prices!$C$12 -> 0 | BB67: =AC67*prices!$C$14 -> 0 | BC67: =SUM(AQ67:AZ67) -> 492853 | BD67: =AQ67/BC67 -> 0.61241792 | BE67: =AS67/BC67 -> 0.17015743 | BF67: Au (Zn, Cu, Ag)

Sheet README
A1: Title of the article:
A2: Authors:
A3: Affiliations:
A4: Journal:
A7: TAB_NAME | B7: DESCRIPTION | C7: SOURCE
A8: site_selection | B8: Describe the selection of sites and their associated data | C8: MetalliCan
A9: prod_data | B9: Ore processed and metal content in product for each sites | C9: MetalliCan
A10: fu
A11: EI | B11: Ecoquery link to some Ecoinvent activities
A15: For dore we assume 88% of Au, 10% of Si and 2% impurities

Sheet site_selection
A1: skip | B1: main_id | C1: facility_group_id | D1: facility_name | E1: facility_group_name | G1: province | H1: facility_type | I1: mining_processing_type | J1: commodities | K1: technosphere_biosphere_data? | L1: material_data? | M1: ghg_data? | N1: water_data? | O1: land_data? | P1: fg_aggregation? | Q1: archetypes | R1: comment
A2: extracted | B2: AB-MAIN-9fed34a8 | D2: AltaSteel | G2: Alberta | H2: manufacturing | I2: Electric arc furnace | J2: Steel | K2: has some biosphere flows only
A3: extracted | B3: AB-MAIN-d3a4aba9 | D3: The Cobalt Refinery Company Inc. | G3: Alberta | H3: manufacturing | I3: Refinery | J3: Nickel, cobalt, copper sulfide, ammonium sulfate | K3: has some biosphere flows only | M3: has GHG data | Q3: Co hydrometallurgical refinery
A4: extracted | B4: BC-MAIN-23155c25 | D4: Myra Falls | G4: British Columbia | H4: mining | I4: Underground | J4: Zinc, copper, silver, gold, lead | K4: has some biosphere flows only | Q4: Porphyry sulfide, flotation-based
A5: extracted | B5: BC-MAIN-3bb6b7cd | D5: Trail | G5: British Columbia | H5: manufacturing | I5: Smelter, refinery, plant | J5: Zinc, lead, bismuth, cadmium, indium, germanium, precious metals, liquid sulfur dioxide, sulfuric acid | K5: has some biosphere flows only | M5: has GHG data | N5: Withdrawal , consumption, discharged
A6: extracted | B6: BC-MAIN-3f490561 | D6: Mount Polley | G6: British Columbia | H6: mining | I6: Open-pit, concentrator | J6: Gold, copper, silver | K6: has some biosphere flows only | M6: has GHG data | Q6: Concentrator with flotation & dewatering; copper-gold concentrate shipped to smelter.
A7: extracted | B7: BC-MAIN-4724f4ba | D7: Elk | G7: British Columbia | H7: mining | I7: Open-pit | J7: Gold | K7: has some technosphere flows | Q7: Free-miling
A8: extracted | B8: BC-MAIN-599152a0 | D8: Copper Mountain | G8: British Columbia | H8: mining | I8: Open-pit, concentrator | J8: Copper, gold, silver | K8: has some technosphere and biosphere flows | M8: has GHG data. Scope 1-2 collected | Q8: Porphyry sulfide, flotation-based
A9: extracted | B9: BC-MAIN-6b4800fe | D9: Gibraltar | G9: British Columbia | H9: mining | I9: Open-pit, concentrator | J9: Copper, molybdenum, silver | K9: has some technosphere and biosphere flows | M9: has GHG data | N9: Withdrawal, consumption (freshwater only) | Q9: Porphyry sulfide, flotation-based
A10: extracted | B10: BC-MAIN-857b7b89 | D10: Brucejack | G10: British Columbia | H10: mining | I10: Underground, concentrator | J10: Gold, silver | K10: has some technosphere and biosphere flows | M10: Scope 1-2-3 collected | N10: Withdrawal
A11: extracted | B11: BC-MAIN-8eb8be0d | D11: Red Chris | G11: British Columbia | H11: mining | I11: Open-pit, concentrator | J11: Gold, copper, silver | K11: has some technosphere and biosphere flows | M11: has GHG data | Q11: Porphyry sulfide, flotation-based
A12: extracted | B12: BC-MAIN-aa76f6f2 | D12: New Afton | G12: British Columbia | H12: mining | I12: Underground, concentrator | J12: Gold, copper, silver | K12: has some technosphere and biosphere flows | L12: has some material flows | M12: Scope 1-2 collected | N12: Withdrawal , consumption, discharged | Q12: Porphyry sulfide, flotation-based
A13: extracted | B13: BC-MAIN-bf503b6b | D13: Highland Valley | G13: British Columbia | H13: mining | I13: Open-pit, concentrator | J13: Copper, silver, molybdenum | K13: has some biosphere flows only | M13: has GHG data | N13: Withdrawal , consumption, discharged | Q13: Porphyry sulfide, flotation-based
A14: extracted | B14: BC-MAIN-ed23117f | D14: Mount Milligan | G14: British Columbia | H14: mining | I14: Open-pit, concentrator | J14: Copper, gold, silver | K14: has some technosphere and biosphere flows, but no NPRI. Energy data in GHG | M14: Scope 1-2 collected | Q14: Porphyry sulfide, flotation-based
A15: extracted | B15: MB-MAIN-0898e255 | C15: GRP-a13779f8 | D15: Stall Lake | E15: Snow Lake | G15: Manitoba | H15: mining | I15: Concentrator | J15: Gold, zinc | K15: has some technosphere and biosphere flows | P15: Production at F level (need to aggregate production); biosphere flows only for New Britannia and Snow Lake
A16: extracted | B16: MB-MAIN-b4ca1426 | D16: Manitoba Mill | G16: Manitoba | H16: manufacturing | I16: Electric arc furnace | J16: Steel | K16: has some biosphere flows only
A17: extracted | B17: MB-MAIN-be5b3dc8 | C17: GRP-a13779f8 | D17: Lalor Lake | E17: Snow Lake | G17: Manitoba | H17: mining | I17: Underground | J17: Gold, zinc, copper, silver | K17: has some technosphere and biosphere flows | P17: Production at F level (need to aggregate production); biosphere flows only for New Britannia and Snow Lake
A18: extracted | B18: MB-MAIN-da0b5c3d | C18: GRP-a13779f8 | D18: New Britannia | E18: Snow Lake | G18: Manitoba | H18: mining | I18: Concentrator | J18: Gold, copper | K18: has some technosphere and biosphere flows | P18: Production at F level (need to aggregate production); biosphere flows only for New Britannia and Snow Lake
A19: extracted | B19: MB-MAIN-e0a6250e | D19: Thompson (T-1 and T-3) | G19: Manitoba | H19: mining | I19: Open-pit, underground, concentrator | J19: Nickel, cobalt, copper, platinum group metals, gold, silver | K19: has some biosphere flows only | M19: has GHG data | Q19: Porphyry sulfide, flotation-based
A20: extracted | B20: NL-MAIN-2d8801d6 | D20: Voisey’s Bay | G20: Newfoundland and Labrador | H20: mining | I20: Open-pit, underground, concentrator | J20: Nickel, copper, cobalt | K20: has some biosphere flows only | M20: has GHG data | Q20: Porphyry sulfide, flotation-based
A21: extracted | B21: NL-MAIN-842ba1b4 | D21: Nugget Pond | G21: Newfoundland and Labrador | H21: mining | I21: Concentrator | J21: Copper | K21: has some biosphere flows only
A22: extracted | B22: NL-MAIN-b64bae7a | D22: Scully | G22: Newfoundland and Labrador | H22: mining | I22: Open-pit, concentrator | J22: Iron | K22: has some technosphere and biosphere flows | M22: has GHG data. Scope 1-2 collected | Q22: Fe concentrator
A23: extracted | B23: NL-MAIN-c139de6d | D23: Ming | G23: Newfoundland and Labrador | H23: mining | I23: Underground | J23: Copper, gold, silver | K23: has some biosphere flows only | Q23: Porphyry sulfide, flotation-based
A24: extracted | B24: NL-MAIN-d9036091 | D24: Long Harbour | G24: Newfoundland and Labrador | H24: manufacturing | I24: Refinery | J24: Nickel, copper, cobalt | K24: has some biosphere flows only | M24: has GHG data | Q24: Ni hydrometallurgical refinery
A25: extracted | B25: NL-MAIN-dd723db4 | D25: Carol Lake | G25: Newfoundland and Labrador | H25: mining | I25: Open-pit, concentrator | J25: Iron | K25: has some technosphere and biosphere flows. Only total energy | M25: has GHG data. Scope1+2 (aggregated) collected | Q25: Fe concentrator + pellet plant
A26: extracted | B26: NL-MAIN-e09881ff | C26: GRP-2a663492 | D26: DSO (3 and 4) | E26: DSO | G26: Newfoundland and Labrador | H26: mining | I26: Open-pit | J26: Iron | K26: has some biosphere flows only | M26: has GHG data | P26: Aggregated production data at FG | Q26: Direct Shipping Ore
A27: extracted | B27: NT-MAIN-0ec39ce0 | D27: Diavik | G27: Northwest Territories | H27: mining | I27: Underground, plant | J27: Diamonds | K27: has some biosphere flows only
A28: extracted | B28: NT-MAIN-6c1d6ee6 | D28: Ekati | G28: Northwest Territories | H28: mining | I28: Underground, plant | J28: Diamonds | K28: has some biosphere flows only | M28: has GHG data
A29: extracted | B29: NT-MAIN-94e652a5 | D29: Gahcho Kué | G29: Northwest Territories | H29: mining | I29: Open-pit, plant | J29: Diamonds | K29: has some biosphere flows only
A30: extracted | B30: NU-MAIN-4ea8ac9d | C30: GRP-0a2c0d69 | D30: Amaruq | E30: Meadowbank complex | G30: Nunavut | H30: mining | I30: Open-pit, underground | J30: Gold | K30: has some technosphere and biosphere flows | P30: Aggregated production data at FG; biosphere flows only for Meadowbank | Q30: Free-miling
A31: extracted | B31: NU-MAIN-5154702a | D31: Mary River | G31: Nunavut | H31: mining | I31: Open-pit | J31: Iron | K31: has some biosphere flows only | M31: Scope 1 collected | Q31: Direct Shipping Ore
A32: extracted | B32: NU-MAIN-730aefe3 | C32: GRP-0a2c0d69 | D32: Meadowbank | E32: Meadowbank complex | G32: Nunavut | H32: mining | I32: Concentrator | J32: Gold | K32: has some technosphere and biosphere flows | M32: has GHG data | P32: Aggregated production data at FG; biosphere flows only for Meadowbank | Q32: Free-miling
A33: extracted | B33: NU-MAIN-8b0264c9 | D33: Meliadine | G33: Nunavut | H33: mining | I33: Open-pit, underground, concentrator | J33: Gold | K33: has some technosphere and biosphere flows | M33: has GHG data | N33: Withdrawal, consumption. Freshwater withdrawal intensity per ore processed and oz gold | Q33: Free-miling
A34: extracted | B34: ON-MAIN-020a683c | D34: Hamilton Works | G34: Ontario | H34: manufacturing | I34: Basic oxygen furnace | J34: Steel | K34: has some biosphere flows only
A35: extracted | B35: ON-MAIN-0aadf28f | D35: Rainy River | G35: Ontario | H35: mining | I35: Open-pit, underground, concentrator | J35: Gold, silver | K35: has some technosphere and biosphere flows | L35: has some material flows | M35: has GHG data. Scope 1-2 collected | N35: Withdrawal , consumption, discharged | Q35: Free-miling
A36: extracted | B36: ON-MAIN-1c674cd0 | C36: GRP-0d911886 | D36: Borden | E36: Porcupine complex | G36: Ontario | H36: mining | I36: Open-pit, underground | J36: Gold | K36: has some technosphere and biosphere flows | L36: has some material flows | P36: Aggregated production data at FG; biosphere flows only for Borden and Hoyle Pond
A37: extracted | B37: ON-MAIN-1f126a43 | D37: Macassa | G37: Ontario | H37: mining | I37: Underground, concentrator | J37: Gold, silver | K37: has some technosphere and biosphere flows | M37: has GHG data | N37: Withdrawal (freshwater separated) , consumption, discharged. Freshwater withdrawal intensity per ore processed and oz gold | Q37: Refractory?
A38: extracted | B38: ON-MAIN-206041d1 | C38: GRP-de097f20 | D38: Fraser | E38: Integrated Nickel Operations | G38: Ontario | H38: mining | I38: Underground | J38: Nickel, copper, platinum group metals, gold, cobalt, silver | K38: has some biosphere flows only | P38: Production at F level | Q38: Porphyry sulfide, flotation-based
A39: extracted | B39: ON-MAIN-21b6ab35 | D39: Whitby Mill | G39: Ontario | H39: manufacturing | I39: Electric arc furnace | J39: Steel | K39: has some biosphere flows only
A40: extracted | B40: ON-MAIN-28f3f0fc | C40: GRP-dc07540b | D40: Totten | E40: Sudbury Operation | G40: Ontario | H40: mining | I40: Underground | J40: Nickel, copper, platinum group metals, gold, silver, cobalt | K40: has some biosphere flows only | P40: Aggregated at FG | Q40: Porphyry sulfide, flotation-based
A41: extracted | B41: ON-MAIN-2e13aaa0 | D41: Port Colborne | G41: Ontario | H41: manufacturing | I41: Refinery | J41: Electrolytic cobalt, platinum group metals (in residues), copper oxide | K41: has some biosphere flows only | M41: has GHG data
A42: extracted | B42: ON-MAIN-387b06fe | D42: Welland Mill | G42: Ontario | H42: manufacturing | I42: Electric arc furnace | J42: Steel | K42: has some biosphere flows only
A43: extracted | B43: ON-MAIN-3b3e5365 | D43: Porcupine | G43: Ontario | H43: mining | I43: Concentrator | J43: Gold | K43: has some biosphere flows only | M43: has GHG data | N43: Water intensity
A44: extracted | B44: ON-MAIN-40ce0593 | C44: GRP-de097f20 | D44: Sudbury | E44: Integrated Nickel Operations | G44: Ontario | H44: manufacturing | I44: Smelter, plant | J44: Nickel-copper matte containing cobalt, gold, silver, platinum group metals | K44: has some biosphere flows only | M44: has GHG data | P44: Production at F level | Q44: Ni-Cu smelter
A45: extracted | B45: ON-MAIN-48fe2205 | C45: GRP-dc07540b | D45: Garson | E45: Sudbury Operation | G45: Ontario | H45: mining | I45: Underground | J45: Nickel, copper, platinum group metals, gold, silver, cobalt, selenium, tellurium | K45: has some biosphere flows only | P45: Aggregated at FG | Q45: Porphyry sulfide, flotation-based
A46: extracted | B46: ON-MAIN-4c35e094 | D46: ArcelorMittal Dofasco | G46: Ontario | H46: manufacturing | I46: Basic oxygen furnace, electric arc furnace | J46: Steel | K46: has some biosphere flows only
A47: extracted | B47: ON-MAIN-4e0734b5 | D47: Fox Complex | G47: Ontario | H47: mining | I47: Open-pit, underground, concentrator | J47: Gold | K47: has some biosphere flows only | Q47: Free-miling
A48: extracted | B48: ON-MAIN-52224e1e | C48: GRP-dc07540b | D48: Creighton | E48: Sudbury Operation | G48: Ontario | H48: mining | I48: Underground | J48: Nickel, copper, platinum group metals, gold, silver, cobalt, selenium, tellurium | K48: has some biosphere flows only | P48: Aggregated at FG | Q48: Porphyry sulfide, flotation-based
A49: extracted | B49: ON-MAIN-538513cd | C49: GRP-0d911886 | D49: Hoyle Pond | E49: Porcupine complex | G49: Ontario | H49: mining | I49: Underground | J49: Gold | K49: has some technosphere and biosphere flows | L49: has some material flows | P49: Aggregated production data at FG; biosphere flows only for Borden and Hoyle Pond
A50: extracted | B50: ON-MAIN-63b394c3 | C50: GRP-dc07540b | D50: Copper Cliff Complex | E50: Sudbury Operation | G50: Ontario | H50: manufacturing | I50: Smelter, refinery, plant | J50: Nickel (oxide sinter, pellets, powder, sulfide), copper cathodes, gold, silver, selenium cake, tellurium dioxide cake, platinum group metals (in residues), liquid sulfur dioxide, sulfuric acid | K50: has some biosphere flows only | M50: has GHG data (aggregated) | P50: Aggregated at FG | Q50: Ni-Cu metallurgical complex
A51: extracted | B51: ON-MAIN-687b8c8d | D51: Island | G51: Ontario | H51: mining | I51: Underground, concentrator | J51: Gold | K51: has some technosphere and biosphere flows | L51: has some material flows | M51: has GHG data. Scope 1-2-3 collected | N51: Withdrawal , consumption, discharged | Q51: Free-miling
A52: extracted | B52: ON-MAIN-6bd6cc80 | D52: Kingston Operation | G52: Ontario | H52: manufacturing | K52: has some biosphere flows only
A53: extracted | B53: ON-MAIN-6e9b2449 | C53: GRP-dc07540b | D53: Coleman | E53: Sudbury Operation | G53: Ontario | H53: mining | I53: Underground | J53: Nickel, copper, platinum group metals, gold, silver, cobalt, selenium, tellurium | K53: has some biosphere flows only | P53: Aggregated at FG | Q53: Porphyry sulfide, flotation-based
A54: extracted | B54: ON-MAIN-6e9be24e | D54: Hemlo (Williams) | G54: Ontario | H54: mining | I54: Open-pit, underground, concentrator | J54: Gold | K54: has some technosphere and biosphere flows | M54: has GHG data. Scope 1-2 collected | N54: Withdrawal (high quality), consumption, discharged (high quality). Withdrawal and consumption intensity per ore processed and oz gold
A55: extracted | B55: ON-MAIN-7001a391 | D55: McCreedy West | G55: Ontario | H55: mining | I55: Underground | J55: Copper, nickel, platinum group metals, gold, silver, cobalt | K55: has some biosphere flows only
A56: extracted | B56: ON-MAIN-7607a50e | D56: Young-Davidson | G56: Ontario | H56: mining | I56: Underground, concentrator | J56: Gold | K56: has some technosphere and biosphere flows | L56: has some material flows | M56: has GHG data. Scope 1-2-3 collected | N56: Withdrawal , consumption, discharged | Q56: Free-miling
A57: extracted | B57: ON-MAIN-7f050560 | D57: Red Lake | G57: Ontario | H57: mining | I57: Underground, concentrator | J57: Gold, silver | K57: has some technosphere and biosphere flows | M57: Scope 1-2 collected | N57: Withdrawal , consumption, discharged | Q57: Refractory?
A58: extracted | B58: ON-MAIN-8629a493 | C58: GRP-0d911886 | D58: Hollinger | E58: Porcupine complex | G58: Ontario | H58: mining | I58: Open-pit | J58: Gold | K58: has some technosphere and biosphere flows | P58: Aggregated production data at FG; biosphere flows only for Borden and Hoyle Pond
A59: extracted | B59: ON-MAIN-8825d90d | D59: Magino | G59: Ontario | H59: mining | I59: Open-pit, concentrator | J59: Gold, silver | K59: has some biosphere flows only | Q59: Free-miling
A60: extracted | B60: ON-MAIN-a3c56a83 | D60: Lac des Iles | G60: Ontario | H60: mining | I60: Open-pit, underground, concentrator | J60: Platinum group metals, gold, nickel, copper, cobalt | K60: has some technosphere and biosphere flows | M60: has GHG data. Scope 1-2 collected | N60: Withdrawal , consumption, discharged | Q60: Porphyry sulfide, flotation-based
A61: extracted | B61: ON-MAIN-aeafbb59 | D61: Detour Lake | G61: Ontario | H61: mining | I61: Open-pit, concentrator | J61: Gold | K61: has some technosphere and biosphere flows | M61: has GHG data | N61: Withdrawal (freshwater separated), consumption, discharged. Freshwater withdrawal intensity per ore processed and oz gold | Q61: Free-miling
A62: extracted | B62: ON-MAIN-b2e5c9bb | D62: Lake Erie Works | G62: Ontario | H62: manufacturing | I62: Basic oxygen furnace | J62: Steel | K62: has some biosphere flows only
A63: extracted | B63: ON-MAIN-bddeaef0 | D63: Cambridge Mill | G63: Ontario | H63: manufacturing | I63: Electric arc furnace | J63: Steel | K63: has some biosphere flows only
A64: extracted | B64: ON-MAIN-bfbcd72e | C64: GRP-147b3123 | D64: Bell Creek | E64: Timmins Operation | G64: Ontario | H64: mining | I64: Underground, concentrator | J64: Gold | K64: has some technosphere and biosphere flows | P64: Aggregated production data at FG; biosphere flows for Bell Creek and Timmins West (need to aggregate biosphere flows)
A65: extracted | B65: ON-MAIN-cb85213a | D65: Eagle River | G65: Ontario | H65: mining | I65: Underground, concentrator | J65: Gold | K65: has some technosphere and biosphere flows | M65: has GHG data. Scope 1-2 collected | N65: Withdrawal (freshwater separated), consumption, discharged. Water intensity per ore processed and oz gold | Q65: Free-miling
A66: extracted | B66: ON-MAIN-de2f9639 | C66: GRP-dc07540b | D66: Clarabelle | E66: Sudbury Operation | G66: Ontario | H66: mining | I66: Concentrator | J66: Nickel, copper, platinum group metals, gold, silver, cobalt, selenium, tellurium | K66: has some biosphere flows only | P66: Aggregated at FG | Q66: Porphyry sulfide, flotation-based
A67: extracted | B67: ON-MAIN-e928d96a | D67: Brampton | G67: Ontario | H67: manufacturing | I67: Refinery | J67: Gold, silver | K67: has some biosphere flows only
A68: extracted | B68: ON-MAIN-eab8c362 | D68: Algoma Steel | G68: Ontario | H68: manufacturing | I68: Basic oxygen furnace | J68: Steel | K68: has some biosphere flows only
A69: extracted | B69: ON-MAIN-ed85ac94 | C69: GRP-de097f20 | D69: Strathcona | E69: Integrated Nickel Operations | G69: Ontario | H69: mining | I69: Concentrator | J69: Nickel, copper, platinum group metals, gold, silver, cobalt, selenium, tellurium | K69: has some biosphere flows only | M69: has GHG data | P69: Production at F level | Q69: Porphyry sulfide, flotation-based
A70: extracted | B70: ON-MAIN-f080c409 | C70: GRP-dc07540b | D70: Copper Cliff Complex | E70: Sudbury Operation | G70: Ontario | H70: mining | I70: Underground | J70: Nickel, copper, platinum group metals, gold, silver, cobalt, selenium, tellurium | K70: has some biosphere flows only | M70: has GHG data (aggregated) | P70: Aggregated at FG | Q70: Porphyry sulfide, flotation-based
A71: extracted | B71: ON-MAIN-f3e6ff08 | C71: GRP-147b3123 | D71: Timmins West | E71: Timmins Operation | G71: Ontario | H71: mining | I71: Underground | J71: Gold | K71: has some technosphere and biosphere flows | M71: has GHG data | P71: Aggregated production data at FG; biosphere flows for Bell Creek and Timmins West (need to aggregate biosphere flows)
A72: extracted | B72: ON-MAIN-f8313ebd | D72: Kidd Creek | G72: Ontario | H72: mining | I72: Underground, concentrator | J72: Copper, zinc, silver, selenium, indium | K72: has some biosphere flows only | M72: has GHG data | Q72: Porphyry sulfide, flotation-based
A73: extracted | B73: ON-MAIN-fc6f1a44 | D73: Ivaco Rolling Mills | G73: Ontario | H73: manufacturing | I73: Electric arc furnace | J73: Steel | K73: has some biosphere flows only
A74: extracted | B74: ON-MAIN-fcb287a4 | C74: GRP-de097f20 | D74: Nickel Rim South | E74: Integrated Nickel Operations | G74: Ontario | H74: mining | I74: Underground | J74: Nickel, copper, cobalt, platinum group metals, gold | K74: has some biosphere flows only | P74: Production at F level | Q74: Porphyry sulfide, flotation-based
A75: extracted | B75: ON-MAIN-fefeaee4 | D75: Musselwhite | G75: Ontario | H75: mining | I75: Underground, concentrator | J75: Gold, silver | K75: has some technosphere and biosphere flows | L75: has some material flows | M75: has GHG data. Scope 1-2-3 collected | N75: Withdrawal , consumption, discharged. Water intensity | Q75: Free-miling
A76: extracted | B76: QC-MAIN-01c1e81f | C76: GRP-677b5973 | D76: Grande-Baie | E76: Saguenay–Lac-Saint-Jean Operations | G76: Quebec | H76: manufacturing | I76: Smelter | J76: Aluminum (pure or alloyed) | K76: has some biosphere flows only | P76: Production at F level for all facilities
A77: extracted | B77: QC-MAIN-02884fb5 | D77: Westwood-Doyon | G77: Quebec | H77: mining | I77: Underground, concentrator | J77: Gold, silver | K77: has some technosphere and biosphere flows | L77: has some material flows | M77: has GHG data. Scope 1-2 collected | N77: Withdrawal (freshwater only), consumption, discharged | Q77: Free-miling
A78: extracted | B78: QC-MAIN-084bd95c | C78: GRP-1402249f | D78: Mont-Wright | E78: AMMC | G78: Quebec | H78: mining | I78: Open-pit, concentrator | J78: Iron | K78: has some biosphere flows only | M78: has GHG data | P78: Production data at F level only for Fire Lake and Mont-Wright | Q78: Fe concentrator + pellet plant
A79: extracted | B79: QC-MAIN-089f3c60 | D79: Bloom Lake | G79: Quebec | H79: mining | I79: Open-pit | J79: Iron | K79: has some biosphere flows only | M79: has GHG data | Q79: Magnetite concentrator
A80: extracted | B80: QC-MAIN-1eee4ace | C80: GRP-7a9ba115 | D80: Contrecœur East | E80: Contrecoeur | G80: Quebec | H80: manufacturing | I80: Electric arc furnace | J80: Steel | K80: has some biosphere flows only | P80: Aggregated production at FG
A81: extracted | B81: QC-MAIN-3032c251 | D81: Renard | G81: Quebec | H81: mining | I81: Open-pit, underground, concentrator | J81: Diamonds | K81: has some biosphere flows only
A82: extracted | B82: QC-MAIN-30c1828c | C82: GRP-b48ec279 | D82: Horne | E82: CCR | G82: Quebec | H82: manufacturing | I82: Smelter | J82: Copper anodes, precious metals, sulfuric acid | K82: has some biosphere flows only | M82: has GHG data | P82: Production available for Horne only
A83: extracted | B83: QC-MAIN-33c09b8b | C83: GRP-1402249f | D83: Fire Lake | E83: AMMC | G83: Quebec | H83: mining | I83: Open-pit | J83: Iron | K83: has some biosphere flows only | M83: has GHG data | P83: Production data at F level only for Fire Lake and Mont-Wright | Q83: Fe concentrator feed
A84: extracted | B84: QC-MAIN-3aa117d8 | C84: GRP-677b5973 | D84: Alma | E84: Saguenay–Lac-Saint-Jean Operations | G84: Quebec | H84: manufacturing | I84: Smelter | J84: Aluminum (pure or alloyed) | K84: has some biosphere flows only | M84: has GHG data | P84: Production at F level for all facilities
A85: extracted | B85: QC-MAIN-3e146840 | C85: GRP-25483238 | D85: Rio Tinto Iron and Titanium | E85: RTFT Operations Quebec | G85: Quebec | H85: manufacturing | I85: Electric arc furnace | J85: Steel, titanium dioxide, scandium | K85: has some biosphere flows only | P85: Production at F level only for Rio Tinto Iron and Titanium
A86: extracted | B86: QC-MAIN-529c96b4 | C86: GRP-b48ec279 | D86: CCR | E86: CCR | G86: Quebec | H86: manufacturing | I86: Refinery | J86: Copper (cathodes), gold, silver, tellurium, selenium, nickel sulfate, copper sulfate, platinum group metals | K86: has some biosphere flows only | M86: has GHG data | P86: Production available for Horne only | Q86: Cu electrorefinery
A87: extracted | B87: QC-MAIN-52c01ae4 | D87: Baie-Comeau | G87: Quebec | H87: manufacturing | I87: Smelter | J87: Aluminum (pure or alloyed) | K87: has some biosphere flows only
A88: extracted | B88: QC-MAIN-5398dfac | D88: Elkem Chicoutimi | G88: Quebec | H88: manufacturing | J88: Ferrosilicon | K88: has some biosphere flows only
A89: extracted | B89: QC-MAIN-5ce331b8 | D89: Nunavik Nickel | G89: Quebec | H89: mining | I89: Open-pit, underground, concentrator | J89: Nickel, copper, platinum group metals, cobalt | K89: has some biosphere flows only | M89: Scope 1-2 collected | N89: Water intensity per ore | Q89: Porphyry sulfide, flotation-based
A90: extracted | B90: QC-MAIN-6dc537e6 | D90: Éléonore | G90: Quebec | H90: mining | I90: Underground, concentrator | J90: Gold | K90: has some technosphere and biosphere flows | L90: has some material flows | M90: Scope 1-2-3 collected | N90: Withdrawal, consumption, discharged. Water intensity per ore processed and oz gold | Q90: Free-miling
A91: extracted | B91: QC-MAIN-844dcc47 | C91: GRP-7a9ba115 | D91: Contrecœur West | E91: Contrecoeur | G91: Quebec | H91: manufacturing | I91: Electric arc furnace | J91: Steel | K91: has some biosphere flows only | P91: Aggregated production at FG
A92: extracted | B92: QC-MAIN-8d6616b4 | C92: GRP-677b5973 | D92: Alouette | E92: Saguenay–Lac-Saint-Jean Operations | G92: Quebec | H92: manufacturing | I92: Smelter | J92: Aluminum (pure) | K92: has some biosphere flows only | M92: has GHG data | P92: Production at F level for all facilities
A93: extracted | B93: QC-MAIN-92628f16 | C93: GRP-677b5973 | D93: Vaudreuil | E93: Saguenay–Lac-Saint-Jean Operations | G93: Quebec | H93: manufacturing | I93: Refinery | J93: Alumina | K93: has some biosphere flows only | M93: has GHG data | P93: Production at F level for all facilities
A94: extracted | B94: QC-MAIN-9de9bb0d | D94: Kiena | G94: Quebec | H94: mining | I94: Open-pit, concentrator | J94: Gold | K94: has some technosphere and biosphere flows | M94: Scope 1-2 collected | N94: Withdrawal (freshwater separated) , consumption, discharged. Water intensity | Q94: Free-miling
A95: extracted | B95: QC-MAIN-a555d9b9 | D95: Niobec | G95: Quebec | H95: mining | I95: Underground, concentrator | J95: Niobium | K95: has some biosphere flows only | M95: has GHG data
A96: extracted | B96: QC-MAIN-a97821c0 | D96: Raglan | G96: Quebec | H96: mining | I96: Underground, concentrator | J96: Nickel, platinum group metals, copper, cobalt, gold, silver | K96: has some biosphere flows only | M96: has GHG data | Q96: Porphyry sulfide, flotation-based
A97: extracted | B97: QC-MAIN-b86f7d07 | D97: Casa Berardi | G97: Quebec | H97: mining | I97: Open-pit, underground, concentrator | J97: Gold, silver | K97: has some technosphere and biosphere flows | M97: Scope 1-2 collected | Q97: Free-miling
A98: extracted | B98: QC-MAIN-b8c826a2 | C98: GRP-2a663492 | D98: DSO (Goodwood) | E98: DSO | G98: Quebec | H98: mining | I98: Open-pit | J98: Iron | K98: has some biosphere flows only | M98: has GHG data | P98: Aggregated production data at FG | Q98: Direct Shipping Ore
A99: extracted | B99: QC-MAIN-c0660aec | D99: Goldex | G99: Quebec | H99: mining | I99: Underground, concentrator | J99: Gold, silver | K99: has some technosphere and biosphere flows | M99: has GHG data | N99: Withdrawal (freshwater separated), consumption, discharged. Freshwater withdrawal intensity per ore processed and oz gold | Q99: Free-miling + significant gravite dore + sometimes some flotation
A100: extracted | B100: QC-MAIN-c0e3a48b | C100: GRP-677b5973 | D100: Laterrière | E100: Saguenay–Lac-Saint-Jean Operations | G100: Quebec | H100: manufacturing | I100: Smelter | J100: Aluminum (pure or alloyed) | K100: has some biosphere flows only | P100: Production at F level for all facilities
...

Sheet prod_data
A1: main_id | B1: facility_group_id | C1: facility_name | D1: facility_group_name | E1: province | F1: facility_type | G1: mining_processing_type | H1: npv | I1: archetypes | J1: archetypes_detailed | K1: biosphere_data? | L1: technosphere_data? | M1: land_data? | N1: ta_data? | O1: infer_energy_data | P1: infer_land_data | Q1: infer_material_data | R1: infer_cement_data | S1: infer_explosives_data | T1: infer_water_data | U1: commodities | V1: Create_LCI? | W1: Main_product | X1: Stream | Y1: ore_processed_t | Z1: dore_t_mass | AA1: conc_t_mass | AB1: tailings_t_mass | AC1: dore_yield | AD1: concentrate_yield | AE1: % tailings | AF1: Au_t | AG1: Ag_t | AH1: Cu_t | AI1: Ni_t | AJ1: Co_t | AK1: Mo_t | AL1: Zn_t | AM1: Pb_t | AN1: Fe_t | AO1: Pt_t | AP1: Pd_t | AQ1: U_t | AR1: Nb_t | AS1: Cu_conc | AT1: Ni_conc | AU1: Mo_conc | AV1: Zn_conc | AW1: Pb_conc | AX1: Fe_conc | AY1: Pt_conc | AZ1: Pd_conc | BA1: U_conc | BB1: Nb_conc | BC1: Au_conc
A2: QC-MAIN-089f3c60 | C2: Bloom Lake | E2: Quebec | F2: mining | G2: Open-pit | I2: Magnetite concentrator | J2: Only mining | K2: NPRI+GHG+Land | L2: (NRJ could be back calculated with GHG) | M2: 15702688 | N2: Concentrate grade | O2: Yes | Q2: Yes | R2: Yes | S2: Yes | T2: Yes | U2: Iron | V2: No (iron) | W2: Fe | X2: Fe conc. | Y2: =prod_table_raw!N11 -> 11187000 | AB2: =Y2-Z2-AA2 -> 11187000 | AC2: =Z2/Y2 -> 0 | AD2: =AA2/Y2 -> 0 | AE2: =1-(Z2+AA2)/AB2 -> 1 | AS2: =AH2/(concentrate_grade!$F$4/100) -> 0 | AT2: =AI2/(concentrate_grade!$F$6/100) -> 0 | AU2: =AK2/(concentrate_grade!$F$5/100) -> 0 | AV2: =AL2/(concentrate_grade!$F$9/100) -> 0 | AW2: =AM2/(concentrate_grade!$F$8/100) -> 0 | BB2: =AR2/concentrate_grade!#REF! -> #REF! | BC2: =Z2 -> 0
A3: BC-MAIN-857b7b89 | C3: Brucejack | E3: British Columbia | F3: mining | G3: Underground, concentrator | H3: Low and High Shrub Tundra | I3: Au–Ag free-milling | J3: Might contain refractory ore? Big GHG outlier | K3: NPRI+GHG+Water | L3: Energy | N3: HG, RR | P3: Yes | Q3: Yes | R3: Yes | S3: Yes | T3: No | U3: Gold, silver | V3: Yes | W3: Au | X3: Au-Ag doré | Y3: =prod_table_raw!N13 -> 166000 | Z3: =(AF3+AG3)/0.98 -> 0.92040969 | AB3: =Y3-Z3-AA3 -> 165999.08 | AC3: =Z3/Y3 -> 5.5446367e-06 | AD3: =AA3/Y3 -> 0 | AE3: =1-(Z3+AA3)/AB3 -> 0.99999446 | AF3: =prod_table_raw!N14 -> 0.9020015 | AS3: =AH3/(concentrate_grade!$F$4/100) -> 0 | AT3: =AI3/(concentrate_grade!$F$6/100) -> 0 | AU3: =AK3/(concentrate_grade!$F$5/100) -> 0 | AV3: =AL3/(concentrate_grade!$F$9/100) -> 0 | AW3: =AM3/(concentrate_grade!$F$8/100) -> 0 | BB3: =AR3/concentrate_grade!#REF! -> #REF! | BC3: =Z3 -> 0.92040969
A4: QC-MAIN-de3d8b7b | C4: Canadian Electrolytic Zinc Limited (CEZinc) | E4: Quebec | F4: manufacturing | G4: Refinery | I4: Zn refinery | K4: Land | M4: 1248584.7 | Q4: Yes | R4: Yes | T4: Yes | U4: Lead, zinc | V4: No | W4: Zn (Pb) | AB4: =Y4-Z4-AA4 -> 0 | AL4: =prod_table_raw!N16 -> 752600 | AM4: =prod_table_raw!N15 -> 244600 | AS4: =AH4/(concentrate_grade!$F$4/100) -> 0 | AT4: =AI4/(concentrate_grade!$F$6/100) -> 0 | AU4: =AK4/(concentrate_grade!$F$5/100) -> 0 | AW4: =AM4/(concentrate_grade!$F$8/100) -> 407666.67 | BC4: =Z4 -> 0
A5: QC-MAIN-e7e6a960 | C5: Canadian Malartic | E5: Quebec | F5: mining | G5: Open-pit, concentrator | H5: Cool Mixed Forest | I5: Au–Ag free-milling | J5: Might contain refractory ore? | K5: NPRI+GHG+Land | L5: Energy | M5: 19028718 | N5: HG, RR, SR for Au | Q5: Yes | R5: Yes | S5: Yes | T5: m3/t | U5: Gold, silver | V5: Yes | W5: Au (Ag) | X5: Au-Ag doré | Y5: =prod_table_raw!N17 -> 17332900 | Z5: =(AF5+AG5)/0.98 -> 29.039085 | AB5: =Y5-Z5-AA5 -> 17332871 | AC5: =Z5/Y5 -> 1.6753737e-06 | AD5: =AA5/Y5 -> 0 | AE5: =1-(Z5+AA5)/AB5 -> 0.99999832 | AF5: =prod_table_raw!N18 -> 18.785114 | AG5: =prod_table_raw!N19 -> 9.6731885 | AS5: =AH5/(concentrate_grade!$F$4/100) -> 0 | AT5: =AI5/(concentrate_grade!$F$6/100) -> 0 | AU5: =AK5/(concentrate_grade!$F$5/100) -> 0 | AV5: =AL5/(concentrate_grade!$F$9/100) -> 0 | AW5: =AM5/(concentrate_grade!$F$8/100) -> 0 | BB5: =AR5/concentrate_grade!#REF! -> #REF! | BC5: =Z5 -> 29.039085
A6: NL-MAIN-dd723db4 | C6: Carol Lake | E6: Newfoundland and Labrador | F6: mining | G6: Open-pit, concentrator | H6: Cold Evergreen Needleleaf Forest | I6: Fe concentrator + pellet plant | K6: NPRI+GHG+Land | L6: Energy | M6: 26104649 | Q6: Yes | R6: Yes | S6: Yes | T6: Yes | U6: Iron | V6: No (iron) | W6: Fe | X6: Fe conc., Fe pellets | Y6: =prod_table_raw!N21 -> 16478000 | AB6: =Y6-Z6-AA6 -> 16478000 | AC6: =Z6/Y6 -> 0 | AD6: =AA6/Y6 -> 0 | AE6: =1-(Z6+AA6)/AB6 -> 1 | AS6: =AH6/(concentrate_grade!$F$4/100) -> 0 | AT6: =AI6/(concentrate_grade!$F$6/100) -> 0 | AU6: =AK6/(concentrate_grade!$F$5/100) -> 0 | AV6: =AL6/(concentrate_grade!$F$9/100) -> 0 | AW6: =AM6/(concentrate_grade!$F$8/100) -> 0 | BB6: =AR6/concentrate_grade!#REF! -> #REF! | BC6: =Z6 -> 0
A7: QC-MAIN-b86f7d07 | C7: Casa Berardi | E7: Quebec | F7: mining | G7: Open-pit, underground, concentrator | H7: Cool Mixed Forest | I7: Au–Ag free-milling | K7: NPRI+GHG+Land | L7: Energy and explosives | M7: 6202897 | N7: HG | R7: Yes | T7: Yes | U7: Gold, silver | V7: Yes | W7: Au | X7: Au-Ag doré | Y7: =prod_table_raw!N24 -> 1361450 | Z7: =(AF7+AG7)/0.98 -> 3.5165998 | AB7: =Y7-Z7-AA7 -> 1361446.5 | AC7: =Z7/Y7 -> 2.5829812e-06 | AD7: =AA7/Y7 -> 0 | AE7: =1-(Z7+AA7)/AB7 -> 0.99999742 | AF7: =prod_table_raw!N22 -> 2.6935631 | AG7: =prod_table_raw!N23 -> 0.7527047 | AS7: =AH7/(concentrate_grade!$F$4/100) -> 0 | AT7: =AI7/(concentrate_grade!$F$6/100) -> 0 | AU7: =AK7/(concentrate_grade!$F$5/100) -> 0 | AV7: =AL7/(concentrate_grade!$F$9/100) -> 0 | AW7: =AM7/(concentrate_grade!$F$8/100) -> 0 | BB7: =AR7/concentrate_grade!#REF! -> #REF! | BC7: =Z7 -> 3.5165998
A8: ON-MAIN-f080c409 | B8: GRP-dc07540b | C8: Copper Cliff Complex (mine) | D8: Sudbury Operation | E8: Ontario | F8: mining | G8: Underground | H8: Cool Mixed Forest | I8: Ni–Cu sulfide | J8: Only mining | K8: NPRI+Land | M8: 21591249 | Q8: Yes | R8: Yes | S8: Yes | T8: Yes | U8: Nickel, copper, platinum group metals, gold, silver, cobalt, selenium, tellurium | V8: Not sure (Vale Sudbury) | W8: Ni+Cu | X8: Ni-Cu bulk conc. | Y8: =prod_table_raw!N30 -> 748000 | AA8: =AI8/(concentrate_grade!$F$6/100) -> 54693.75 | AB8: =Y8-Z8-AA8 -> 693306.25 | AC8: =Z8/Y8 -> 0 | AD8: =AA8/Y8 -> 0.073119987 | AE8: =1-(Z8+AA8)/AB8 -> 0.9211117 | AH8: =prod_table_raw!N29 -> 10098 | AI8: =prod_table_raw!N28 -> 8751 | AT8: =AI8/(concentrate_grade!$F$6/100) -> 54693.75 | AU8: =AK8/(concentrate_grade!$F$5/100) -> 0 | AV8: =AL8/(concentrate_grade!$F$9/100) -> 0 | AW8: =AM8/(concentrate_grade!$F$8/100) -> 0 | BB8: =AR8/concentrate_grade!#REF! -> #REF! | BC8: =Z8 -> 0
A9: ON-MAIN-63b394c3 | B9: GRP-dc07540b | C9: Copper Cliff Complex (refinery) | D9: Sudbury Operation | E9: Ontario | F9: manufacturing | G9: Smelter, refinery, plant | H9: Cool Mixed Forest | I9: Cu-Ni smelter and refinery | K9: NPRI+GHG+Land | L9: (NRJ could be back calculated with GHG) | M9: 3963061.6 | O9: Yes | Q9: Yes | R9: Yes | T9: Yes | U9: Nickel (oxide sinter, pellets, powder, sulfide), copper cathodes, gold, silver, selenium cake, tellurium dioxide cake, platinum group metals (in residues), liquid sulfur dioxide, sulfuric acid | V9: Not sure (Vale Sudbury) | W9: Ni+Cu | X9: Refined Ni+Cu | AB9: =Y9-Z9-AA9 -> 0 | AH9: =prod_table_raw!N31 -> 57900 | AI9: =prod_table_raw!N32 -> 38200 | AU9: =AK9/(concentrate_grade!$F$5/100) -> 0 | AW9: =AM9/(concentrate_grade!$F$8/100) -> 0 | BC9: =Z9 -> 0
A10: BC-MAIN-599152a0 | C10: Copper Mountain | E10: British Columbia | F10: mining | G10: Open-pit, concentrator | H10: Cool Evergreen Needleleaf Forest | I10: Cu Porphyry | K10: NPRI+GHG+Land | L10: Energy (but sanity issue) | M10: 13233210 | N10: HG (Au, Ag, Cu), RR, SR | O10: Yes | Q10: Yes | R10: Yes | S10: Yes | T10: Yes | U10: Copper, gold, silver | V10: Yes | W10: Cu (Au, Ag) | X10: Cu conc. | Y10: =prod_table_raw!N36 -> 6862152 | AA10: =AH10/(concentrate_grade!$F$4/100) -> 63500 | AB10: =Y10-Z10-AA10 -> 6798652 | AC10: =Z10/Y10 -> 0 | AD10: =AA10/Y10 -> 0.0092536569 | AE10: =1-(Z10+AA10)/AB10 -> 0.99065991 | AF10: =prod_table_raw!N35 -> 0.27520377 | AG10: =prod_table_raw!N38 -> 6.7893342 | AH10: =prod_table_raw!N39 -> 19050 | AS10: =AH10/(concentrate_grade!$F$4/100) -> 63500 | AT10: =AI10/(concentrate_grade!$F$6/100) -> 0 | AU10: =AK10/(concentrate_grade!$F$5/100) -> 0 | AV10: =AL10/(concentrate_grade!$F$9/100) -> 0 | AW10: =AM10/(concentrate_grade!$F$8/100) -> 0 | BB10: =AR10/concentrate_grade!#REF! -> #REF! | BC10: =Z10 -> 0
A11: ON-MAIN-52224e1e | B11: GRP-dc07540b | C11: Creighton | D11: Sudbury Operation | E11: Ontario | F11: mining | G11: Underground | H11: Cool Mixed Forest | I11: Ni–Cu sulfide | J11: Only mining | K11: NPRI+land | M11: 1929968.2 | N11: HG | Q11: Yes | R11: Yes | S11: Yes | T11: Yes | U11: Nickel, copper, platinum group metals, gold, silver, cobalt, selenium, tellurium | V11: Not sure (Vale Sudbury) | W11: Ni+Cu | X11: Ni-Cu bulk conc. | Y11: =prod_table_raw!N44 -> 433000 | AA11: =AI11/(concentrate_grade!$F$6/100) -> 70900 | AB11: =Y11-Z11-AA11 -> 362100 | AC11: =Z11/Y11 -> 0 | AD11: =AA11/Y11 -> 0.16374134 | AE11: =1-(Z11+AA11)/AB11 -> 0.80419774 | AH11: =prod_table_raw!N43 -> 9396 | AI11: =prod_table_raw!N42 -> 11344 | AT11: =AI11/(concentrate_grade!$F$6/100) -> 70900 | AU11: =AK11/(concentrate_grade!$F$5/100) -> 0 | AV11: =AL11/(concentrate_grade!$F$9/100) -> 0 | AW11: =AM11/(concentrate_grade!$F$8/100) -> 0 | BB11: =AR11/concentrate_grade!#REF! -> #REF! | BC11: =Z11 -> 0
A12: ON-MAIN-aeafbb59 | C12: Detour Lake | E12: Ontario | F12: mining | G12: Open-pit, concentrator | H12: Cool Evergreen Needleleaf Forest | I12: Au–Ag free-milling | K12: NPRI+GHG+Land | L12: Energy | M12: 10276967 | N12: SR | Q12: Yes | R12: Yes | T12: m3/t | U12: Gold | V12: Yes | W12: Au (Ag) | X12: Au-Ag doré | Y12: =prod_table_raw!N48 -> 25434854 | Z12: =(AF12+AG12)/0.98 -> 24.008284 | AB12: =Y12-Z12-AA12 -> 25434829 | AC12: =Z12/Y12 -> 9.439128e-07 | AD12: =AA12/Y12 -> 0 | AE12: =1-(Z12+AA12)/AB12 -> 0.99999906 | AF12: =prod_table_raw!N49 -> 21.070942 | AG12: =prod_table_raw!N50 -> 2.4571765 | AS12: =AH12/(concentrate_grade!$F$4/100) -> 0 | AT12: =AI12/(concentrate_grade!$F$6/100) -> 0 | AU12: =AK12/(concentrate_grade!$F$5/100) -> 0 | AV12: =AL12/(concentrate_grade!$F$9/100) -> 0 | AW12: =AM12/(concentrate_grade!$F$8/100) -> 0 | BB12: =AR12/concentrate_grade!#REF! -> #REF! | BC12: =Z12 -> 24.008284
A13: ON-MAIN-cb85213a | C13: Eagle River | E13: Ontario | F13: mining | G13: Underground, concentrator | H13: Cool Mixed Forest | I13: Au–Ag free-milling | K13: NPRI+GHG | L13: Energy and explosives (but sanity issue) | M13: 352884.57 | N13: HG, RR, SR | O13: Yes | R13: Yes | T13: m3/t | U13: Gold | V13: Yes | W13: Au | X13: Au-Ag doré | Y13: =prod_table_raw!N55 -> 222627 | Z13: =(AF13+AG13)/0.98 -> 2.7760509 | AB13: =Y13-Z13-AA13 -> 222624.22 | AC13: =Z13/Y13 -> 1.2469516e-05 | AD13: =AA13/Y13 -> 0 | AE13: =1-(Z13+AA13)/AB13 -> 0.99998753 | AF13: =prod_table_raw!N54 -> 2.7205298 | AS13: =AH13/(concentrate_grade!$F$4/100) -> 0 | AT13: =AI13/(concentrate_grade!$F$6/100) -> 0 | AU13: =AK13/(concentrate_grade!$F$5/100) -> 0 | AV13: =AL13/(concentrate_grade!$F$9/100) -> 0 | AW13: =AM13/(concentrate_grade!$F$8/100) -> 0 | BB13: =AR13/concentrate_grade!#REF! -> #REF! | BC13: =Z13 -> 2.7760509
A14: QC-MAIN-6dc537e6 | C14: Éléonore | E14: Quebec | F14: mining | G14: Underground, concentrator | H14: Cold Evergreen Needleleaf Forest | I14: Au–Ag free-milling | K14: NPRI+GHG | L14: Energy and materials | M14: 1445491.9 | N14: HG, RR, SR | S14: Yes | T14: Yes | U14: Gold, silver | V14: Yes | W14: Au (Ag) | X14: Au-Ag doré | Y14: =prod_table_raw!N62 -> 1661000 | Z14: =(AF14+AG14)/0.98 -> 7.7388999 | AB14: =Y14-Z14-AA14 -> 1660992.3 | AC14: =Z14/Y14 -> 4.6591812e-06 | AD14: =AA14/Y14 -> 0 | AE14: =1-(Z14+AA14)/AB14 -> 0.99999534 | AF14: =prod_table_raw!N59 -> 7.216012 | AG14: =prod_table_raw!N60 -> 0.36810992 | AS14: =AH14/(concentrate_grade!$F$4/100) -> 0 | AT14: =AI14/(concentrate_grade!$F$6/100) -> 0 | AU14: =AK14/(concentrate_grade!$F$5/100) -> 0 | AV14: =AL14/(concentrate_grade!$F$9/100) -> 0 | AW14: =AM14/(concentrate_grade!$F$8/100) -> 0 | BB14: =AR14/concentrate_grade!#REF! -> #REF! | BC14: =Z14 -> 7.7388999
A15: BC-MAIN-4724f4ba | C15: Elk | E15: British Columbia | F15: mining | G15: Open-pit | H15: Cold Evergreen Needleleaf Forest | I15: Au–Ag free-milling | J15: Only mining | K15: Land | M15: 416736.86 | N15: OG, SR | Q15: Yes | R15: Yes | S15: Yes | T15: Yes | U15: Gold | V15: Not sure (no NPRI) | W15: Au | X15: Au-Ag doré | Y15: =prod_table_raw!N64 -> 33245 | Z15: =(AF15+AG15)/0.98 -> 0.12428705 | AB15: =Y15-Z15-AA15 -> 33244.876 | AC15: =Z15/Y15 -> 3.7385185e-06 | AD15: =AA15/Y15 -> 0 | AE15: =1-(Z15+AA15)/AB15 -> 0.99999626 | AF15: =prod_table_raw!N65 -> 0.12180131 | AS15: =AH15/(concentrate_grade!$F$4/100) -> 0 | AT15: =AI15/(concentrate_grade!$F$6/100) -> 0 | AU15: =AK15/(concentrate_grade!$F$5/100) -> 0 | AV15: =AL15/(concentrate_grade!$F$9/100) -> 0 | AW15: =AM15/(concentrate_grade!$F$8/100) -> 0 | BB15: =AR15/concentrate_grade!#REF! -> #REF! | BC15: =Z15 -> 0.12428705
A16: ON-MAIN-4e0734b5 | C16: Fox Complex | E16: Ontario | F16: mining | G16: Open-pit, underground, concentrator | H16: Cool Mixed Forest | I16: Au–Ag free-milling | K16: NPRI+land | M16: 7405086.2 | N16: OG, HG | Q16: Yes | R16: Yes | S16: Yes | T16: Yes | U16: Gold | V16: Not sure (no technosphere) | W16: Au | X16: Au-Ag doré | Y16: =prod_table_raw!N70 -> 457000 | Z16: =(AF16+AG16)/0.98 -> 1.4536126 | AB16: =Y16-Z16-AA16 -> 456998.55 | AC16: =Z16/Y16 -> 3.1807714e-06 | AD16: =AA16/Y16 -> 0 | AE16: =1-(Z16+AA16)/AB16 -> 0.99999682 | AF16: =prod_table_raw!N71 -> 1.3809954 | AG16: =prod_table_raw!N72 -> 0.0435449 | AS16: =AH16/(concentrate_grade!$F$4/100) -> 0 | AT16: =AI16/(concentrate_grade!$F$6/100) -> 0 | AU16: =AK16/(concentrate_grade!$F$5/100) -> 0 | AV16: =AL16/(concentrate_grade!$F$9/100) -> 0 | AW16: =AM16/(concentrate_grade!$F$8/100) -> 0 | BB16: =AR16/concentrate_grade!#REF! -> #REF! | BC16: =Z16 -> 1.4536126
A17: ON-MAIN-206041d1 | B17: GRP-de097f20 | C17: Fraser | D17: Integrated Nickel Operations | E17: Ontario | F17: mining | G17: Underground | H17: Cool Mixed Forest | I17: Ni–Cu sulfide | J17: Only mining | K17: Land | M17: 1760913.6 | Q17: Yes | R17: Yes | S17: Yes | T17: Yes | U17: Nickel, copper, platinum group metals, gold, cobalt, silver | V17: No | W17: Ni+Cu | X17: Ni-Cu bulk conc. | Y17: =prod_table_raw!N73 -> 553033 | AA17: =AI17/(concentrate_grade!$F$6/100) -> 0 | AB17: =Y17-Z17-AA17 -> 553033 | AC17: =Z17/Y17 -> 0 | AD17: =AA17/Y17 -> 0 | AE17: =1-(Z17+AA17)/AB17 -> 1 | AT17: =AI17/(concentrate_grade!$F$6/100) -> 0 | AU17: =AK17/(concentrate_grade!$F$5/100) -> 0 | AV17: =AL17/(concentrate_grade!$F$9/100) -> 0 | AW17: =AM17/(concentrate_grade!$F$8/100) -> 0 | BB17: =AR17/concentrate_grade!#REF! -> #REF! | BC17: =Z17 -> 0
A18: ON-MAIN-48fe2205 | B18: GRP-dc07540b | C18: Garson | D18: Sudbury Operation | E18: Ontario | F18: mining | G18: Underground | H18: Cool Mixed Forest | I18: Ni–Cu sulfide | J18: Only mining | K18: NPRI+Land | M18: 2161806.1 | N18: HG | Q18: Yes | R18: Yes | S18: Yes | T18: Yes | U18: Nickel, copper, platinum group metals, gold, silver, cobalt, selenium, tellurium | V18: Not sure (Vale Sudbury) | W18: Ni+Cu | X18: Ni-Cu bulk conc. | Y18: =prod_table_raw!N76 -> 616000 | AA18: =AI18/(concentrate_grade!$F$6/100) -> 49662.5 | AB18: =Y18-Z18-AA18 -> 566337.5 | AC18: =Z18/Y18 -> 0 | AD18: =AA18/Y18 -> 0.080620942 | AE18: =1-(Z18+AA18)/AB18 -> 0.91230936 | AH18: =prod_table_raw!N75 -> 7453 | AI18: =prod_table_raw!N74 -> 7946 | AT18: =AI18/(concentrate_grade!$F$6/100) -> 49662.5 | AU18: =AK18/(concentrate_grade!$F$5/100) -> 0 | AV18: =AL18/(concentrate_grade!$F$9/100) -> 0 | AW18: =AM18/(concentrate_grade!$F$8/100) -> 0 | BB18: =AR18/concentrate_grade!#REF! -> #REF! | BC18: =Z18 -> 0
A19: BC-MAIN-6b4800fe | C19: Gibraltar | E19: British Columbia | F19: mining | G19: Open-pit, concentrator | H19: Cold Evergreen Needleleaf Forest | I19: Cu polymetallic | K19: NPRI+GHG+Water+Land | L19: Energy | M19: 22527999 | N19: HG, SR, RR for Cu | Q19: Yes | R19: Yes | S19: Yes | T19: No | U19: Copper, molybdenum, silver | V19: Yes | W19: Cu+Mo | X19: Cu and Mo conc. | Y19: =prod_table_raw!N80 -> 30000000 | AA19: =AH19/(concentrate_grade!$F$4/100)+AK19/(concentrate_grade!$F$5/100) -> 186436.98 | AB19: =Y19-Z19-AA19 -> 29813563 | AC19: =Z19/Y19 -> 0 | AD19: =AA19/Y19 -> 0.0062145662 | AE19: =1-(Z19+AA19)/AB19 -> 0.99374657 | AH19: =prod_table_raw!N82 -> 55610.379 | AK19: =prod_table_raw!N81 -> 545.21758 | AS19: =AH19/(concentrate_grade!$F$4/100) -> 185367.93 | AT19: =AI19/(concentrate_grade!$F$6/100) -> 0 | AU19: =AK19/(concentrate_grade!$F$5/100) -> 1069.0541 | AV19: =AL19/(concentrate_grade!$F$9/100) -> 0 | AW19: =AM19/(concentrate_grade!$F$8/100) -> 0 | BB19: =AR19/concentrate_grade!#REF! -> #REF! | BC19: =Z19 -> 0
A20: QC-MAIN-c0660aec | C20: Goldex | E20: Quebec | F20: mining | G20: Underground, concentrator | I20: Au–Ag polymetallic | J20: Particular production pattern | K20: NPRI+GHG+Land | L20: Energy | M20: 1341835.2 | N20: HG, RR | Q20: Yes | R20: Yes | S20: Yes | T20: m3/t | U20: Gold, silver | V20: Yes | W20: Au-Ag+Cu | X20: Au-Ag doré, Cu conc. | Y20: =prod_table_raw!N86 -> 2886927.3 | Z20: =(AF20+AG20)/0.98 -> 4.4745421 | AA20: =AH20/(concentrate_grade!$F$4/100) -> 130.12253 | AB20: =Y20-Z20-AA20 -> 2886792.7 | AC20: =Z20/Y20 -> 1.5499324e-06 | AD20: =AA20/Y20 -> 4.5073018e-05 | AE20: =1-(Z20+AA20)/AB20 -> 0.99995337 | AF20: =prod_table_raw!N87 -> 4.3850513 | AH20: =prod_table_raw!N85 -> 39.036758 | AS20: =AH20/(concentrate_grade!$F$4/100) -> 130.12253 | AT20: =AI20/(concentrate_grade!$F$6/100) -> 0 | AU20: =AK20/(concentrate_grade!$F$5/100) -> 0 | AV20: =AL20/(concentrate_grade!$F$9/100) -> 0 | AW20: =AM20/(concentrate_grade!$F$8/100) -> 0 | BB20: =AR20/concentrate_grade!#REF! -> #REF! | BC20: =Z20 -> 4.4745421
A21: ON-MAIN-6e9be24e | C21: Hemlo (Williams) | E21: Ontario | F21: mining | G21: Open-pit, underground, concentrator | H21: Cool Mixed Forest | I21: Au–Ag free-milling | K21: NPRI+GHG+Land | L21: Energy (but sanity issue) | M21: 3503071.1 | N21: SR | O21: Yes | Q21: Yes | R21: Yes | S21: Yes | T21: m3/t | U21: Gold | V21: Yes | W21: Au | X21: Au-Ag doré | Y21: =prod_table_raw!N91 -> 1266009 | Z21: =(AF21+AG21)/0.98 -> 4.4765236 | AB21: =Y21-Z21-AA21 -> 1266004.5 | AC21: =Z21/Y21 -> 3.5359335e-06 | AD21: =AA21/Y21 -> 0 | AE21: =1-(Z21+AA21)/AB21 -> 0.99999646 | AF21: =prod_table_raw!N92 -> 4.3869932 | AS21: =AH21/(concentrate_grade!$F$4/100) -> 0 | AT21: =AI21/(concentrate_grade!$F$6/100) -> 0 | AU21: =AK21/(concentrate_grade!$F$5/100) -> 0 | AV21: =AL21/(concentrate_grade!$F$9/100) -> 0 | AW21: =AM21/(concentrate_grade!$F$8/100) -> 0 | BB21: =AR21/concentrate_grade!#REF! -> #REF! | BC21: =Z21 -> 4.4765236
A22: BC-MAIN-bf503b6b | C22: Highland Valley | E22: British Columbia | F22: mining | G22: Open-pit, concentrator | H22: Cool Evergreen Needleleaf Forest | I22: Cu polymetallic | K22: NPRI+GHG+Water+Land | L22: (NRJ could be back calculated with GHG) | M22: 63924260 | N22: HG (Cu) | O22: Yes | Q22: Yes | R22: Yes | S22: Yes | T22: No | U22: Copper, silver, molybdenum | V22: Yes | W22: Cu+Mo | X22: Cu and Mo conc. | Y22: =prod_table_raw!N93 -> 17408000 | AA22: =AH22/(concentrate_grade!$F$4/100)+AK22/(concentrate_grade!$F$5/100) -> 343098.04 | AB22: =Y22-Z22-AA22 -> 17064902 | AC22: =Z22/Y22 -> 0 | AD22: =AA22/Y22 -> 0.019709216 | AE22: =1-(Z22+AA22)/AB22 -> 0.97989452 | AH22: =prod_table_raw!N95 -> 102400 | AK22: =prod_table_raw!N94 -> 900 | AS22: =AH22/(concentrate_grade!$F$4/100) -> 341333.33 | AT22: =AI22/(concentrate_grade!$F$6/100) -> 0 | AU22: =AK22/(concentrate_grade!$F$5/100) -> 1764.7059 | AV22: =AL22/(concentrate_grade!$F$9/100) -> 0 | AW22: =AM22/(concentrate_grade!$F$8/100) -> 0 | BB22: =AR22/concentrate_grade!#REF! -> #REF! | BC22: =Z22 -> 0
A23: QC-MAIN-30c1828c | B23: GRP-b48ec279 | C23: Horne | D23: CCR | E23: Quebec | F23: manufacturing | G23: Smelter | H23: Cool Mixed Forest | I23: Cu smelter | K23: NPRI+GHG | L23: (NRJ could be back calculated with GHG) | O23: Yes | P23: Yes | Q23: Yes | R23: Yes | T23: Yes | U23: Copper anodes, precious metals, sulfuric acid | V23: Manufacturing | W23: Cu | AB23: =Y23-Z23-AA23 -> 0 | AS23: =AH23/(concentrate_grade!$F$4/100) -> 0 | AT23: =AI23/(concentrate_grade!$F$6/100) -> 0 | AU23: =AK23/(concentrate_grade!$F$5/100) -> 0 | AW23: =AM23/(concentrate_grade!$F$8/100) -> 0 | BC23: =Z23 -> 0
A24: ON-MAIN-687b8c8d | C24: Island | E24: Ontario | F24: mining | G24: Underground, concentrator | H24: Cool Mixed Forest | I24: Au–Ag free-milling | K24: NPRI+GHG | L24: Energy and materials (blasting and acid only) | N24: OG, HG, RR | P24: Yes | R24: Yes | T24: Yes | U24: Gold | V24: Yes | W24: Au | X24: Au-Ag doré | Y24: =prod_table_raw!N105 -> 439008 | Z24: =(AF24+AG24)/0.98 -> 4.1704081 | AB24: =Y24-Z24-AA24 -> 439003.83 | AC24: =Z24/Y24 -> 9.4996175e-06 | AD24: =AA24/Y24 -> 0 | AE24: =1-(Z24+AA24)/AB24 -> 0.9999905 | AF24: =prod_table_raw!N103 -> 4.0869999 | AS24: =AH24/(concentrate_grade!$F$4/100) -> 0 | AT24: =AI24/(concentrate_grade!$F$6/100) -> 0 | AU24: =AK24/(concentrate_grade!$F$5/100) -> 0 | AV24: =AL24/(concentrate_grade!$F$9/100) -> 0 | AW24: =AM24/(concentrate_grade!$F$8/100) -> 0 | BB24: =AR24/concentrate_grade!#REF! -> #REF! | BC24: =Z24 -> 4.1704081
A25: YT-MAIN-44857446 | C25: Keno Hill Silver District | D25: Key Lake + McArthur River | E25: Yukon | F25: mining | G25: Underground, concentrator | H25: Cold Evergreen Needleleaf Forest | I25: Ag polymetallic | L25: Energy and explosives | M25: 5293594 | N25: HG (Ag, Pb, Zn) | R25: Yes | T25: Yes | U25: Silver, zinc, lead | V25: Not sure (no NPRI) but technosphere | W25: Ag (Zn, Pb) | X25: Pb and Zn conc. | Y25: =prod_table_raw!N110 -> 127307 | AA25: =AL25/(concentrate_grade!F9/100)+AM25/(concentrate_grade!F8/100) -> 4719.6667 | AB25: =Y25-Z25-AA25 -> 122587.33 | AC25: =Z25/Y25 -> 0 | AD25: =AA25/Y25 -> 0.037073112 | AE25: =1-(Z25+AA25)/AB25 -> 0.96149956 | AG25: =prod_table_raw!N109 -> 46.735404 | AL25: =prod_table_raw!N112 -> 1339 | AM25: =prod_table_raw!N111 -> 1225 | AS25: =AH25/(concentrate_grade!$F$4/100) -> 0 | AT25: =AI25/(concentrate_grade!$F$6/100) -> 0 | AU25: =AK25/(concentrate_grade!$F$5/100) -> 0 | AV25: =AL25/(concentrate_grade!$F$9/100) -> 2678 | AW25: =AM25/(concentrate_grade!$F$8/100) -> 2041.6667 | BB25: =AR25/concentrate_grade!#REF! -> #REF! | BC25: =Z25 -> 0
A26: ON-MAIN-f8313ebd | C26: Kidd Creek | E26: Ontario | F26: mining | G26: Underground, concentrator | H26: Cool Mixed Forest | I26: Cu polymetallic | K26: NPRI+Land+GHG | M26: 4202253.5 | N26: HG (Cu, Zn) | Q26: Yes | R26: Yes | S26: Yes | T26: Yes | U26: Copper, zinc, silver, selenium, indium | V26: Not sure (no technosphere) | W26: Cu+Zn (Ag) | X26: Cu and Zn conc. | Y26: =prod_table_raw!N116 -> 1340000 | AA26: =AH26/(concentrate_grade!$F$4/100)+AL26/(concentrate_grade!$F$9/100) -> 152533.33 | AB26: =Y26-Z26-AA26 -> 1187466.7 | AC26: =Z26/Y26 -> 0 | AD26: =AA26/Y26 -> 0.11383085 | AE26: =1-(Z26+AA26)/AB26 -> 0.87154727 | AG26: =prod_table_raw!N115 -> 42.860623 | AH26: =prod_table_raw!N113 -> 22600 | AL26: =prod_table_raw!N114 -> 38600 | AS26: =AH26/(concentrate_grade!$F$4/100) -> 75333.333 | AT26: =AI26/(concentrate_grade!$F$6/100) -> 0 | AU26: =AK26/(concentrate_grade!$F$5/100) -> 0 | AV26: =AL26/(concentrate_grade!$F$9/100) -> 77200 | AW26: =AM26/(concentrate_grade!$F$8/100) -> 0 | BB26: =AR26/concentrate_grade!#REF! -> #REF! | BC26: =Z26 -> 0
A27: QC-MAIN-9de9bb0d | C27: Kiena | E27: Quebec | F27: mining | G27: Open-pit, concentrator | I27: Au–Ag free-milling | K27: Land+GHG | L27: Energy and explosives (but sanity issue) | M27: 3436361.1 | N27: HG, RR | O27: Yes | R27: Yes | T27: Yes | U27: Gold, silver | V27: Not sure (no NPRI) but technosphere | W27: Au (Ag) | X27: Au-Ag doré | Y27: =prod_table_raw!N120 -> 191148 | Z27: =(AF27+AG27)/0.98 -> 1.2201776 | AB27: =Y27-Z27-AA27 -> 191146.78 | AC27: =Z27/Y27 -> 6.3834181e-06 | AD27: =AA27/Y27 -> 0 | AE27: =1-(Z27+AA27)/AB27 -> 0.99999362 | AF27: =prod_table_raw!N119 -> 1.1053251 | AG27: =prod_table_raw!N121 -> 0.090448978 | AS27: =AH27/(concentrate_grade!$F$4/100) -> 0 | AT27: =AI27/(concentrate_grade!$F$6/100) -> 0 | AU27: =AK27/(concentrate_grade!$F$5/100) -> 0 | AV27: =AL27/(concentrate_grade!$F$9/100) -> 0 | AW27: =AM27/(concentrate_grade!$F$8/100) -> 0 | BB27: =AR27/concentrate_grade!#REF! -> #REF! | BC27: =Z27 -> 1.2201776
A28: ON-MAIN-a3c56a83 | C28: Lac des Iles | E28: Ontario | F28: mining | G28: Open-pit, underground, concentrator | H28: Cold Evergreen Needleleaf Forest | I28: Ni–Cu sulfide | J28: Contains PGMs so might be a bit special | K28: GHG | L28: Energy | M28: 8409093.1 | N28: HG (PGMs) | Q28: Yes | R28: Yes | S28: Yes | T28: Yes | U28: Platinum group metals, gold, nickel, copper, cobalt | V28: Not sure (no NPRI) but technosphere | W28: Pt | X28: PGM bulk conc. | Y28: =prod_table_raw!N124 -> 3798000 | AB28: =Y28-Z28-AA28 -> 3798000 | AC28: =Z28/Y28 -> 0 | AD28: =AA28/Y28 -> 0 | AE28: =1-(Z28+AA28)/AB28 -> 1 | AF28: =prod_table_raw!N125 -> 0.59407685 | AO28: =prod_table_raw!N127 -> 0.6780563 | AP28: =prod_table_raw!N126 -> 0.7775875 | AS28: =AH28/(concentrate_grade!$F$4/100) -> 0 | AT28: =AI28/(concentrate_grade!$F$6/100) -> 0 | AU28: =AK28/(concentrate_grade!$F$5/100) -> 0 | AV28: =AL28/(concentrate_grade!$F$9/100) -> 0 | AW28: =AM28/(concentrate_grade!$F$8/100) -> 0 | BB28: =AR28/concentrate_grade!#REF! -> #REF! | BC28: =Z28 -> 0
A29: QC-MAIN-f9e41c2a | C29: Lamaque | E29: Quebec | F29: mining | G29: Underground, concentrator | H29: Cool Mixed Forest | I29: Au–Ag free-milling | K29: Land+GHG | L29: Energy | M29: 11904080 | N29: HG, RR | Q29: Yes | R29: Yes | S29: Yes | T29: Yes | U29: Gold, silver | V29: Not sure (no NPRI) but technosphere | W29: Au (Ag) | X29: Au-Ag doré | Y29: =prod_table_raw!N134 -> 838419 | Z29: =(AF29+AG29)/0.98 -> 7.9328207 | AB29: =Y29-Z29-AA29 -> 838411.07 | AC29: =Z29/Y29 -> 9.4616424e-06 | AD29: =AA29/Y29 -> 0 | AE29: =1-(Z29+AA29)/AB29 -> 0.99999054 | AF29: =prod_table_raw!N133 -> 5.5074656 | AG29: =prod_table_raw!N135 -> 2.2666987 | AS29: =AH29/(concentrate_grade!$F$4/100) -> 0 | AT29: =AI29/(concentrate_grade!$F$6/100) -> 0 | AU29: =AK29/(concentrate_grade!$F$5/100) -> 0 | AV29: =AL29/(concentrate_grade!$F$9/100) -> 0 | AW29: =AM29/(concentrate_grade!$F$8/100) -> 0 | BB29: =AR29/concentrate_grade!#REF! -> #REF! | BC29: =Z29 -> 7.9328207
A30: QC-MAIN-e51eda66 | C30: LaRonde | E30: Quebec | F30: mining | G30: Underground, concentrator | H30: Cool Mixed Forest | I30: Au–Ag polymetallic | J30: Particular production pattern, zinc and copper flotation in addition to precious metals and recovery and refining | K30: NPRI+GHG+Land | L30: Energy | M30: 5574424 | N30: HG, RR (Cu, Au, Zn), SR | Q30: Yes | R30: Yes | S30: Yes | T30: m3/t | U30: Gold, zinc, copper, silver, cadmium | V30: Yes | W30: Au-Ag+Cu+Zn | X30: Au-Ag doré, Cu and Zn conc. | Y30: =prod_table_raw!N139 -> 1501500 | Z30: =(AF30+AG30)/0.98 -> 9.8029028 | AA30: =AH30/(concentrate_grade!$F$4/100)+AL30/(concentrate_grade!$F$9/100) -> 23998.078 | AB30: =Y30-Z30-AA30 -> 1477492.1 | AC30: =Z30/Y30 -> 6.5287398e-06 | AD30: =AA30/Y30 -> 0.015982736 | AE30: =1-(Z30+AA30)/AB30 -> 0.98375092 | AF30: =prod_table_raw!N138 -> 7.3401461 | AG30: =prod_table_raw!N135 -> 2.2666987 | AH30: =prod_table_raw!N137 -> 2577.9604 | AL30: =prod_table_raw!N136 -> 7702.4385 | AS30: =AH30/(concentrate_grade!$F$4/100) -> 8593.2013 | AT30: =AI30/(concentrate_grade!$F$6/100) -> 0 | AU30: =AK30/(concentrate_grade!$F$5/100) -> 0 | AV30: =AL30/(concentrate_grade!$F$9/100) -> 15404.877 | AW30: =AM30/(concentrate_grade!$F$8/100) -> 0 | BB30: =AR30/concentrate_grade!#REF! -> #REF! | BC30: =Z30 -> 9.8029028
A31: NL-MAIN-d9036091 | C31: Long Harbour | E31: Newfoundland and Labrador | F31: manufacturing | G31: Refinery | H31: Cool Mixed Forest | I31: Ni hydrometallurgical refinery | K31: NPRI+GHG+Land | L31: (NRJ could be back calculated with GHG) | M31: 681890 | O31: Yes | P31: Yes | Q31: Yes | R31: Yes | T31: Yes | U31: Nickel | V31: Yes (manufacturing) | W31: Ni | X31: Refined Ni | AB31: =Y31-Z31-AA31 -> 0 | AI31: =prod_table_raw!N145 -> 27700 | AS31: =AH31/(concentrate_grade!$F$4/100) -> 0 | AU31: =AK31/(concentrate_grade!$F$5/100) -> 0 | AW31: =AM31/(concentrate_grade!$F$8/100) -> 0 | BC31: =Z31 -> 0
A32: ON-MAIN-1f126a43 | C32: Macassa | E32: Ontario | F32: mining | G32: Underground, concentrator | H32: Cool Mixed Forest | I32: Au–Ag free-milling | J32: High water consumption | K32: NPRI+GHG+Land | L32: Energy (but sanity issue) | M32: 5804864.9 | N32: HG, RR | O32: Yes | Q32: Yes | R32: Yes | S32: Yes | T32: m3/t | U32: Gold, silver | V32: Yes | W32: Au | X32: Au-Ag doré | Y32: =prod_table_raw!N146 -> 441588 | Z32: =(AF32+AG32)/0.98 -> 7.2533045 | AB32: =Y32-Z32-AA32 -> 441580.75 | AC32: =Z32/Y32 -> 1.6425502e-05 | AD32: =AA32/Y32 -> 0 | AE32: =1-(Z32+AA32)/AB32 -> 0.99998357 | AF32: =prod_table_raw!N147 -> 7.1082384 | AS32: =AH32/(concentrate_grade!$F$4/100) -> 0 | AT32: =AI32/(concentrate_grade!$F$6/100) -> 0 | AU32: =AK32/(concentrate_grade!$F$5/100) -> 0 | AV32: =AL32/(concentrate_grade!$F$9/100) -> 0 | AW32: =AM32/(concentrate_grade!$F$8/100) -> 0 | BB32: =AR32/concentrate_grade!#REF! -> #REF! | BC32: =Z32 -> 7.2533045
A33: ON-MAIN-8825d90d | C33: Magino | E33: Ontario | F33: mining | G33: Open-pit, concentrator | H33: Cool Mixed Forest | I33: Au–Ag free-milling | K33: NPRI+Land | M33: 240468.71 | N33: OG, HG, RR | Q33: Yes | R33: Yes | S33: Yes | T33: Yes | U33: Gold, silver | V33: Not sure (no technosphere) | W33: Au | X33: Au-Ag doré | Y33: =prod_table_raw!N150 -> 1165551 | Z33: =(AF33+AG33)/0.98 -> 1.0473628 | AB33: =Y33-Z33-AA33 -> 1165550 | AC33: =Z33/Y33 -> 8.9859882e-07 | AD33: =AA33/Y33 -> 0 | AE33: =1-(Z33+AA33)/AB33 -> 0.9999991 | AF33: =prod_table_raw!N148 -> 1.0264155 | AS33: =AH33/(concentrate_grade!$F$4/100) -> 0 | AT33: =AI33/(concentrate_grade!$F$6/100) -> 0 | AU33: =AK33/(concentrate_grade!$F$5/100) -> 0 | AV33: =AL33/(concentrate_grade!$F$9/100) -> 0 | AW33: =AM33/(concentrate_grade!$F$8/100) -> 0 | BB33: =AR33/concentrate_grade!#REF! -> #REF! | BC33: =Z33 -> 1.0473628
A34: NU-MAIN-5154702a | C34: Mary River | E34: Nunavut | F34: mining | G34: Open-pit | H34: Graminoid and Forb Tundra | I34: Direct Shipping Ore | J34: Only mining | K34: GHG | L34: (NRJ could be back calculated with GHG) | O34: Yes | P34: Yes | Q34: Yes | R34: Yes | S34: Yes | T34: Yes | U34: Iron ore | V34: No (iron) | W34: Fe | X34: DSO | Y34: =prod_table_raw!N151 -> 5600000 | AB34: =Y34-Z34-AA34 -> 5600000 | AC34: =Z34/Y34 -> 0 | AD34: =AA34/Y34 -> 0 | AE34: =1-(Z34+AA34)/AB34 -> 1 | AS34: =AH34/(concentrate_grade!$F$4/100) -> 0 | AT34: =AI34/(concentrate_grade!$F$6/100) -> 0 | AU34: =AK34/(concentrate_grade!$F$5/100) -> 0 | AV34: =AL34/(concentrate_grade!$F$9/100) -> 0 | AW34: =AM34/(concentrate_grade!$F$8/100) -> 0 | BB34: =AR34/concentrate_grade!#REF! -> #REF! | BC34: =Z34 -> 0
A35: ON-MAIN-7001a391 | C35: McCreedy West | E35: Ontario | F35: mining | G35: Underground | H35: Cool Mixed Forest | I35: Ni–Cu sulfide | J35: Contains PGMs so might be a bit special | K35: NPRI+Land | M35: 989146.07 | N35: HG (Co, Pd, Pt, Ag, Au, Cu, Ni) | Q35: Yes | R35: Yes | S35: Yes | T35: Yes | U35: Copper, nickel, platinum group metals, gold, silver, cobalt | V35: Not sure (no technosphere and no GHG) | W35: PGMs+Cu+Ni | X35: Cu-PGM conc. and Ni-Cu conc. | Y35: =prod_table_raw!N157 -> 317660 | AB35: =Y35-Z35-AA35 -> 317660 | AC35: =Z35/Y35 -> 0 | AD35: =AA35/Y35 -> 0 | AE35: =1-(Z35+AA35)/AB35 -> 1 | AS35: =AH35/(concentrate_grade!$F$4/100) -> 0 | AT35: =AI35/(concentrate_grade!$F$6/100) -> 0 | AU35: =AK35/(concentrate_grade!$F$5/100) -> 0 | AV35: =AL35/(concentrate_grade!$F$9/100) -> 0 | AW35: =AM35/(concentrate_grade!$F$8/100) -> 0 | BB35: =AR35/concentrate_grade!#REF! -> #REF! | BC35: =Z35 -> 0
A36: NU-MAIN-8b0264c9 | C36: Meliadine | E36: Nunavut | F36: mining | G36: Open-pit, underground, concentrator | H36: Cold Evergreen Needleleaf Forest | I36: Au–Ag free-milling | K36: NPRI+GHG+Land | L36: Energy | N36: HG, RR, SR | P36: Yes | Q36: Yes | R36: Yes | T36: m3/t | U36: Gold | V36: Yes | W36: Au (Ag) | X36: Au-Ag doré | Y36: =prod_table_raw!N163 -> 1918143 | Z36: =(AF36+AG36)/0.98 -> 12.414137 | AB36: =Y36-Z36-AA36 -> 1918130.6 | AC36: =Z36/Y36 -> 6.4719559e-06 | AD36: =AA36/Y36 -> 0 | AE36: =1-(Z36+AA36)/AB36 -> 0.99999353 | AF36: =prod_table_raw!N164 -> 11.32606 | AG36: =prod_table_raw!N165 -> 0.8397945 | AS36: =AH36/(concentrate_grade!$F$4/100) -> 0 | AT36: =AI36/(concentrate_grade!$F$6/100) -> 0 | AU36: =AK36/(concentrate_grade!$F$5/100) -> 0 | AV36: =AL36/(concentrate_grade!$F$9/100) -> 0 | AW36: =AM36/(concentrate_grade!$F$8/100) -> 0 | BB36: =AR36/concentrate_grade!#REF! -> #REF! | BC36: =Z36 -> 12.414137
A37: BC-MAIN-ed23117f | C37: Mount Milligan | E37: British Columbia | F37: mining | G37: Open-pit, concentrator | H37: Cold Evergreen Needleleaf Forest | I37: Cu Porphyry | K37: NPRI+GHG+Water+Land | L37: Energy | M37: 12606786 | N37: HG, RR (Cu, Au) | Q37: Yes | R37: Yes | S37: Yes | T37: No | U37: Copper, gold, silver | V37: Yes | W37: Cu (Au) | X37: Cu conc. | Y37: =prod_table_raw!N175 -> 21680000 | AA37: =AH37/(concentrate_grade!$F$4/100) -> 93533.694 | AB37: =Y37-Z37-AA37 -> 21586466 | AC37: =Z37/Y37 -> 0 | AD37: =AA37/Y37 -> 0.0043142848 | AE37: =1-(Z37+AA37)/AB37 -> 0.99566702 | AF37: =prod_table_raw!N173 -> 4.8021005 | AH37: =prod_table_raw!N171 -> 28060.108 | AS37: =AH37/(concentrate_grade!$F$4/100) -> 93533.694 | AT37: =AI37/(concentrate_grade!$F$6/100) -> 0 | AU37: =AK37/(concentrate_grade!$F$5/100) -> 0 | AV37: =AL37/(concentrate_grade!$F$9/100) -> 0 | AW37: =AM37/(concentrate_grade!$F$8/100) -> 0 | BB37: =AR37/concentrate_grade!#REF! -> #REF! | BC37: =Z37 -> 0
A38: BC-MAIN-3f490561 | C38: Mount Polley | E38: British Columbia | F38: mining | G38: Open-pit, concentrator | H38: Cold Evergreen Needleleaf Forest | I38: Cu Porphyry | K38: NPRI+GHG+Land | L38: (NRJ could be back calculated with GHG) | M38: 7967834.6 | N38: OG, RR (Cu, Au) | O38: Yes | Q38: Yes | R38: Yes | S38: Yes | T38: Yes | U38: Gold, copper, silver | V38: Yes | W38: Cu (Au) | X38: Cu conc. | Y38: =prod_table_raw!N179 -> 5948239 | AA38: =AH38/(concentrate_grade!$F$4/100) -> 45578.436 | AB38: =Y38-Z38-AA38 -> 5902660.6 | AC38: =Z38/Y38 -> 0 | AD38: =AA38/Y38 -> 0.0076625092 | AE38: =1-(Z38+AA38)/AB38 -> 0.99227832 | AF38: =prod_table_raw!N178 -> 1.3011838 | AH38: =prod_table_raw!N180 -> 13673.531 | AS38: =AH38/(concentrate_grade!$F$4/100) -> 45578.436 | AT38: =AI38/(concentrate_grade!$F$6/100) -> 0 | AU38: =AK38/(concentrate_grade!$F$5/100) -> 0 | AV38: =AL38/(concentrate_grade!$F$9/100) -> 0 | AW38: =AM38/(concentrate_grade!$F$8/100) -> 0 | BB38: =AR38/concentrate_grade!#REF! -> #REF! | BC38: =Z38 -> 0
A39: ON-MAIN-fefeaee4 | C39: Musselwhite | E39: Ontario | F39: mining | G39: Underground, concentrator | H39: Cold Evergreen Needleleaf Forest | I39: Au–Ag free-milling | K39: NPRI+GHG+Land | L39: Energy and materials | M39: 1550354.5 | N39: OG, RR | S39: Yes | T39: m3/t | U39: Gold, silver | V39: Yes | W39: Au | X39: Au-Ag doré | Y39: =prod_table_raw!N183 -> 1028000 | Z39: =(AF39+AG39)/0.98 -> 5.7128878 | AB39: =Y39-Z39-AA39 -> 1027994.3 | AC39: =Z39/Y39 -> 5.5572838e-06 | AD39: =AA39/Y39 -> 0 | AE39: =1-(Z39+AA39)/AB39 -> 0.99999444 | AF39: =prod_table_raw!N184 -> 5.59863 | AS39: =AH39/(concentrate_grade!$F$4/100) -> 0 | AT39: =AI39/(concentrate_grade!$F$6/100) -> 0 | AU39: =AK39/(concentrate_grade!$F$5/100) -> 0 | AV39: =AL39/(concentrate_grade!$F$9/100) -> 0 | AW39: =AM39/(concentrate_grade!$F$8/100) -> 0 | BB39: =AR39/concentrate_grade!#REF! -> #REF! | BC39: =Z39 -> 5.7128878
A40: BC-MAIN-aa76f6f2 | C40: New Afton | E40: British Columbia | F40: mining | G40: Underground, concentrator | H40: Temperate Evergreen Needleleaf Open Woodland | I40: Cu Porphyry | K40: NPRI+GHG+Water+Land | L40: Energy and materials | M40: 4950459.9 | N40: OG, RR (Cu, Au) | R40: Yes | S40: Yes | T40: No | U40: Gold, copper, silver | V40: Yes | W40: Cu (Au) | X40: Cu conc. | Y40: =prod_table_raw!N189 -> 3065000 | AA40: =AH40/(concentrate_grade!$F$4/100) -> 71667.536 | AB40: =Y40-Z40-AA40 -> 2993332.5 | AC40: =Z40/Y40 -> 0 | AD40: =AA40/Y40 -> 0.023382557 | AE40: =1-(Z40+AA40)/AB40 -> 0.97605761 | AF40: =prod_table_raw!N187 -> 2.0974023 | AH40: =prod_table_raw!N190 -> 21500.261 | AS40: =AH40/(concentrate_grade!$F$4/100) -> 71667.536 | AT40: =AI40/(concentrate_grade!$F$6/100) -> 0 | AU40: =AK40/(concentrate_grade!$F$5/100) -> 0 | AV40: =AL40/(concentrate_grade!$F$9/100) -> 0 | AW40: =AM40/(concentrate_grade!$F$8/100) -> 0 | BB40: =AR40/concentrate_grade!#REF! -> #REF! | BC40: =Z40 -> 0
A41: ON-MAIN-fcb287a4 | B41: GRP-de097f20 | C41: Nickel Rim South | D41: Integrated Nickel Operations | E41: Ontario | F41: mining | G41: Underground | H41: Cool Mixed Forest | I41: Ni–Cu sulfide | J41: Only mining | K41: NPRI+Land | P41: Yes | Q41: Yes | R41: Yes | S41: Yes | T41: Yes | U41: Nickel, copper, cobalt, platinum group metals, gold | V41: No | W41: Ni+Cu | X41: Ni-Cu bulk conc. | Y41: =prod_table_raw!N194 -> 320160 | AA41: =AI41/(concentrate_grade!$F$6/100) -> 0 | AB41: =Y41-Z41-AA41 -> 320160 | AC41: =Z41/Y41 -> 0 | AD41: =AA41/Y41 -> 0 | AE41: =1-(Z41+AA41)/AB41 -> 1 | AT41: =AI41/(concentrate_grade!$F$6/100) -> 0 | AU41: =AK41/(concentrate_grade!$F$5/100) -> 0 | AV41: =AL41/(concentrate_grade!$F$9/100) -> 0 | AW41: =AM41/(concentrate_grade!$F$8/100) -> 0 | BB41: =AR41/concentrate_grade!#REF! -> #REF! | BC41: =Z41 -> 0
A42: QC-MAIN-a555d9b9 | C42: Niobec | E42: Quebec | F42: mining | G42: Underground, concentrator | H42: Cool Mixed Forest | I42: Nb mine | K42: NPRI+GHG+Land | L42: (NRJ could be back calculated with GHG) | M42: 2323252.9 | O42: Yes | P42: Yes | Q42: Yes | R42: Yes | S42: Yes | T42: Yes | U42: Niobium | V42: Not sure | W42: Nb | X42: Nb conc. | Y42: =prod_table_raw!N195 -> 2200000 | AA42: =AR42/(concentrate_grade!#REF!/100) -> #REF! | AB42: =Y42-Z42-AA42 -> #REF! | AC42: =Z42/Y42 -> 0 | AE42: =1-(Z42+AA42)/AB42 -> #REF! | AR42: =prod_table_raw!N196 -> 6568.95 | AS42: =AH42/(concentrate_grade!$F$4/100) -> 0 | AT42: =AI42/(concentrate_grade!$F$6/100) -> 0 | AU42: =AK42/(concentrate_grade!$F$5/100) -> 0 | AV42: =AL42/(concentrate_grade!$F$9/100) -> 0 | AW42: =AM42/(concentrate_grade!$F$8/100) -> 0 | BB42: =AR42/concentrate_grade!#REF! -> #REF! | BC42: =Z42 -> 0
A43: QC-MAIN-649d2873 | C43: Niobec Converter | E43: Quebec | F43: manufacturing | G43: Convertor | H43: Cool Mixed Forest | I43: Nb smelter | P43: Yes | Q43: Yes | R43: Yes | T43: Yes | U43: Ferroniobium | V43: Manufacturing | W43: Nb | AB43: =Y43-Z43-AA43 -> 0 | AR43: =prod_table_raw!N197 -> 11700 | AS43: =AH43/(concentrate_grade!$F$4/100) -> 0 | AT43: =AI43/(concentrate_grade!$F$6/100) -> 0 | AU43: =AK43/(concentrate_grade!$F$5/100) -> 0 | AW43: =AM43/(concentrate_grade!$F$8/100) -> 0 | BC43: =Z43 -> 0
A44: QC-MAIN-5ce331b8 | C44: Nunavik Nickel | E44: Quebec | F44: mining | G44: Open-pit, underground, concentrator | H44: Low and High Shrub Tundra | I44: Ni–Cu sulfide | K44: NPRI+GHG | L44: (NRJ could be back calculated with GHG) | O44: Yes | P44: Yes | Q44: Yes | R44: Yes | S44: Yes | T44: Yes | U44: Nickel, copper, platinum group metals, cobalt | V44: Yes | W44: Ni+Cu | X44: Ni-Cu bulk conc. | Y44: =prod_table_raw!N202 -> 6835294.1 | AA44: =AI44/(concentrate_grade!$F$6/100) -> 363125 | AB44: =Y44-Z44-AA44 -> 6472169.1 | AC44: =Z44/Y44 -> 0 | AD44: =AA44/Y44 -> 0.053125 | AE44: =1-(Z44+AA44)/AB44 -> 0.94389439 | AH44: =prod_table_raw!N200 -> 40926 | AI44: =prod_table_raw!N201 -> 58100 | AT44: =AI44/(concentrate_grade!$F$6/100) -> 363125 | AU44: =AK44/(concentrate_grade!$F$5/100) -> 0 | AV44: =AL44/(concentrate_grade!$F$9/100) -> 0 | AW44: =AM44/(concentrate_grade!$F$8/100) -> 0 | BB44: =AR44/concentrate_grade!#REF! -> #REF! | BC44: =Z44 -> 0
A45: QC-MAIN-a97821c0 | C45: Raglan | E45: Quebec | F45: mining | G45: Underground, concentrator | H45: Low and High Shrub Tundra | I45: Ni–Cu sulfide | K45: NPRI+GHG+Land | L45: (NRJ could be back calculated with GHG) | M45: 2475749.8 | O45: Yes | Q45: Yes | R45: Yes | S45: Yes | T45: Yes | U45: Nickel, platinum group metals, copper, cobalt, gold, silver | V45: Yes | W45: Ni+PGM+Cu (Co) | X45: Ni-Cu bulk conc. | Y45: =prod_table_raw!N207 -> 1500000 | AA45: =AI45/(concentrate_grade!$F$6/100) -> 151450 | AB45: =Y45-Z45-AA45 -> 1348550 | AC45: =Z45/Y45 -> 0 | AD45: =AA45/Y45 -> 0.10096667 | AE45: =1-(Z45+AA45)/AB45 -> 0.88769419 | AH45: =prod_table_raw!N203 -> 5488 | AI45: =prod_table_raw!N204 -> 24232 | AJ45: =prod_table_raw!N205 -> 498 | AO45: =prod_table_raw!N206 -> 4.4160749 | AT45: =AI45/(concentrate_grade!$F$6/100) -> 151450 | AU45: =AK45/(concentrate_grade!$F$5/100) -> 0 | AV45: =AL45/(concentrate_grade!$F$9/100) -> 0 | AW45: =AM45/(concentrate_grade!$F$8/100) -> 0 | BB45: =AR45/concentrate_grade!#REF! -> #REF! | BC45: =Z45 -> 0
A46: ON-MAIN-0aadf28f | C46: Rainy River | E46: Ontario | F46: mining | G46: Open-pit, underground, concentrator | H46: Cool Mixed Forest | I46: Au–Ag free-milling | K46: NPRI+GHG+Land | L46: Energy and materials | M46: 22789723 | N46: OG, RR, SR | R46: Yes | T46: Yes | U46: Gold, silver | V46: Yes | W46: Au | X46: Au-Ag doré | Y46: =prod_table_raw!N211 -> 8764000 | Z46: =(AF46+AG46)/0.98 -> 8.0534261 | AB46: =Y46-Z46-AA46 -> 8763991.9 | AC46: =Z46/Y46 -> 9.1892128e-07 | AD46: =AA46/Y46 -> 0 | AE46: =1-(Z46+AA46)/AB46 -> 0.99999908 | AF46: =prod_table_raw!N212 -> 7.8923576 | AS46: =AH46/(concentrate_grade!$F$4/100) -> 0 | AT46: =AI46/(concentrate_grade!$F$6/100) -> 0 | AU46: =AK46/(concentrate_grade!$F$5/100) -> 0 | AV46: =AL46/(concentrate_grade!$F$9/100) -> 0 | AW46: =AM46/(concentrate_grade!$F$8/100) -> 0 | BB46: =AR46/concentrate_grade!#REF! -> #REF! | BC46: =Z46 -> 8.0534261
A47: BC-MAIN-8eb8be0d | C47: Red Chris | E47: British Columbia | F47: mining | G47: Open-pit, concentrator | H47: Cold Evergreen Needleleaf Forest | I47: Au–Ag polymetallic | J47: Big outlier in GHG, not sure if doré is really produced | K47: NPRI+GHG+Water+Land | L47: Energy | M47: 11531647 | N47: HG, RR | Q47: Yes | R47: Yes | S47: Yes | T47: No | U47: Gold, copper, silver | V47: Yes | W47: Au+Cu | X47: Cu conc. | Y47: =prod_table_raw!N215 -> 1139000 | Z47: =(AF47+AG47)/0.98 -> 0.15869133 | AA47: =AH47/(concentrate_grade!$F$4/100) -> 13333.333 | AB47: =Y47-Z47-AA47 -> 1125666.5 | AC47: =Z47/Y47 -> 1.3932513e-07 | AD47: =AA47/Y47 -> 0.011706175 | AE47: =1-(Z47+AA47)/AB47 -> 0.98815502 | AF47: =prod_table_raw!N214 -> 0.1555175 | AH47: =prod_table_raw!N217 -> 4000 | AS47: =AH47/(concentrate_grade!$F$4/100) -> 13333.333 | AT47: =AI47/(concentrate_grade!$F$6/100) -> 0 | AU47: =AK47/(concentrate_grade!$F$5/100) -> 0 | AV47: =AL47/(concentrate_grade!$F$9/100) -> 0 | AW47: =AM47/(concentrate_grade!$F$8/100) -> 0 | BB47: =AR47/concentrate_grade!#REF! -> #REF! | BC47: =Z47 -> 0.15869133
A48: ON-MAIN-7f050560 | C48: Red Lake | E48: Ontario | F48: mining | G48: Underground, concentrator | H48: Cool Mixed Forest | I48: Au–Ag refractory | J48: Refractory? | K48: NPRI+GHG+Land | L48: Energy (but sanity issue) | M48: 6139378.5 | N48: SR | O48: Yes | Q48: Yes | R48: Yes | S48: Yes | T48: Yes | U48: Gold, silver | V48: Yes | W48: Au | X48: Au-Ag doré | Y48: =prod_table_raw!N222 -> 841000 | Z48: =(AF48+AG48)/0.98 -> 3.5769025 | AB48: =Y48-Z48-AA48 -> 840996.42 | AC48: =Z48/Y48 -> 4.253154e-06 | AD48: =AA48/Y48 -> 0 | AE48: =1-(Z48+AA48)/AB48 -> 0.99999575 | AF48: =prod_table_raw!N223 -> 3.5053645 | AS48: =AH48/(concentrate_grade!$F$4/100) -> 0 | AT48: =AI48/(concentrate_grade!$F$6/100) -> 0 | AU48: =AK48/(concentrate_grade!$F$5/100) -> 0 | AV48: =AL48/(concentrate_grade!$F$9/100) -> 0 | AW48: =AM48/(concentrate_grade!$F$8/100) -> 0 | BB48: =AR48/concentrate_grade!#REF! -> #REF! | BC48: =Z48 -> 3.5769025
A49: NL-MAIN-b64bae7a | C49: Scully | E49: Newfoundland and Labrador | F49: mining | G49: Open-pit, concentrator | H49: Cold Evergreen Needleleaf Forest | I49: Fe concentrator | K49: NPRI+GHG+Land | L49: Energy | M49: 10572189 | Q49: Yes | R49: Yes | S49: Yes | T49: Yes | U49: Iron | V49: No (iron) | W49: Fe | X49: Fe conc. | Y49: =prod_table_raw!N226 -> 3560000 | AB49: =Y49-Z49-AA49 -> 3560000 | AC49: =Z49/Y49 -> 0 | AD49: =AA49/Y49 -> 0 | AE49: =1-(Z49+AA49)/AB49 -> 1 | AS49: =AH49/(concentrate_grade!$F$4/100) -> 0 | AT49: =AI49/(concentrate_grade!$F$6/100) -> 0 | AU49: =AK49/(concentrate_grade!$F$5/100) -> 0 | AV49: =AL49/(concentrate_grade!$F$9/100) -> 0 | AW49: =AM49/(concentrate_grade!$F$8/100) -> 0 | BB49: =AR49/concentrate_grade!#REF! -> #REF! | BC49: =Z49 -> 0
A50: ON-MAIN-ed85ac94 | B50: GRP-de097f20 | C50: Strathcona | D50: Integrated Nickel Operations | E50: Ontario | F50: mining | G50: Concentrator | H50: Cool Mixed Forest | I50: Ni–Cu sulfide | J50: Only concentration? Or need to integrate Fraser + Nickel Rim South (mines) | K50: NPRI+GHG+Land | L50: (NRJ could be back calculated with GHG) | M50: 1039802.2 | O50: Yes | Q50: Yes | R50: Yes | T50: Yes | U50: Nickel, copper, platinum group metals, gold, silver, cobalt, selenium, tellurium | V50: Yes | W50: Ni+Cu | X50: Ni-Cu bulk conc. | Y50: =prod_table_raw!N239 -> 1025997 | AA50: =AI50/(concentrate_grade!$F$6/100) -> 47062.5 | AB50: =Y50-Z50-AA50 -> 978934.5 | AC50: =Z50/Y50 -> 0 | AD50: =AA50/Y50 -> 0.045870017 | AE50: =1-(Z50+AA50)/AB50 -> 0.95192477 | AH50: =prod_table_raw!N237 -> 7154 | AI50: =prod_table_raw!N238 -> 7530 | AT50: =AI50/(concentrate_grade!$F$6/100) -> 47062.5 | AU50: =AK50/(concentrate_grade!$F$5/100) -> 0 | AV50: =AL50/(concentrate_grade!$F$9/100) -> 0 | AW50: =AM50/(concentrate_grade!$F$8/100) -> 0 | BB50: =AR50/concentrate_grade!#REF! -> #REF! | BC50: =Z50 -> 0
A51: ON-MAIN-40ce0593 | B51: GRP-de097f20 | C51: Sudbury | D51: Integrated Nickel Operations | E51: Ontario | F51: manufacturing | G51: Smelter, plant | H51: Cool Mixed Forest | I51: Ni-Cu smelter | K51: NPRI+GHG | L51: (NRJ could be back calculated with GHG) | O51: Yes | P51: Yes | Q51: Yes | R51: Yes | T51: Yes | U51: Nickel-copper matte containing cobalt, gold, silver, platinum group metals | V51: Yes (manufacturing) | W51: Ni+Cu | X51: Refined Ni+Cu | AB51: =Y51-Z51-AA51 -> 0 | AH51: =prod_table_raw!N241 -> 13720 | AI51: =prod_table_raw!N240 -> 62251 | AU51: =AK51/(concentrate_grade!$F$5/100) -> 0 | AW51: =AM51/(concentrate_grade!$F$8/100) -> 0 | BC51: =Z51 -> 0
A52: ON-MAIN-f4fc3276 | C52: Sugar Zone | E52: Ontario | F52: mining | G52: Underground, concentrator | H52: Cool Mixed Forest | I52: Au–Ag free-milling | N52: OG | P52: Yes | Q52: Yes | R52: Yes | S52: Yes | T52: Yes | U52: Gold | V52: Not sure (no NPRI) | W52: Au | X52: Au-Ag doré | Y52: =prod_table_raw!N244 -> 234671 | Z52: =(AF52+AG52)/0.98 -> 1.2269696 | AB52: =Y52-Z52-AA52 -> 234669.77 | AC52: =Z52/Y52 -> 5.2284671e-06 | AD52: =AA52/Y52 -> 0 | AE52: =1-(Z52+AA52)/AB52 -> 0.99999477 | AF52: =prod_table_raw!N245 -> 1.2024302 | AS52: =AH52/(concentrate_grade!$F$4/100) -> 0 | AT52: =AI52/(concentrate_grade!$F$6/100) -> 0 | AU52: =AK52/(concentrate_grade!$F$5/100) -> 0 | AV52: =AL52/(concentrate_grade!$F$9/100) -> 0 | AW52: =AM52/(concentrate_grade!$F$8/100) -> 0 | BB52: =AR52/concentrate_grade!#REF! -> #REF! | BC52: =Z52 -> 1.2269696
A53: AB-MAIN-d3a4aba9 | C53: The Cobalt Refinery Company Inc. | E53: Alberta | F53: manufacturing | G53: Refinery | H53: Cold Evergreen Needleleaf Forest | I53: Co hydrometallurgical refinery | K53: NPRI+GHG | L53: (NRJ could be back calculated with GHG) | O53: Yes | P53: Yes | Q53: Yes | R53: Yes | T53: Yes | U53: Nickel, cobalt, copper sulfide, ammonium sulfate | V53: Yes (manufacturing) | W53: Ni+Co | X53: Refined Co+Ni | AB53: =Y53-Z53-AA53 -> 0 | AI53: =prod_table_raw!N247 -> 32268 | AJ53: =prod_table_raw!N246 -> 3368 | AS53: =AH53/(concentrate_grade!$F$4/100) -> 0 | BC53: =Z53 -> 0
A54: MB-MAIN-e0a6250e | C54: Thompson (T-1 and T-3) | E54: Manitoba | F54: mining | G54: Open-pit, underground, concentrator | H54: Cold Evergreen Needleleaf Forest | I54: Ni–Cu sulfide | K54: NPRI+GHG+Land | L54: (NRJ could be back calculated with GHG) | O54: Yes | P54: Yes | Q54: Yes | R54: Yes | S54: Yes | T54: Yes | U54: Nickel, cobalt, copper, platinum group metals, gold, silver | V54: Yes | W54: Ni+Cu | X54: Ni-Cu bulk conc. | Y54: =prod_table_raw!N250 -> 464705.88 | AA54: =AI54/(concentrate_grade!$F$6/100) -> 49375 | AB54: =Y54-Z54-AA54 -> 415330.88 | AC54: =Z54/Y54 -> 0 | AD54: =AA54/Y54 -> 0.10625 | AE54: =1-(Z54+AA54)/AB54 -> 0.88111888 | AH54: =prod_table_raw!N248 -> 4700 | AI54: =prod_table_raw!N249 -> 7900 | AT54: =AI54/(concentrate_grade!$F$6/100) -> 49375 | AU54: =AK54/(concentrate_grade!$F$5/100) -> 0 | AV54: =AL54/(concentrate_grade!$F$9/100) -> 0 | AW54: =AM54/(concentrate_grade!$F$8/100) -> 0 | BB54: =AR54/concentrate_grade!#REF! -> #REF! | BC54: =Z54 -> 0
A55: ON-MAIN-28f3f0fc | B55: GRP-dc07540b | C55: Totten | D55: Sudbury Operation | E55: Ontario | F55: mining | G55: Underground | H55: Cool Mixed Forest | I55: Ni–Cu sulfide | J55: Only mining | K55: NPRI | M55: 559241.26 | N55: HG (Cu, Ni) | Q55: Yes | R55: Yes | S55: Yes | T55: Yes | U55: Nickel, copper, platinum group metals, gold, silver, cobalt | V55: Not sure (Vale Sudbury) | W55: Ni+Cu | X55: Ni-Cu bulk conc. | Y55: =prod_table_raw!N259 -> 414000 | AA55: =AI55/(concentrate_grade!$F$6/100) -> 39587.5 | AB55: =Y55-Z55-AA55 -> 374412.5 | AC55: =Z55/Y55 -> 0 | AD55: =AA55/Y55 -> 0.095621981 | AE55: =1-(Z55+AA55)/AB55 -> 0.89426769 | AH55: =prod_table_raw!N258 -> 7783 | AI55: =prod_table_raw!N257 -> 6334 | AT55: =AI55/(concentrate_grade!$F$6/100) -> 39587.5 | AU55: =AK55/(concentrate_grade!$F$5/100) -> 0 | AV55: =AL55/(concentrate_grade!$F$9/100) -> 0 | AW55: =AM55/(concentrate_grade!$F$8/100) -> 0 | BB55: =AR55/concentrate_grade!#REF! -> #REF! | BC55: =Z55 -> 0
A56: BC-MAIN-3bb6b7cd | C56: Trail | E56: British Columbia | F56: manufacturing | G56: Refinery | H56: Cool Evergreen Needleleaf Forest | I56: Zn refinery | K56: NPRI+GHG+Water | L56: (NRJ could be back calculated with GHG) | O56: Yes | P56: Yes | Q56: Yes | R56: Yes | T56: No | U56: Zinc, lead, bismuth, cadmium, indium, germanium, precious metals, liquid sulfur dioxide, sulfuric acid | V56: No | W56: Zn (Pb) | AB56: =Y56-Z56-AA56 -> 0 | AL56: =prod_table_raw!N262 -> 256000 | AS56: =AH56/(concentrate_grade!$F$4/100) -> 0 | AT56: =AI56/(concentrate_grade!$F$6/100) -> 0 | BC56: =Z56 -> 0
A57: NL-MAIN-2d8801d6 | C57: Voisey’s Bay | E57: Newfoundland and Labrador | F57: mining | G57: Open-pit, underground, concentrator | H57: Cold Evergreen Needleleaf Forest | I57: Ni–Cu sulfide | K57: NPRI+GHG+Land | L57: (NRJ could be back calculated with GHG) | O57: Yes | P57: Yes | Q57: Yes | R57: Yes | S57: Yes | T57: Yes | U57: Nickel, copper, cobalt | V57: Yes | W57: Ni+Cu | X57: Ni-Cu bulk conc. | Y57: =prod_table_raw!N268 -> 794117.65 | AA57: =AI57/(concentrate_grade!$F$6/100) -> 84375 | AB57: =Y57-Z57-AA57 -> 709742.65 | AC57: =Z57/Y57 -> 0 | AD57: =AA57/Y57 -> 0.10625 | AE57: =1-(Z57+AA57)/AB57 -> 0.88111888 | AH57: =prod_table_raw!N266 -> 9600 | AI57: =prod_table_raw!N267 -> 13500 | AT57: =AI57/(concentrate_grade!$F$6/100) -> 84375 | AU57: =AK57/(concentrate_grade!$F$5/100) -> 0 | AV57: =AL57/(concentrate_grade!$F$9/100) -> 0 | AW57: =AM57/(concentrate_grade!$F$8/100) -> 0 | BB57: =AR57/concentrate_grade!#REF! -> #REF! | BC57: =Z57 -> 0
A58: QC-MAIN-02884fb5 | C58: Westwood-Doyon | E58: Quebec | F58: mining | G58: Underground, concentrator | H58: Cool Mixed Forest | I58: Au–Ag free-milling | K58: GHG+Land | L58: Energy and materials | M58: 7249147.2 | N58: OG, HG, SR, RR | R58: Yes | T58: Yes | U58: Gold, silver | V58: Not sure (no NPRI) but technosphere | W58: Au (Ag) | X58: Au-Ag doré | Y58: =prod_table_raw!N271 -> 1034000 | Z58: =(AF58+AG58)/0.98 -> 4.1181669 | AB58: =Y58-Z58-AA58 -> 1033995.9 | AC58: =Z58/Y58 -> 3.9827533e-06 | AD58: =AA58/Y58 -> 0 | AE58: =1-(Z58+AA58)/AB58 -> 0.99999602 | AF58: =prod_table_raw!N273 -> 2.8926255 | AG58: =prod_table_raw!N274 -> 1.143178 | AS58: =AH58/(concentrate_grade!$F$4/100) -> 0 | AT58: =AI58/(concentrate_grade!$F$6/100) -> 0 | AU58: =AK58/(concentrate_grade!$F$5/100) -> 0 | AV58: =AL58/(concentrate_grade!$F$9/100) -> 0 | AW58: =AM58/(concentrate_grade!$F$8/100) -> 0 | BB58: =AR58/concentrate_grade!#REF! -> #REF! | BC58: =Z58 -> 4.1181669
A59: ON-MAIN-7607a50e | C59: Young-Davidson | E59: Ontario | F59: mining | G59: Underground, concentrator | H59: Cool Mixed Forest | I59: Au–Ag free-milling | K59: NPRI+GHG+Land | L59: Energy and materials (blasting and acid only) | M59: 1874190.5 | N59: OG, HG, SR, RR | R59: Yes | T59: Yes | U59: Gold | V59: Yes | W59: Au | X59: Au-Ag doré | Y59: =prod_table_raw!N277 -> 2878047 | Z59: =(AF59+AG59)/0.98 -> 5.8747529 | AB59: =Y59-Z59-AA59 -> 2878041.1 | AC59: =Z59/Y59 -> 2.041229e-06 | AD59: =AA59/Y59 -> 0 | AE59: =1-(Z59+AA59)/AB59 -> 0.99999796 | AF59: =prod_table_raw!N275 -> 5.7572578 | AS59: =AH59/(concentrate_grade!$F$4/100) -> 0 | AT59: =AI59/(concentrate_grade!$F$6/100) -> 0 | AU59: =AK59/(concentrate_grade!$F$5/100) -> 0 | AV59: =AL59/(concentrate_grade!$F$9/100) -> 0 | AW59: =AM59/(concentrate_grade!$F$8/100) -> 0 | BB59: =AR59/concentrate_grade!#REF! -> #REF! | BC59: =Z59 -> 5.8747529
B60: GRP-91aaa60b | D60: Cigar Lake + McClean Lake | E60: Saskatchewan | F60: mining | G60: Underground, concentrator | H60: Cold Evergreen Needleleaf Forest | I60: High-grade U mine + mill | K60: NPRI+GHG+Land | L60: (NRJ could be back calculated with GHG) | M60: 1600590.1 | O60: Yes | Q60: Yes | R60: Yes | S60: Yes | T60: Yes | U60: Uranium | V60: Yes | W60: U | X60: Yellowcake | Y60: =prod_table_raw!N154 -> 43726.856 | AA60: =BA60 -> 9605.4776 | AB60: =Y60-Z60-AA60 -> 34121.379 | AC60: =Z60/Y60 -> 0 | AD60: =AA60/Y60 -> 0.21966998 | AE60: =1-(Z60+AA60)/AB60 -> 0.71849093 | AQ60: =prod_table_raw!N155 -> 8164.656 | AS60: =AH60/(concentrate_grade!$F$4/100) -> 0 | AT60: =AI60/(concentrate_grade!$F$6/100) -> 0 | AU60: =AK60/(concentrate_grade!$F$5/100) -> 0 | AV60: =AL60/(concentrate_grade!$F$9/100) -> 0 | AW60: =AM60/(concentrate_grade!$F$8/100) -> 0 | BA60: =AQ60/(concentrate_grade!$F$10/100) -> 9605.4776 | BB60: =AR60/concentrate_grade!#REF! -> #REF! | BC60: =Z60 -> 0
B61: GRP-21eee27d | D61: Key Lake + McArthur River | E61: Saskatchewan | F61: mining | G61: Underground, concentrator | H61: Cold Evergreen Needleleaf Forest | I61: High-grade U mine + mill | K61: NPRI+GHG | L61: (NRJ could be back calculated with GHG) | M61: 10235647 | O61: Yes | Q61: Yes | R61: Yes | S61: Yes | T61: Yes | U61: Uranium | V61: Yes | W61: U | X61: Yellowcake | Y61: =prod_table_raw!N153 -> 98408.871 | AA61: =BA61 -> 7204.1082 | AB61: =Y61-Z61-AA61 -> 91204.763 | AC61: =Z61/Y61 -> 0 | AD61: =AA61/Y61 -> 0.073205882 | AE61: =1-(Z61+AA61)/AB61 -> 0.92101171 | AQ61: =prod_table_raw!N152 -> 6123.492 | AS61: =AH61/(concentrate_grade!$F$4/100) -> 0 | AT61: =AI61/(concentrate_grade!$F$6/100) -> 0 | AU61: =AK61/(concentrate_grade!$F$5/100) -> 0 | AV61: =AL61/(concentrate_grade!$F$9/100) -> 0 | AW61: =AM61/(concentrate_grade!$F$8/100) -> 0 | BA61: =AQ61/(concentrate_grade!$F$10/100) -> 7204.1082 | BB61: =AR61/concentrate_grade!#REF! -> #REF! | BC61: =Z61 -> 0
B62: GRP-0a2c0d69 | D62: Meadowbank complex | E62: Nunavut | F62: mining | G62: Open-pit, underground | I62: Au–Ag free-milling | K62: NPRI+GHG+Land | L62: Energy | M62: 7644288.9 | Q62: Yes | R62: Yes | T62: m3/t | U62: Gold | V62: Yes | W62: Au (Ag) | X62: Au-Ag doré | Y62: =prod_table_raw!N160 -> 3842649 | Z62: =(AF62+AG62)/0.98 -> 17.667601 | AB62: =Y62-Z62-AA62 -> 3842631.3 | AC62: =Z62/Y62 -> 4.5977661e-06 | AD62: =AA62/Y62 -> 0 | AE62: =1-(Z62+AA62)/AB62 -> 0.9999954 | AF62: =prod_table_raw!N161 -> 13.426312 | AG62: =prod_table_raw!N162 -> 3.8879375 | AS62: =AH62/(concentrate_grade!$F$4/100) -> 0 | AT62: =AI62/(concentrate_grade!$F$6/100) -> 0 | AU62: =AK62/(concentrate_grade!$F$5/100) -> 0 | AV62: =AL62/(concentrate_grade!$F$9/100) -> 0 | AW62: =AM62/(concentrate_grade!$F$8/100) -> 0 | BB62: =AR62/concentrate_grade!#REF! -> #REF! | BC62: =Z62 -> 17.667601
B63: GRP-0d911886 | D63: Porcupine complex | E63: Ontario | F63: mining | G63: Open-pit, underground | I63: Au–Ag free-milling | K63: NPRI+GHG+Land | L63: Energy and materials | M63: 16569167 | S63: Yes | T63: m3/t | U63: Gold | V63: Yes | W63: Au | X63: Au-Ag doré | Y63: =prod_table_raw!N101 -> 2911000 | Z63: =(AF63+AG63)/0.98 -> 8.251949 | AB63: =Y63-Z63-AA63 -> 2910991.7 | AC63: =Z63/Y63 -> 2.8347472e-06 | AD63: =AA63/Y63 -> 0 | AE63: =1-(Z63+AA63)/AB63 -> 0.99999717 | AF63: =prod_table_raw!N100 -> 8.08691 | AS63: =AH63/(concentrate_grade!$F$4/100) -> 0 | AT63: =AI63/(concentrate_grade!$F$6/100) -> 0 | AU63: =AK63/(concentrate_grade!$F$5/100) -> 0 | AV63: =AL63/(concentrate_grade!$F$9/100) -> 0 | AW63: =AM63/(concentrate_grade!$F$8/100) -> 0 | BB63: =AR63/concentrate_grade!#REF! -> #REF! | BC63: =Z63 -> 8.251949
B64: GRP-147b3123 | D64: Timmins Operation | E64: Ontario | F64: mining | G64: Underground, concentrator | I64: Au–Ag free-milling | K64: NPRI+GHG+Land | L64: Energy (but sanity issue) | M64: 1464485.5 | O64: Yes | Q64: Yes | R64: Yes | T64: Yes | U64: Gold | V64: Yes | W64: Au | X64: Au-Ag doré | Y64: =prod_table_raw!N254 -> 1574000 | Z64: =(AF64+AG64)/0.98 -> 4.2180155 | AB64: =Y64-Z64-AA64 -> 1573995.8 | AC64: =Z64/Y64 -> 2.6798065e-06 | AD64: =AA64/Y64 -> 0 | AE64: =1-(Z64+AA64)/AB64 -> 0.99999732 | AF64: =prod_table_raw!N255 -> 4.1336552 | AS64: =AH64/(concentrate_grade!$F$4/100) -> 0 | AT64: =AI64/(concentrate_grade!$F$6/100) -> 0 | AU64: =AK64/(concentrate_grade!$F$5/100) -> 0 | AV64: =AL64/(concentrate_grade!$F$9/100) -> 0 | AW64: =AM64/(concentrate_grade!$F$8/100) -> 0 | BB64: =AR64/concentrate_grade!#REF! -> #REF! | BC64: =Z64 -> 4.2180155
B65: GRP-14bfbb82 | D65: Seabee Gold Operation | E65: Saskatchewan | F65: mining | G65: Underground, concentrator | I65: Au–Ag free-milling | K65: NPRI+GHG+Land | L65: Energy (but sanity issue) | M65: 517003.99 | N65: HG, RR | O65: Yes | Q65: Yes | R65: Yes | S65: Yes | T65: Yes | U65: Gold | V65: Yes | W65: Au | X65: Au-Ag doré | Y65: =prod_table_raw!N229 -> 122000 | Z65: =(AF65+AG65)/0.98 -> 1.2300799 | AB65: =Y65-Z65-AA65 -> 121998.77 | AC65: =Z65/Y65 -> 1.0082623e-05 | AD65: =AA65/Y65 -> 0 | AE65: =1-(Z65+AA65)/AB65 -> 0.99998992 | AF65: =prod_table_raw!N231 -> 1.2054783 | AS65: =AH65/(concentrate_grade!$F$4/100) -> 0 | AT65: =AI65/(concentrate_grade!$F$6/100) -> 0 | AU65: =AK65/(concentrate_grade!$F$5/100) -> 0 | AV65: =AL65/(concentrate_grade!$F$9/100) -> 0 | AW65: =AM65/(concentrate_grade!$F$8/100) -> 0 | BB65: =AR65/concentrate_grade!#REF! -> #REF! | BC65: =Z65 -> 1.2300799
B66: GRP-a13779f8 | D66: Snow Lake | E66: Manitoba | F66: mining | G66: Underground, concentrator | I66: Au–Ag polymetallic | J66: Particular production pattern. Check GHG coverage (only one facility?) | K66: NPRI+Land+GHG | L66: Energy (but sanity issue) | M66: 3104130.9 | N66: HG, RR, CG for New Britannia and Stall Lake (Cu, AG, Au, Zn) | O66: Yes | Q66: Yes | R66: Yes | S66: Yes | T66: Yes | U66: Gold, zinc, copper, silver | V66: Not sure (no GHG) | W66: Au-Ag+Cu+Zn | X66: Au-Ag doré, Cu and Zn conc. | Y66: =prod_table_raw!N193+prod_table_raw!N130 -> 2123641 | Z66: =(AF66+AG66)/0.98 -> 32.978787 | AA66: =AH66/(concentrate_grade!$F$4/100)+AL66/(concentrate_grade!$F$9/100) -> 109797.33 | AB66: =Y66-Z66-AA66 -> 2013810.7 | AC66: =Z66/Y66 -> 1.5529361e-05 | AD66: =AA66/Y66 -> 0.051702399 | AE66: =1-(Z66+AA66)/AB66 -> 0.94546145 | AF66: =prod_table_raw!N232 -> 5.8276451 | AG66: =prod_table_raw!N233 -> 26.491566 | AH66: =prod_table_raw!N235 -> 12154 | AL66: =prod_table_raw!N234 -> 34642 | AS66: =AH66/(concentrate_grade!$F$4/100) -> 40513.333 | AT66: =AI66/(concentrate_grade!$F$6/100) -> 0 | AU66: =AK66/(concentrate_grade!$F$5/100) -> 0 | AV66: =AL66/(concentrate_grade!$F$9/100) -> 69284 | AW66: =AM66/(concentrate_grade!$F$8/100) -> 0 | BB66: =AR66/concentrate_grade!#REF! -> #REF! | BC66: =Z66 -> 32.978787
Y68: =SUM(Y2:Y66) -> 2.2722718e+08 | Z68: =SUM(Z2:Z66) -> 215.43764 | AA68: =SUM(AA2:AA66) -> #REF! | AB68: =SUM(AB2:AB66) -> #REF! | AC68: =AVERAGE(AC2:AC66) -> 2.6911521e-06 | AE68: =SUM(AE2:AE66) -> #REF! | AF68: =SUM(AF2:AF66) -> 169.9178 | AG68: =SUM(AG2:AG66) -> 146.66641 | AH68: =SUM(AH2:AH66) -> 455883.28 | AI68: =SUM(AI2:AI66) -> 306056 | AJ68: =SUM(AJ2:AJ66) -> 3866 | AK68: =SUM(AK2:AK66) -> 1445.2176 | AL68: =SUM(AL2:AL66) -> 1090883.4 | ... BC68: =SUM(BC2:BC66) -> 215.43764

Sheet market_shares
A1: facility_name | B1: facility_group_name | C1: commodities | D1: stream | E1: Au-Ag | F1: Cu | G1: Ni | H1: U | I1: Zn | J1: Mo
A2: =prod_data!C2 -> Bloom Lake | B2: =prod_data!D2 -> 0 | C2: =prod_data!U2 -> Iron | D2: =prod_data!X2 -> Fe conc. | E2: =prod_data!Z2/prod_data!$Z$68 -> 0 | F2: =prod_data!AS2/prod_data!$AS$68 -> 0 | G2: =prod_data!AT2/prod_data!$AT$68 -> 0 | H2: =prod_data!BA2/prod_data!$BA$68 -> 0 | I2: =prod_data!AV2/prod_data!$AV$68 -> 0 | J2: =prod_data!AU2/prod_data!$AU$68 -> 0
A3: =prod_data!C3 -> Brucejack | B3: =prod_data!D3 -> 0 | C3: =prod_data!U3 -> Gold, silver | D3: =prod_data!X3 -> Au-Ag doré | E3: =prod_data!Z3/prod_data!$Z$68 -> 0.004272279 | F3: =prod_data!AS3/prod_data!$AS$68 -> 0 | G3: =prod_data!AT3/prod_data!$AT$68 -> 0 | H3: =prod_data!BA3/prod_data!$BA$68 -> 0 | I3: =prod_data!AV3/prod_data!$AV$68 -> 0 | J3: =prod_data!AU3/prod_data!$AU$68 -> 0
A4: =prod_data!C4 -> Canadian Electrolytic Zinc Limited (CEZinc) | B4: =prod_data!D4 -> 0 | C4: =prod_data!U4 -> Lead, zinc | D4: =prod_data!X4 -> 0 | E4: =prod_data!Z4/prod_data!$Z$68 -> 0 | F4: =prod_data!AS4/prod_data!$AS$68 -> 0 | G4: =prod_data!AT4/prod_data!$AT$68 -> 0 | H4: =prod_data!BA4/prod_data!$BA$68 -> 0 | I4: =prod_data!AV4/prod_data!$AV$68 -> 0 | J4: =prod_data!AU4/prod_data!$AU$68 -> 0
A5: =prod_data!C5 -> Canadian Malartic | B5: =prod_data!D5 -> 0 | C5: =prod_data!U5 -> Gold, silver | D5: =prod_data!X5 -> Au-Ag doré | E5: =prod_data!Z5/prod_data!$Z$68 -> 0.13479114 | F5: =prod_data!AS5/prod_data!$AS$68 -> 0 | G5: =prod_data!AT5/prod_data!$AT$68 -> 0 | H5: =prod_data!BA5/prod_data!$BA$68 -> 0 | I5: =prod_data!AV5/prod_data!$AV$68 -> 0 | J5: =prod_data!AU5/prod_data!$AU$68 -> 0
A6: =prod_data!C6 -> Carol Lake | B6: =prod_data!D6 -> 0 | C6: =prod_data!U6 -> Iron | D6: =prod_data!X6 -> Fe conc., Fe pellets | E6: =prod_data!Z6/prod_data!$Z$68 -> 0 | F6: =prod_data!AS6/prod_data!$AS$68 -> 0 | G6: =prod_data!AT6/prod_data!$AT$68 -> 0 | H6: =prod_data!BA6/prod_data!$BA$68 -> 0 | I6: =prod_data!AV6/prod_data!$AV$68 -> 0 | J6: =prod_data!AU6/prod_data!$AU$68 -> 0
A7: =prod_data!C7 -> Casa Berardi | B7: =prod_data!D7 -> 0 | C7: =prod_data!U7 -> Gold, silver | D7: =prod_data!X7 -> Au-Ag doré | E7: =prod_data!Z7/prod_data!$Z$68 -> 0.016323052 | F7: =prod_data!AS7/prod_data!$AS$68 -> 0 | G7: =prod_data!AT7/prod_data!$AT$68 -> 0 | H7: =prod_data!BA7/prod_data!$BA$68 -> 0 | I7: =prod_data!AV7/prod_data!$AV$68 -> 0 | J7: =prod_data!AU7/prod_data!$AU$68 -> 0
A8: =prod_data!C8 -> Copper Cliff Complex (mine) | B8: =prod_data!D8 -> Sudbury Operation | C8: =prod_data!U8 -> Nickel, copper, platinum group metals, gold, silver, cobalt, selenium, tellurium | D8: =prod_data!X8 -> Ni-Cu bulk conc. | E8: =prod_data!Z8/prod_data!$Z$68 -> 0 | F8: =prod_data!AS8/prod_data!$AS$68 -> 0 | G8: =prod_data!AT8/prod_data!$AT$68 -> 0.060087752 | H8: =prod_data!BA8/prod_data!$BA$68 -> 0 | I8: =prod_data!AV8/prod_data!$AV$68 -> 0 | J8: =prod_data!AU8/prod_data!$AU$68 -> 0
A9: =prod_data!C9 -> Copper Cliff Complex (refinery) | B9: =prod_data!D9 -> Sudbury Operation | C9: =prod_data!U9 -> Nickel (oxide sinter, pellets, powder, sulfide), copper cathodes, gold, silver, selenium cake, tellurium dioxide cake, platinum group metals (in residues), liquid sulfur dioxide, sulfuric acid | D9: =prod_data!X9 -> Refined Ni+Cu | E9: =prod_data!Z9/prod_data!$Z$68 -> 0 | F9: =prod_data!AS9/prod_data!$AS$68 -> 0 | G9: =prod_data!AT9/prod_data!$AT$68 -> 0 | H9: =prod_data!BA9/prod_data!$BA$68 -> 0 | I9: =prod_data!AV9/prod_data!$AV$68 -> 0 | J9: =prod_data!AU9/prod_data!$AU$68 -> 0
A10: =prod_data!C10 -> Copper Mountain | B10: =prod_data!D10 -> 0 | C10: =prod_data!U10 -> Copper, gold, silver | D10: =prod_data!X10 -> Cu conc. | E10: =prod_data!Z10/prod_data!$Z$68 -> 0 | F10: =prod_data!AS10/prod_data!$AS$68 -> 0.06763347 | G10: =prod_data!AT10/prod_data!$AT$68 -> 0 | H10: =prod_data!BA10/prod_data!$BA$68 -> 0 | I10: =prod_data!AV10/prod_data!$AV$68 -> 0 | J10: =prod_data!AU10/prod_data!$AU$68 -> 0
A11: =prod_data!C11 -> Creighton | B11: =prod_data!D11 -> Sudbury Operation | C11: =prod_data!U11 -> Nickel, copper, platinum group metals, gold, silver, cobalt, selenium, tellurium | D11: =prod_data!X11 -> Ni-Cu bulk conc. | E11: =prod_data!Z11/prod_data!$Z$68 -> 0 | F11: =prod_data!AS11/prod_data!$AS$68 -> 0 | G11: =prod_data!AT11/prod_data!$AT$68 -> 0.077892294 | H11: =prod_data!BA11/prod_data!$BA$68 -> 0 | I11: =prod_data!AV11/prod_data!$AV$68 -> 0 | J11: =prod_data!AU11/prod_data!$AU$68 -> 0
A12: =prod_data!C12 -> Detour Lake | B12: =prod_data!D12 -> 0 | C12: =prod_data!U12 -> Gold | D12: =prod_data!X12 -> Au-Ag doré | E12: =prod_data!Z12/prod_data!$Z$68 -> 0.1114396 | F12: =prod_data!AS12/prod_data!$AS$68 -> 0 | G12: =prod_data!AT12/prod_data!$AT$68 -> 0 | H12: =prod_data!BA12/prod_data!$BA$68 -> 0 | I12: =prod_data!AV12/prod_data!$AV$68 -> 0 | J12: =prod_data!AU12/prod_data!$AU$68 -> 0
A13: =prod_data!C13 -> Eagle River | B13: =prod_data!D13 -> 0 | C13: =prod_data!U13 -> Gold | D13: =prod_data!X13 -> Au-Ag doré | E13: =prod_data!Z13/prod_data!$Z$68 -> 0.012885635 | F13: =prod_data!AS13/prod_data!$AS$68 -> 0 | G13: =prod_data!AT13/prod_data!$AT$68 -> 0 | H13: =prod_data!BA13/prod_data!$BA$68 -> 0 | I13: =prod_data!AV13/prod_data!$AV$68 -> 0 | J13: =prod_data!AU13/prod_data!$AU$68 -> 0
... A66: =prod_data!C66 -> 0 | B66: =prod_data!D66 -> Snow Lake | C66: =prod_data!U66 -> Gold, zinc, copper, silver | D66: =prod_data!X66 -> Au-Ag doré, Cu and Zn conc. | E66: =prod_data!Z66/prod_data!$Z$68 -> 0.15307811 | F66: =prod_data!AS66/prod_data!$AS$68 -> 0.043150509 | G66: =prod_data!AT66/prod_data!$AT$68 -> 0 | H66: =prod_data!BA66/prod_data!$BA$68 -> 0 | I66: =prod_data!AV66/prod_data!$AV$68 -> 0.42100817 | J66: =prod_data!AU66/prod_data!$AU$68 -> 0

Sheet concentrate_grade
A1: Commodity | B1: Type | C1: Unit | D1: Min | E1: Max | F1: Value | G1: Source
A2: Au | B2: Dore | C2: % | D2: 80 | E2: 95 | F2: 88
A3: Ag | B3: Dore | C3: % | D3: 5 | E3: 15 | F3: 10
A4: Cu | B4: Concentrate | C4: % | D4: 20 | E4: 40 | F4: 30 | G4: https://internationalcopper.org/wp-content/uploads/2021/11/copper-concentrates-2014.pdf#:~:text=The%20concentrates%20from%20primary%20sulfides,concentrations%20of%20up%20to%2040; https://www.teck.com/media/2006_Teck_Sustainability_Report_Highland_Valley_Copper.PDF?utm_source=chatgpt.com
A5: Mo | B5: Concentrate | C5: % | D5: 50 | E5: 52 | F5: 51 | G5: https://www.chemetalusa.com/dual-track-analysis-of-molybdenum-concentrate-prices-in-april-2025-domestic-mine-transactions-vs-international-fob-benchmarks/#:~:text=Dual,premium%20over%20domestic%20Chinese
A6: Ni | B6: Concentrate | C6: % | D6: 10 | E6: 20 | F6: 16 | G6: https://www.newswire.ca/news-releases/royal-nickel-completes-dumont-bulk-test-and-successfully-produces-worlds-highest-grade-nickel-sulphide-concentrate-562307091.html#:~:text=as%20the%20basis%20of%20the,performed%20well%20with%20pilot%20plant
A7: Fe | B7: Concentrate | C7: % | D7: 64 | E7: 67 | F7: 66 | G7: https://www.championiron.com/project/bloom-lake/
A8: Pb | B8: Concentrate | C8: % | D8: 50 | E8: 70 | F8: 60
A9: Zn | B9: Concentrate | C9: % | D9: 45 | E9: 55 | F9: 50
A10: U | B10: Concentrate | C10: % | F10: 85 | G10: https://www.orano.group/en/unpacking-nuclear/mining-recipe-for-yellowcake
A14: Dore bars = 70-90% Au, 5-20% Ag, 0-10% impurities
A15: Dore mass = mass Au in dore + mass Ag in dore + impurities

Sheet prod_table_raw
A1: prod_id | B1: year | C1: geography | D1: main_id | E1: facility_group_id | F1: facility_name | G1: facility_group_name | H1: commodity | I1: reference_point | J1: material_type | K1: data_type | L1: unit | M1: value | N1: value_tonnes | O1: comment | P1: company_id | Q1: source_id
A2: PROD-3aa117d8-2023-1 | B2: 2023 | C2: Canada | D2: QC-MAIN-3aa117d8 | E2: GRP-677b5973 | F2: Alma | G2: Saguenay–Lac-Saint-Jean Operations | H2: Aluminum | I2: Intermediate metal produced | J2: Smelter production | K2: Capacity | L2: t | M2: 473000 | P2: CMP-7a096012 | Q2: https://aluminium.ca/en/the-industry/
A3: PROD-3aa117d8-2023-2 | B3: 2023 | C3: Canada | D3: QC-MAIN-3aa117d8 | E3: GRP-677b5973 | F3: Alma | G3: Saguenay–Lac-Saint-Jean Operations | H3: Aluminum | I3: Intermediate metal produced | J3: Smelter production | K3: Production | L3: kt | M3: 484 | N3: 484000 | P3: CMP-7a096012 | Q3: RioTinto_rt-fact-book-addendum
A4: PROD-8d6616b4-2023-1 | B4: 2023 | C4: Canada | D4: QC-MAIN-8d6616b4 | E4: GRP-677b5973 | F4: Alouette | G4: Saguenay–Lac-Saint-Jean Operations | H4: Aluminum | I4: Intermediate metal produced | J4: Smelter production | K4: Capacity | L4: t | M4: 620000 | P4: CMP-7a096012 | Q4: https://aluminium.ca/en/the-industry/
A5: PROD-8d6616b4-2023-2 | B5: 2023 | C5: Canada | D5: QC-MAIN-8d6616b4 | E5: GRP-677b5973 | F5: Alouette | G5: Saguenay–Lac-Saint-Jean Operations | H5: Aluminum | I5: Intermediate metal produced | J5: Smelter production | K5: Production | L5: kt | M5: 634 | N5: 634000 | P5: CMP-7a096012 | Q5: RioTinto_rt-fact-book-addendum
A6: PROD-4c35e094-2024-1 | B6: 2024 | C6: Canada | D6: ON-MAIN-4c35e094 | F6: ArcelorMittal Dofasco | H6: Steel | I6: Refined metal produced | J6: Flat | K6: Production | L6: mt | M6: 3.1 | N6: 3100000 | O6: Integrated, mini-mill | P6: CMP-3775c12e | Q6: ArcelorMittal_Factbook_2024
A7: PROD-c1c7eb99-2023-1 | B7: 2023 | C7: Canada | D7: QC-MAIN-c1c7eb99 | E7: GRP-677b5973 | F7: Arvida | G7: Saguenay–Lac-Saint-Jean Operations | H7: Aluminum | I7: Intermediate metal produced | J7: Smelter production | K7: Capacity | L7: t | M7: 234000 | P7: CMP-7a096012 | Q7: RioTinto_rt-fact-book-addendum
A8: PROD-c1c7eb99-2023-2 | B8: 2023 | C8: Canada | D8: QC-MAIN-c1c7eb99 | E8: GRP-677b5973 | F8: Arvida | G8: Saguenay–Lac-Saint-Jean Operations | H8: Aluminum | I8: Intermediate metal produced | J8: Smelter production | K8: Production | L8: kt | M8: 172.03945 | N8: 172039.45 | P8: CMP-7a096012 | Q8: RioTinto_rt-fact-book-addendum
A9: PROD-52c01ae4-2023-1 | B9: 2023 | C9: Canada | D9: QC-MAIN-52c01ae4 | F9: Baie-Comeau | H9: Aluminum | I9: Intermediate metal produced | J9: Capacity | K9: Capacity | L9: t | M9: 312000 | P9: CMP-140e111b | Q9: https://aluminium.ca/en/the-industry/
A10: PROD-c8966bdc-2023-1 | B10: 2023 | C10: Canada | D10: QC-MAIN-c8966bdc | F10: Bécancour | H10: Aluminum | I10: Intermediate metal produced | J10: Capacity | K10: Capacity | L10: t | M10: 462000 | P10: CMP-dc21de8a | Q10: https://aluminium.ca/en/the-industry/
A11: PROD-089f3c60-2022-1 | B11: 2022 | C11: Canada | D11: QC-MAIN-089f3c60 | F11: Bloom Lake | H11: Iron | I11: Total extraction | J11: Ore mined | K11: Production | L11: kt | M11: 11187 | N11: 11187000 | P11: CMP-c08ac7d7 | Q11: https://www.gem.wiki/Quebec_Iron_Bloom_Lake_Mine
A12: PROD-857b7b89-2023-1 | B12: 2023 | C12: Canada | D12: BC-MAIN-857b7b89 | F12: Brucejack | H12: Ore | I12: Total extraction | J12: Ore mined | K12: Production | L12: kt | M12: 167 | N12: 167000 | P12: CMP-4a434d72 | Q12: NewmontCorporation_Operating_statistics_2023
A13: PROD-857b7b89-2023-2 | B13: 2023 | C13: Canada | D13: BC-MAIN-857b7b89 | F13: Brucejack | H13: Ore | I13: Crude ore | J13: Ore processed | K13: Production | L13: kt | M13: 166 | N13: 166000 | P13: CMP-4a434d72 | Q13: NewmontCorporation_Operating_statistics_2023
A14: PROD-857b7b89-2023-3 | B14: 2023 | C14: Canada | D14: BC-MAIN-857b7b89 | F14: Brucejack | H14: Gold | I14: Usable ore | J14: Contained metal in doré | K14: Production | L14: koz | M14: 29 | N14: 0.9020015 | P14: CMP-4a434d72 | Q14: NewmontCorporation_Operating_statistics_2023
A15: PROD-de3d8b7b-2023-1 | B15: 2023 | C15: Canada | D15: QC-MAIN-de3d8b7b | F15: Canadian Electrolytic Zinc Limited (CEZinc) | H15: Lead | I15: Refined metal produced | J15: Refinery production | K15: Production | L15: kt | M15: 244.6 | N15: 244600 | P15: CMP-d5f1c66b | Q15: Glencore_GLEN_2024-FY_ProductionReport_tables
A16: PROD-de3d8b7b-2023-2 | B16: 2023 | C16: Canada | D16: QC-MAIN-de3d8b7b | F16: Canadian Electrolytic Zinc Limited (CEZinc) | H16: Zinc | I16: Refined metal produced | J16: Refinery production | K16: Production | L16: kt | M16: 752.6 | N16: 752600 | P16: CMP-d5f1c66b | Q16: Glencore_GLEN_2024-FY_ProductionReport_tables
A17: PROD-e7e6a960-2023-1 | B17: 2023 | C17: Canada | D17: QC-MAIN-e7e6a960 | F17: Canadian Malartic | H17: Ore | I17: Crude ore | J17: Ore processed | K17: Production | L17: kt | M17: 17332.9 | N17: 17332900 | P17: CMP-6265c407 | Q17: AgnicoEagleMinesLimited_operational_data
A18: PROD-e7e6a960-2023-2 | B18: 2023 | C18: Canada | D18: QC-MAIN-e7e6a960 | F18: Canadian Malartic | H18: Gold | I18: Usable ore | J18: Contained metal in doré | K18: Production | L18: oz | M18: 603955 | N18: 18.785114 | O18: "Production reflects Agnico Eagle's 50% interest up to March 30 2023 and 100% thereafter" | P18: CMP-6265c407 | Q18: AgnicoEagleMinesLimited_operational_data
A19: PROD-e7e6a960-2023-3 | B19: 2023 | C19: Canada | D19: QC-MAIN-e7e6a960 | F19: Canadian Malartic | H19: Silver | I19: Usable ore | J19: Contained metal in doré | K19: Production | L19: koz | M19: 311 | N19: 9.6731885 | O19: "Production reflects Agnico Eagle's 50% interest up to March 30 2023 and 100% thereafter" | P19: CMP-6265c407 | Q19: AgnicoEagleMinesLimited_operational_data
A20: PROD-dd723db4-2023-1 | B20: 2023 | C20: Canada | D20: NL-MAIN-dd723db4 | F20: Carol Lake | H20: Iron | I20: Usable ore | J20: Capacity | K20: Capacity | L20: kt | M20: 23000 | P20: CMP-2da4630a | Q20: https://www.gem.wiki/IOC_Carol_Lake_Mine
A21: PROD-dd723db4-2023-2 | B21: 2023 | C21: Canada | D21: NL-MAIN-dd723db4 | F21: Carol Lake | H21: Iron | I21: Total extraction | J21: Ore mined | K21: Production | L21: kt | M21: 16478 | N21: 16478000 | O21: Total production based on Rio Tinto's ownership share | P21: CMP-2da4630a | Q21: IronOreCompanyofCanada_rt-fact-book-addendum
A22: PROD-b86f7d07-2023-1 | B22: 2023 | C22: Canada | D22: QC-MAIN-b86f7d07 | F22: Casa Berardi | H22: Gold | I22: Usable ore | J22: Contained metal in doré | K22: Production | L22: koz | M22: 86.6 | N22: 2.6935631 | P22: CMP-7e360a1f | Q22: https://www.hecla.com/operations/casa-berardi-quebec-canada
A23: PROD-b86f7d07-2023-2 | B23: 2023 | C23: Canada | D23: QC-MAIN-b86f7d07 | F23: Casa Berardi | H23: Silver | I23: Usable ore | J23: Contained metal in doré | K23: Production | L23: koz | M23: 24.2 | N23: 0.7527047 | P23: CMP-7e360a1f | Q23: https://www.hecla.com/operations/casa-berardi-quebec-canada
A24: PROD-b86f7d07-2023-3 | B24: 2023 | C24: Canada | D24: QC-MAIN-b86f7d07 | F24: Casa Berardi | H24: Ore | I24: Crude ore | J24: Mill feed | K24: Production | L24: t | M24: 1361450 | N24: 1361450 | O24: "The Casa Berardi mill processes 3,730tpd, with future maximum production of 4,400tpd." | P24: CMP-7e360a1f | Q24: HeclaMiningCompany_TR_Casa_Berardi_2024
A25: 1754055_prod | B25: 2023 | C25: Canada | D25: ON-MAIN-6e9b2449 | E25: GRP-dc07540b | F25: Coleman | G25: Sudbury Operation | H25: Copper | I25: Crude ore | K25: Production | L25: t of copper ore | M25: 863000 | N25: 863000 | P25: CMP-9617aef4 | Q25: https://github.com/climatetracecoalition/methodology-documents/tree/main/2024/Mineral%20Extraction
A26: 1754055_cap | B26: 2023 | C26: Canada | D26: ON-MAIN-6e9b2449 | E26: GRP-dc07540b | F26: Coleman | G26: Sudbury Operation | I26: Crude ore | K26: Capacity | L26: tonnes | M26: 4624000 | N26: 4624000 | P26: CMP-9617aef4 | Q26: https://github.com/climatetracecoalition/methodology-documents/tree/main/2024/Mineral%20Extraction
A27: PROD-GRP-7a9ba115-2024-1 | B27: 2024 | C27: Canada | E27: GRP-7a9ba115 | F27: Contrecœur West | G27: Contrecoeur | H27: Steel | I27: Refined metal produced | J27: Long/wire rod, bars, slabs | K27: Production | L27: mt | M27: 1.9 | N27: 1900000 | O27: Mini-mill | P27: CMP-3775c12e | Q27: ArcelorMittal_Factbook_2024
A28: PROD-f080c409-2023-1 | B28: 2023 | C28: Canada | D28: ON-MAIN-f080c409 | E28: GRP-dc07540b | F28: Copper Cliff Complex | G28: Sudbury Operation | H28: Nickel | I28: Usable ore | J28: Contained metal in concentrate | K28: Production | L28: t | M28: 8751 | N28: 8751 | O28: https://www.geologyontario.mines.gov.on.ca/mineral-inventory/MDI41I06NE00002 | P28: CMP-9617aef4 | Q28: Vale_nan
A29: PROD-f080c409-2023-2 | B29: 2023 | C29: Canada | D29: ON-MAIN-f080c409 | E29: GRP-dc07540b | F29: Copper Cliff Complex | G29: Sudbury Operation | H29: Copper | I29: Usable ore | J29: Contained metal in concentrate | K29: Production | L29: t | M29: 10098 | N29: 10098 | O29: https://www.geologyontario.mines.gov.on.ca/mineral-inventory/MDI41I06NE00002 | P29: CMP-9617aef4 | Q29: Vale_nan
A30: PROD-f080c409-2023-3 | B30: 2023 | C30: Canada | D30: ON-MAIN-f080c409 | E30: GRP-dc07540b | F30: Copper Cliff Complex | G30: Sudbury Operation | H30: Ore | I30: Crude ore | J30: Ore processed | K30: Production | L30: t | M30: 748000 | N30: 748000 | O30: https://www.geologyontario.mines.gov.on.ca/mineral-inventory/MDI41I06NE00002 | P30: CMP-9617aef4 | Q30: Vale_nan
A31: PROD-63b394c3-2023-1 | B31: 2023 | C31: Canada | D31: ON-MAIN-63b394c3 | E31: GRP-dc07540b | F31: Copper Cliff Complex | G31: Sudbury Operation | H31: Copper | I31: Refined metal produced | J31: Refinery production | K31: Production | L31: kt | M31: 57.9 | N31: 57900 | O31: Finished production by source (In Vale's reporting, "by source" refers to finished production from ore that originated from a specific mine), no data for site. 7.2kt additional feed from third-parties | P31: CMP-9617aef4 | Q31: Vale_Vale'sperformancein1Q25-xls
A32: PROD-63b394c3-2023-2 | B32: 2023 | C32: Canada | D32: ON-MAIN-63b394c3 | E32: GRP-dc07540b | F32: Copper Cliff Complex | G32: Sudbury Operation | H32: Nickel | I32: Refined metal produced | J32: Refinery production | K32: Production | L32: kt | M32: 38.2 | N32: 38200 | P32: CMP-9617aef4 | Q32: Vale_Vale'sperformancein1Q25-xls
A33: 1754056_prod | B33: 2023 | C33: Canada | D33: ON-MAIN-f080c409 | E33: GRP-dc07540b | F33: Copper Cliff Complex | G33: Sudbury Operation | H33: Copper | I33: Crude ore | K33: Production | L33: t of copper ore | M33: 985000 | N33: 985000 | P33: CMP-9617aef4 | Q33: https://github.com/climatetracecoalition/methodology-documents/tree/main/2024/Mineral%20Extraction
A34: 1754056_cap | B34: 2023 | C34: Canada | D34: ON-MAIN-f080c409 | E34: GRP-dc07540b | F34: Copper Cliff Complex | G34: Sudbury Operation | I34: Crude ore | K34: Capacity | L34: tonnes | M34: 35547000 | N34: 35547000 | P34: CMP-9617aef4 | Q34: https://github.com/climatetracecoalition/methodology-documents/tree/main/2024/Mineral%20Extraction
A35: PROD-599152a0-2023-1 | B35: 2023 | C35: Canada | D35: BC-MAIN-599152a0 | F35: Copper Mountain | H35: Gold | I35: Usable ore | J35: Contained metal in doré | K35: Production | L35: oz | M35: 8848 | N35: 0.27520377 | O35: "As Copper Mountain was acquired on June 20, 2023, the results for the year ended December 31, 2023 represents the period from the acquisition date, June 20, 2023, through to the end of the fourth quarter of 2023" | P35: CMP-12afc634 | Q35: HudbayMineralsInc_MDA25
A36: PROD-599152a0-2023-2 | B36: 2023 | C36: Canada | D36: BC-MAIN-599152a0 | F36: Copper Mountain | H36: Ore | I36: Crude ore | J36: Ore milled | K36: Production | L36: t | M36: 6862152 | N36: 6862152 | O36: "As Copper Mountain was acquired on June 20, 2023, the results for the year ended December 31, 2023 represents the period from the acquisition date, June 20, 2023, through to the end of the fourth quarter of 2023" | P36: CMP-12afc634 | Q36: HudbayMineralsInc_MDA25
A37: PROD-599152a0-2023-3 | B37: 2023 | C37: Canada | D37: BC-MAIN-599152a0 | F37: Copper Mountain | H37: Ore | I37: Total extraction | J37: Ore mined | K37: Production | L37: t | M37: 6975389 | N37: 6975389 | O37: "As Copper Mountain was acquired on June 20, 2023, the results for the year ended December 31, 2023 represents the period from the acquisition date, June 20, 2023, through to the end of the fourth quarter of 2023" | P37: CMP-12afc634 | Q37: HudbayMineralsInc_MDA25
A38: PROD-599152a0-2023-4 | B38: 2023 | C38: Canada | D38: BC-MAIN-599152a0 | F38: Copper Mountain | H38: Silver | I38: Usable ore | J38: Contained metal in doré | K38: Production | L38: oz | M38: 218282 | N38: 6.7893342 | O38: "As Copper Mountain was acquired on June 20, 2023, the results for the year ended December 31, 2023 represents the period from the acquisition date, June 20, 2023, through to the end of the fourth quarter of 2023" | P38: CMP-12afc634 | Q38: HudbayMineralsInc_MDA25
A39: PROD-599152a0-2023-5 | B39: 2023 | C39: Canada | D39: BC-MAIN-599152a0 | F39: Copper Mountain | H39: Copper | I39: Usable ore | J39: Contained metal in concentrate | K39: Production | L39: t | M39: 19050 | N39: 19050 | O39: "As Copper Mountain was acquired on June 20, 2023, the results for the year ended December 31, 2023 represents the period from the acquisition date, June 20, 2023, through to the end of the fourth quarter of 2023" | P39: CMP-12afc634 | Q39: HudbayMineralsInc_MDA25
A40: 1754057_prod | B40: 2023 | C40: Canada | D40: BC-MAIN-599152a0 | F40: Copper Mountain | H40: Copper | I40: Crude ore | K40: Production | L40: t of copper ore | M40: 14575000 | N40: 14575000 | P40: CMP-12afc634 | Q40: https://github.com/climatetracecoalition/methodology-documents/tree/main/2024/Mineral%20Extraction
A41: 1754057_cap | B41: 2023 | C41: Canada | D41: BC-MAIN-599152a0 | F41: Copper Mountain | I41: Crude ore | K41: Capacity | L41: tonnes | M41: 3.67e+08 | N41: 3.67e+08 | P41: CMP-12afc634 | Q41: https://github.com/climatetracecoalition/methodology-documents/tree/main/2024/Mineral%20Extraction
A42: PROD-52224e1e-2023-1 | B42: 2023 | C42: Canada | D42: ON-MAIN-52224e1e | E42: GRP-dc07540b | F42: Creighton | G42: Sudbury Operation | H42: Nickel | I42: Usable ore | J42: Contained metal in concentrate | K42: Production | L42: t | M42: 11344 | N42: 11344 | O42: https://www.geologyontario.mndm.gov.on.ca/mndmfiles/mdi/data/records/MDI41I06NE00005.html | P42: CMP-9617aef4 | Q42: Vale_nan
A43: PROD-52224e1e-2023-2 | B43: 2023 | C43: Canada | D43: ON-MAIN-52224e1e | E43: GRP-dc07540b | F43: Creighton | G43: Sudbury Operation | H43: Copper | I43: Usable ore | J43: Contained metal in concentrate | K43: Production | L43: t | M43: 9396 | N43: 9396 | O43: https://www.geologyontario.mndm.gov.on.ca/mndmfiles/mdi/data/records/MDI41I06NE00005.html | P43: CMP-9617aef4 | Q43: Vale_nan
A44: PROD-52224e1e-2023-3 | B44: 2023 | C44: Canada | D44: ON-MAIN-52224e1e | E44: GRP-dc07540b | F44: Creighton | G44: Sudbury Operation | H44: Ore | I44: Crude ore | J44: Ore processed | K44: Production | L44: t | M44: 433000 | N44: 433000 | O44: https://www.geologyontario.mndm.gov.on.ca/mndmfiles/mdi/data/records/MDI41I06NE00005.html | P44: CMP-9617aef4 | Q44: Vale_nan
A45: 1754058_prod | B45: 2023 | C45: Canada | D45: ON-MAIN-52224e1e | E45: GRP-dc07540b | F45: Creighton | G45: Sudbury Operation | H45: Copper | I45: Crude ore | K45: Production | L45: t of copper ore | M45: 406000 | N45: 406000 | P45: CMP-9617aef4 | Q45: https://github.com/climatetracecoalition/methodology-documents/tree/main/2024/Mineral%20Extraction
A46: 1754058_cap | B46: 2023 | C46: Canada | D46: ON-MAIN-52224e1e | E46: GRP-dc07540b | F46: Creighton | G46: Sudbury Operation | I46: Crude ore | K46: Capacity | L46: tonnes | M46: 11041000 | N46: 11041000 | P46: CMP-9617aef4 | Q46: https://github.com/climatetracecoalition/methodology-documents/tree/main/2024/Mineral%20Extraction
A47: PROD-eac5a52b-2023-1 | B47: 2023 | C47: Canada | D47: QC-MAIN-eac5a52b | F47: Deschambault | H47: Aluminum | I47: Intermediate metal produced | J47: Capacity | K47: Capacity | L47: t | M47: 287000 | P47: CMP-140e111b | Q47: https://aluminium.ca/en/the-industry/
A48: PROD-aeafbb59-2023-1 | B48: 2023 | C48: Canada | D48: ON-MAIN-aeafbb59 | F48: Detour Lake | H48: Gold | I48: Crude ore | J48: Ore processed | K48: Production | L48: t | M48: 25434854 | N48: 25434854 | P48: CMP-6265c407 | Q48: AgnicoEagleMinesLimited_2023-Sustainability-Performance_data
A49: PROD-aeafbb59-2023-2 | B49: 2023 | C49: Canada | D49: ON-MAIN-aeafbb59 | F49: Detour Lake | H49: Gold | I49: Usable ore | J49: Contained metal in doré | K49: Production | L49: oz | M49: 677446 | N49: 21.070942 | P49: CMP-6265c407 | Q49: AgnicoEagleMinesLimited_2023-Sustainability-Performance_data
A50: PROD-aeafbb59-2023-3 | B50: 2023 | C50: Canada | D50: ON-MAIN-aeafbb59 | F50: Detour Lake | H50: Silver | I50: Usable ore | J50: Contained metal in doré | K50: Production | L50: koz | M50: 79 | N50: 2.4571765 | P50: CMP-6265c407 | Q50: AgnicoEagleMinesLimited_2023-Sustainability-Performance_data
A51: PROD-0ec39ce0-2023-1 | B51: 2023 | C51: Canada | D51: NT-MAIN-0ec39ce0 | F51: Diavik | H51: Diamonds | I51: Usable ore | J51: Diamond recovered | K51: Production | L51: kct | M51: 3339.762 | N51: 0.66795241 | P51: CMP-7a096012 | Q51: RioTinto_2024-4qor-xlsx
A52: PROD-0ec39ce0-2023-2 | B52: 2023 | C52: Canada | D52: NT-MAIN-0ec39ce0 | F52: Diavik | H52: Diamonds | I52: Crude ore | J52: Ore processed | K52: Production | L52: kct | M52: 1687.71 | N52: 0.337542 | P52: CMP-7a096012 | Q52: RioTinto_2024-4qor-xlsx
A53: PROD-GRP-2a663492-2023-1 | B53: 2023 | C53: Canada | E53: GRP-2a663492 | F53: DSO (Goodwood) | G53: DSO | H53: Iron | I53: Total extraction | J53: Ore mined | K53: Capacity | L53: mt | M53: 4.2 | P53: CMP-31bb0d19 | Q53: https://www.gov.nl.ca/iet/files/Mining-in-NL-Fall-2024.pdf
A54: PROD-cb85213a-2023-1 | B54: 2023 | C54: Canada | D54: ON-MAIN-cb85213a | F54: Eagle River | H54: Gold | I54: Usable ore | J54: Contained metal in doré | K54: Production | L54: oz | M54: 87467 | N54: 2.7205298 | O54: Gold production' | P54: CMP-3d2c4955 | Q54: WesdomeGoldMinesLtd_2024-MDA-FINAL
A55: PROD-cb85213a-2023-2 | B55: 2023 | C55: Canada | D55: ON-MAIN-cb85213a | F55: Eagle River | H55: Gold | I55: Crude ore | J55: Ore milled | K55: Production | L55: t | M55: 222627 | N55: 222627 | P55: CMP-3d2c4955 | Q55: WesdomeGoldMinesLtd_2024-MDA-FINAL
A56: PROD-6c1d6ee6-2023-1 | B56: 2023 | C56: Canada | D56: NT-MAIN-6c1d6ee6 | F56: Ekati | H56: Diamonds | I56: Usable ore | J56: Carats recovered | K56: Production | L56: mcts | M56: 5.1 | N56: 1.02 | P56: CMP-caa580a0 | Q56: BurgundyDiamondMines_Quarterly-Activities-Report-for-the-Period-ended-September-30th-2027
A57: PROD-6c1d6ee6-2023-2 | B57: 2023 | C57: Canada | D57: NT-MAIN-6c1d6ee6 | F57: Ekati | H57: Diamonds | I57: Crude ore | J57: Ore processed | K57: Production | L57: mdmt | M57: 4.2 | N57: 4200000 | P57: CMP-caa580a0 | Q57: BurgundyDiamondMines_Quarterly-Activities-Report-for-the-Period-ended-September-30th-2026
A58: PROD-6c1d6ee6-2023-3 | B58: 2023 | C58: Canada | D58: NT-MAIN-6c1d6ee6 | F58: Ekati | H58: Diamonds | I58: Total extraction | J58: Ore mined | K58: Production | L58: mwmt | M58: 4.6 | N58: 4600000 | P58: CMP-caa580a0 | Q58: BurgundyDiamondMines_Quarterly-Activities-Report-for-the-Period-ended-September-30th-2025
A59: PROD-6dc537e6-2023-1 | B59: 2023 | C59: Canada | D59: QC-MAIN-6dc537e6 | F59: Éléonore | H59: Gold | I59: Usable ore | J59: Contained metal in doré | K59: Production | L59: koz | M59: 232 | N59: 7.216012 | P59: CMP-4a434d72 | Q59: NewmontCorporation_Operating_statistics_2023
A60: PROD-6dc537e6-2023-2 | B60: 2023 | C60: Canada | D60: QC-MAIN-6dc537e6 | F60: Éléonore | H60: Silver | I60: Usable ore | J60: Contained metal in doré | K60: Production | L60: oz | M60: 11835 | N60: 0.36810992 | P60: CMP-4a434d72 | Q60: https://mrnf.gouv.qc.ca/en/mines/publications/quantity-mine-mouth-output-value-and-duties-paid-by-mining-companies/
A61: PROD-6dc537e6-2023-3 | B61: 2023 | C61: Canada | D61: QC-MAIN-6dc537e6 | F61: Éléonore | H61: Gold | I61: Total extraction | J61: Ore mined | K61: Production | L61: kt | M61: 1656 | N61: 1656000 | P61: CMP-4a434d72 | Q61: NewmontCorporation_Operating_statistics_2023
A62: PROD-6dc537e6-2023-4 | B62: 2023 | C62: Canada | D62: QC-MAIN-6dc537e6 | F62: Éléonore | H62: Gold | I62: Crude ore | J62: Ore processed | K62: Production | L62: kt | M62: 1661 | N62: 1661000 | P62: CMP-4a434d72 | Q62: NewmontCorporation_Operating_statistics_2023
A63: PROD-4724f4ba-2024-1 | B63: 2024 | C63: Canada | D63: BC-MAIN-4724f4ba | F63: Elk | H63: Gold | I63: Total extraction | J63: Ore mined | K63: Production | L63: t | M63: 34017 | N63: 34017 | P63: CMP-d726df1c | Q63: https://www.accessnewswire.com/newsroom/en/metals-and-mining/gold-mountain-reports-its-interim-q4-2025-financial-and-operating-results-1001121?utm_source=chatgpt.com
A64: PROD-4724f4ba-2024-2 | B64: 2024 | C64: Canada | D64: BC-MAIN-4724f4ba | F64: Elk | H64: Gold | I64: Crude ore | J64: Ore delivered | K64: Production | L64: t | M64: 33245 | N64: 33245 | P64: CMP-d726df1c | Q64: https://www.accessnewswire.com/newsroom/en/metals-and-mining/gold-mountain-reports-its-interim-q4-2025-financial-and-operating-results-1001121?utm_source=chatgpt.com
A65: PROD-4724f4ba-2024-3 | B65: 2024 | C65: Canada | D65: BC-MAIN-4724f4ba | F65: Elk | H65: Gold | I65: Usable ore | J65: Contained metal in doré | K65: Production | L65: oz | M65: 3916 | N65: 0.12180131 | O65: Gold ounces sold' | P65: CMP-d726df1c | Q65: https://www.accessnewswire.com/newsroom/en/metals-and-mining/gold-mountain-reports-its-interim-q4-2025-financial-and-operating-results-1001121?utm_source=chatgpt.com
A66: PROD-26b9aaf3-2021-1 | B66: 2021 | C66: Canada | D66: SK-MAIN-26b9aaf3 | F66: EVRAZ Regina | H66: Steel | I66: Intermediate metal produced | J66: EAF production | K66: Production | L66: kt | M66: 828 | N66: 828000 | P66: CMP-28720916 | Q66: https://www.gem.wiki/Evraz_Regina_Steel_plant
A67: PROD-26b9aaf3-2021-2 | B67: 2021 | C67: Canada | D67: SK-MAIN-26b9aaf3 | F67: EVRAZ Regina | H67: Steel | I67: Intermediate metal produced | J67: Nominal crude steel capacity | K67: Capacity | L67: ttpa | M67: 1200 | P67: CMP-28720916 | Q67: https://www.gem.wiki/Evraz_Regina_Steel_plant
A68: PROD-33c09b8b-2023-1 | B68: 2023 | C68: Canada | D68: QC-MAIN-33c09b8b | E68: GRP-1402249f | F68: Fire Lake | G68: AMMC | H68: Iron | I68: Total extraction | J68: Ore mined | K68: Production | L68: kt | M68: 5901 | N68: 5901000 | O68: Given in ttpa (total ton per annum) | P68: CMP-3775c12e | Q68: https://www.gem.wiki/ArcelorMittal_Fire_Lake_Mine
A69: PROD-4e0734b5-2023-1 | B69: 2023 | C69: Canada | D69: ON-MAIN-4e0734b5 | F69: Fox Complex | H69: Gold | I69: Total extraction | J69: Ore mined | K69: Production | L69: kt | M69: 391 | N69: 391000 | O69: Unit confirmed in the website: https://www.mcewenmining.com/operations/black-fox-complex/default.aspx | P69: CMP-3ff42329 | Q69: McEwenMiningInc_SEC_2024
A70: PROD-4e0734b5-2023-2 | B70: 2023 | C70: Canada | D70: ON-MAIN-4e0734b5 | F70: Fox Complex | H70: Gold | I70: Crude ore | J70: Ore processed | K70: Production | L70: kt | M70: 457 | N70: 457000 | O70: Unit confirmed in the website: https://www.mcewenmining.com/operations/black-fox-complex/default.aspx | P70: CMP-3ff42329 | Q70: McEwenMiningInc_SEC_2024
A71: PROD-4e0734b5-2023-3 | B71: 2023 | C71: Canada | D71: ON-MAIN-4e0734b5 | F71: Fox Complex | H71: Gold | I71: Usable ore | J71: Contained metal in doré | K71: Production | L71: koz | M71: 44.4 | N71: 1.3809954 | O71: Unit confirmed in the website: https://www.mcewenmining.com/operations/black-fox-complex/default.aspx | P71: CMP-3ff42329 | Q71: McEwenMiningInc_SEC_2024
A72: PROD-4e0734b5-2023-4 | B72: 2023 | C72: Canada | D72: ON-MAIN-4e0734b5 | F72: Fox Complex | H72: Silver | I72: Usable ore | J72: Contained metal in doré | K72: Production | L72: koz | M72: 1.4 | N72: 0.0435449 | O72: Unit confirmed in the website: https://www.mcewenmining.com/operations/black-fox-complex/default.aspx | P72: CMP-3ff42329 | Q72: McEwenMiningInc_SEC_2024
A73: PROD-206041d1-2024-1 | B73: 2024 | C73: Canada | D73: ON-MAIN-206041d1 | E73: GRP-de097f20 | F73: Fraser | G73: Integrated Nickel Operations | H73: Ore | I73: Total extraction | J73: Ore mined | K73: Production | L73: t | M73: 553033 | N73: 553033 | P73: CMP-d5f1c66b | Q73: https://www.glencore.ca/en/sudburyino/who-we-are/at-a-glance
A74: PROD-48fe2205-2023-1 | B74: 2023 | C74: Canada | D74: ON-MAIN-48fe2205 | E74: GRP-dc07540b | F74: Garson | G74: Sudbury Operation | H74: Nickel | I74: Usable ore | J74: Contained metal in concentrate | K74: Production | L74: t | M74: 7946 | N74: 7946 | O74: https://www.geologyontario.mndm.gov.on.ca/mndmfiles/mdi/data/records/MDI41I10SW00006.html | P74: CMP-9617aef4 | Q74: Vale_nan
A75: PROD-48fe2205-2023-2 | B75: 2023 | C75: Canada | D75: ON-MAIN-48fe2205 | E75: GRP-dc07540b | F75: Garson | G75: Sudbury Operation | H75: Copper | I75: Usable ore | J75: Contained metal in concentrate | K75: Production | L75: t | M75: 7453 | N75: 7453 | O75: https://www.geologyontario.mndm.gov.on.ca/mndmfiles/mdi/data/records/MDI41I10SW00006.html | P75: CMP-9617aef4 | Q75: Vale_nan
A76: PROD-48fe2205-2023-3 | B76: 2023 | C76: Canada | D76: ON-MAIN-48fe2205 | E76: GRP-dc07540b | F76: Garson | G76: Sudbury Operation | H76: Ore | I76: Crude ore | J76: Ore processed | K76: Production | L76: t | M76: 616000 | N76: 616000 | O76: https://www.geologyontario.mndm.gov.on.ca/mndmfiles/mdi/data/records/MDI41I10SW00006.html | P76: CMP-9617aef4 | Q76: Vale_nan
A77: 1754060_prod | B77: 2023 | C77: Canada | D77: ON-MAIN-48fe2205 | E77: GRP-dc07540b | F77: Garson | G77: Sudbury Operation | H77: Copper | I77: Crude ore | K77: Production | L77: t of copper ore | M77: 650000 | N77: 650000 | P77: CMP-9617aef4 | Q77: https://github.com/climatetracecoalition/methodology-documents/tree/main/2024/Mineral%20Extraction
A78: 1754060_cap | B78: 2023 | C78: Canada | D78: ON-MAIN-48fe2205 | E78: GRP-dc07540b | F78: Garson | G78: Sudbury Operation | I78: Crude ore | K78: Capacity | L78: tonnes | M78: 4822000 | N78: 4822000 | P78: CMP-9617aef4 | Q78: https://github.com/climatetracecoalition/methodology-documents/tree/main/2024/Mineral%20Extraction
A79: PROD-6b4800fe-2023-1 | B79: 2023 | C79: Canada | D79: BC-MAIN-6b4800fe | F79: Gibraltar | H79: Ore | I79: Total extraction | J79: Ore mined | K79: Production | L79: mt | M79: 88.1 | N79: 88100000 | P79: CMP-e35f138c | Q79: https://www.tasekomines.com/investors/news/taseko-reports-strong-fourth-quarter-financial-performance-and-190-million-of-adjusted-ebitda-for-2023/
A80: PROD-6b4800fe-2023-2 | B80: 2023 | C80: Canada | D80: BC-MAIN-6b4800fe | F80: Gibraltar | H80: Ore | I80: Crude ore | J80: Ore milled | K80: Production | L80: mt | M80: 30 | N80: 30000000 | P80: CMP-e35f138c | Q80: https://www.tasekomines.com/investors/news/taseko-reports-strong-fourth-quarter-financial-performance-and-190-million-of-adjusted-ebitda-for-2023/
A81: PROD-6b4800fe-2023-3 | B81: 2023 | C81: Canada | D81: BC-MAIN-6b4800fe | F81: Gibraltar | H81: Molybdenum | I81: Usable ore | J81: Contained metal in concentrate | K81: Production | L81: klbs | M81: 1202 | N81: 545.21758 | O81: Given in klbs Mo so assumed metal in concentrate | P81: CMP-e35f138c | Q81: https://www.tasekomines.com/investors/news/taseko-reports-strong-fourth-quarter-financial-performance-and-190-million-of-adjusted-ebitda-for-2023/
A82: PROD-6b4800fe-2023-4 | B82: 2023 | C82: Canada | D82: BC-MAIN-6b4800fe | F82: Gibraltar | H82: Copper | I82: Usable ore | J82: Contained metal in concentrate | K82: Production | L82: mlbs | M82: 122.6 | N82: 55610.379 | O82: Given in Mlbs Cu so assumed metal in concentrate | P82: CMP-e35f138c | Q82: https://www.tasekomines.com/investors/news/taseko-reports-strong-fourth-quarter-financial-performance-and-190-million-of-adjusted-ebitda-for-2023/
A83: 1754061_prod | B83: 2023 | C83: Canada | D83: BC-MAIN-6b4800fe | F83: Gibraltar | H83: Copper | I83: Crude ore | K83: Production | L83: t of copper ore | M83: 88100000 | N83: 88100000 | P83: CMP-e35f138c | Q83: https://github.com/climatetracecoalition/methodology-documents/tree/main/2024/Mineral%20Extraction
A84: 1754061_cap | B84: 2023 | C84: Canada | D84: BC-MAIN-6b4800fe | F84: Gibraltar | I84: Crude ore | K84: Capacity | L84: tonnes | M84: 6.45e+08 | N84: 6.45e+08 | P84: CMP-e35f138c | Q84: https://github.com/climatetracecoalition/methodology-documents/tree/main/2024/Mineral%20Extraction
A85: PROD-c0660aec-2023-1 | B85: 2023 | C85: Canada | D85: QC-MAIN-c0660aec | F85: Goldex | H85: Copper | I85: Usable ore | J85: Contained metal in concentrate | K85: Production | L85: t | M85: 39.036758 | N85: 39.036758 | O85: The sustainability report inversed zinc and copper | P85: CMP-6265c407 | Q85: AgnicoEagleMinesLimited_operational_data
A86: PROD-c0660aec-2023-2 | B86: 2023 | C86: Canada | D86: QC-MAIN-c0660aec | F86: Goldex | H86: Ore | I86: Crude ore | J86: Ore processed | K86: Production | L86: t | M86: 2886927.3 | N86: 2886927.3 | P86: CMP-6265c407 | Q86: AgnicoEagleMinesLimited_2023-Sustainability-Performance_data
A87: PROD-c0660aec-2023-3 | B87: 2023 | C87: Canada | D87: QC-MAIN-c0660aec | F87: Goldex | H87: Gold | I87: Usable ore | J87: Contained metal in doré | K87: Production | L87: oz | M87: 140982.57 | N87: 4.3850513 | P87: CMP-6265c407 | Q87: AgnicoEagleMinesLimited_2023-Sustainability-Performance_data
A88: PROD-c0660aec-2023-4 | B88: 2023 | C88: Canada | D88: QC-MAIN-c0660aec | F88: Goldex | H88: Silver | I88: Usable ore | J88: Contained metal in doré | K88: Production | L88: koz | M88: 2 | N88: 0.062207 | P88: CMP-6265c407 | Q88: AgnicoEagleMinesLimited_2023-Sustainability-Performance_data
A89: PROD-01c1e81f-2023-1 | B89: 2023 | C89: Canada | D89: QC-MAIN-01c1e81f | E89: GRP-677b5973 | F89: Grande-Baie | G89: Saguenay–Lac-Saint-Jean Operations | H89: Aluminum | I89: Intermediate metal produced | J89: Smelter production | K89: Capacity | L89: t | M89: 233000 | P89: CMP-7a096012 | Q89: https://aluminium.ca/en/the-industry/
A90: PROD-01c1e81f-2023-2 | B90: 2023 | C90: Canada | D90: QC-MAIN-01c1e81f | E90: GRP-677b5973 | F90: Grande-Baie | G90: Saguenay–Lac-Saint-Jean Operations | H90: Aluminum | I90: Intermediate metal produced | J90: Smelter production | K90: Production | L90: kt | M90: 229 | N90: 229000 | P90: CMP-7a096012 | Q90: RioTinto_rt-fact-book-addendum
A91: PROD-6e9be24e-2023-1 | B91: 2023 | C91: Canada | D91: ON-MAIN-6e9be24e | F91: Hemlo (Williams) | H91: Gold | I91: Crude ore | J91: Ore processed | K91: Production | L91: t | M91: 1266009 | N91: 1266009 | O91: Not sure of the unit | P91: CMP-79bcdb91 | Q91: BarrickGoldCorporation_Barrick_2023_Performance-Data
A92: PROD-6e9be24e-2023-2 | B92: 2023 | C92: Canada | D92: ON-MAIN-6e9be24e | F92: Hemlo (Williams) | H92: Gold | I92: Usable ore | J92: Contained metal in doré | K92: Production | L92: oz | M92: 141045 | N92: 4.3869932 | P92: CMP-79bcdb91 | Q92: BarrickGoldCorporation_Barrick_2023_Performance-Data
A93: PROD-bf503b6b-2024-1 | B93: 2024 | C93: Canada | D93: BC-MAIN-bf503b6b | F93: Highland Valley | H93: Ore | I93: Crude ore | J93: Ore processed | K93: Production | L93: kt | M93: 17408 | N93: =M93*1000 -> 17408000 | O93: Assumed 0,34% ore grade and 85% recovery rate, taking copper as the reference | P93: CMP-06e20c6e | Q93: https://minfile.gov.bc.ca/summary.aspx?minfilno=092ISW012
A94: PROD-bf503b6b-2024-2 | B94: 2024 | C94: Canada | D94: BC-MAIN-bf503b6b | F94: Highland Valley | H94: Molybdenum | I94: Usable ore | J94: Contained metal in concentrate | K94: Production | L94: kt | M94: 0.9 | N94: 900 | P94: CMP-06e20c6e | Q94: TeckResourcesLimited_2024_Annual_report
A95: PROD-bf503b6b-2024-3 | B95: 2024 | C95: Canada | D95: BC-MAIN-bf503b6b | F95: Highland Valley | H95: Copper | I95: Usable ore | J95: Contained metal in concentrate | K95: Production | L95: kt | M95: 102.4 | N95: 102400 | P95: CMP-06e20c6e | Q95: TeckResourcesLimited_2024_Annual_report
A96: 1754066_prod | B96: 2023 | C96: Canada | D96: BC-MAIN-bf503b6b | F96: Highland Valley | H96: Copper | I96: Crude ore | K96: Production | L96: t of copper ore | M96: 72886000 | N96: 72886000 | P96: CMP-06e20c6e | Q96: https://github.com/climatetracecoalition/methodology-documents/tree/main/2024/Mineral%20Extraction
A97: 1754066_cap | B97: 2023 | C97: Canada | D97: BC-MAIN-bf503b6b | F97: Highland Valley | I97: Crude ore | K97: Capacity | L97: tonnes | M97: 2.631e+08 | N97: 2.631e+08 | P97: CMP-06e20c6e | Q97: https://github.com/climatetracecoalition/methodology-documents/tree/main/2024/Mineral%20Extraction
A98: 1754067_prod | B98: 2023 | C98: Canada | D98: QC-MAIN-30c1828c | E98: GRP-b48ec279 | F98: Horne | G98: CCR | H98: Copper | I98: Crude ore | K98: Production | L98: t of copper ore | M98: 0 | N98: 0 | P98: CMP-d5f1c66b | Q98: https://github.com/climatetracecoalition/methodology-documents/tree/main/2024/Mineral%20Extraction
A99: 1754067_cap | B99: 2023 | C99: Canada | D99: QC-MAIN-30c1828c | E99: GRP-b48ec279 | F99: Horne | G99: CCR | I99: Crude ore | K99: Capacity | L99: tonnes | M99: 87879593 | N99: 87879593 | P99: CMP-d5f1c66b | Q99: https://github.com/climatetracecoalition/methodology-documents/tree/main/2024/Mineral%20Extraction
A100: PROD-GRP-0d911886-2023-1 | B100: 2023 | C100: Canada | E100: GRP-0d911886 | F100: Hoyle Pond | G100: Porcupine complex | H100: Gold | I100: Usable ore | J100: Contained metal in doré | K100: Production | L100: koz | M100: 260 | N100: 8.08691 | P100: CMP-4a434d72 | Q100: NewmontCorporation_Operating_statistics_2023
...

Sheet site_selection_1
A1: Category | B1: Site_id | C1: Site_name | D1: Commodities | E1: Type | F1: Comment
A2: Unique_to_TA | B2: QC-MAIN-089f3c60 | C2: Bloom Lake | D2: Iron ore | E2: Mining
A3: Unique_to_matnrj | B3: NL-MAIN-dd723db4 | C3: Carol Lake | D3: Iron ore | E3: Mining
A4: Unique_to_TA | B4: ON-MAIN-de2f9639 | C4: Clarabelle | D4: Nickel, copper, platinum group metals, gold, silver, cobalt | E4: Mining
A5: Unique_to_TA | B5: ON-MAIN-52224e1e | C5: Creighton | D5: Nickel, copper, platinum group metals, gold, silver, cobalt | E5: Mining
A6: Unique_to_TA | B6: BC-MAIN-4724f4ba | C6: Elk | D6: Gold | E6: Mining | F6: No biosphere flows
A7: Unique_to_TA | B7: ON-MAIN-4e0734b5 | C7: Fox Complex | D7: Gold | E7: Mining
A8: Unique_to_TA | B8: ON-MAIN-48fe2205 | C8: Garson | D8: Nickel, copper, platinum group metals, gold, silver, cobalt | E8: Mining
A9: Unique_to_TA | B9: BC-MAIN-bf503b6b | C9: Highland Valley | D9: Copper, silver, molybdenum | E9: Mining
A10: Unique_to_TA | B10: ON-MAIN-f8313ebd | C10: Kidd Creek | D10: Copper, zinc, silver, selenium, indium | E10: Mining
A11: Unique_to_TA | B11: MB-MAIN-be5b3dc8 | C11: Lalor Lake
A12: Unique_to_TA | B12: ON-MAIN-8825d90d | C12: Magino | D12: Gold, silver | E12: Mining
A13: Unique_to_TA | B13: ON-MAIN-7001a391 | C13: McCreedy West | D13: Copper, nickel, platinum group metals, gold, silver, cobalt | E13: Mining
A14: Unique_to_TA | B14: BC-MAIN-3f490561 | C14: Mount Polley | D14: Gold, copper, silver | E14: Mining
A15: Unique_to_TA | B15: MB-MAIN-da0b5c3d | C15: New Britannia
A16: Unique_to_matnrj | B16: NL-MAIN-b64bae7a | C16: Scully | D16: Iron ore | E16: Mining
A17: Unique_to_matnrj | B17: GRP-a13779f8 | C17: Snow Lake
A18: Unique_to_TA | B18: MB-MAIN-0898e255 | C18: Stall Lake
A19: Unique_to_TA | B19: ON-MAIN-f4fc3276 | C19: Sugar Zone | D19: Gold | E19: Mining | F19: No biosphere flows
A20: Unique_to_TA | B20: AB-MAIN-d3a4aba9 | C20: The Cobalt Refinery Company Inc. | D20: Nickel, cobalt, copper sulfide, ammonium sulfate | E20: Manufacturing
A21: Unique_to_TA | B21: ON-MAIN-28f3f0fc | C21: Totten | D21: Nickel, copper, platinum group metals, gold, silver, cobalt | E21: Mining
A26: Mine Name | B26: Mining Method | C26: Ore Type | D26: Processing Steps | E26: Final Product | F26: Onsite Refining
A27: Brucejack | B27: Underground | C27: Partially free-milling, partially refractory | D27: Gravity + Flotation | E27: Doré + Gold-Silver Concentrate | F27: Partial
A28: Canadian Malartic | B28: Open-pit + Underground | C28: Free-milling | D28: Crushing, Grinding, Cyanide Leaching, CIP | E28: Doré | F28: Yes
A29: Carol Lake | B29: Open-pit | C29: Magnetite/Hematite (Iron Ore) | D29: Crushing, Grinding, Magnetic Separation | E29: Iron Ore Concentrate | F29: No
A30: Casa Berardi | B30: Underground + Open-pit | C30: Free-milling | D30: Gravity, Cyanidation, CIL | E30: Doré | F30: Yes
A31: Copper Mountain | B31: Open-pit | C31: Refractory | D31: Flotation | E31: Copper Concentrate (Au/Ag by-products) | F31: No
A32: Detour Lake | B32: Open-pit | C32: Free-milling | D32: Gravity, Cyanidation, CIP | E32: Doré | F32: Yes
A33: Eagle River | B33: Underground | C33: Free-milling | D33: Cyanidation, Merrill-Crowe | E33: Doré | F33: Yes
A34: Éléonore | B34: Underground | C34: Refractory | D34: Gravity, Flotation, Regrind, Leaching, CIP | E34: Doré | F34: Yes
A35: Gibraltar | B35: Open-pit | C35: Porphyry Copper (Gold/Silver in sulfides) | D35: Crushing, Grinding, Flotation | E35: Copper & Molybdenum Concentrates | F35: No
A36: Goldex | B36: Underground | C36: Partially free-milling, partially refractory | D36: Gravity + Flotation (concentrate sent to LaRonde) | E36: Doré + Pyrite Concentrate | F36: Partial
A37: Hemlo (Williams) | B37: Underground | C37: Free-milling | D37: Gravity, Cyanidation, CIP | E37: Doré | F37: Yes
... A59: Snow Lake | B59: Underground | C59: Partly Free-milling, Partly Refractory | D59: Flotation (Cu/Zn), Gravity + CIL (Au) | E59: Doré + Base Metal Concentrates | F59: Yes

Sheet ms_benchmark
A1: commodity | B1: mine | C1: source
A2: Gold | B2: Detour Lake | C2: https://www.mining-technology.com/marketdata/five-largest-gold-mines-canada/
A3: Gold | B3: Canadian Malartic | C3: https://www.mining-technology.com/marketdata/five-largest-gold-mines-canada/
A4: Gold | B4: Meadowbank complex | C4: https://www.mining-technology.com/marketdata/five-largest-gold-mines-canada/
A5: Gold | B5: Meliadine | C5: https://www.mining-technology.com/marketdata/five-largest-gold-mines-canada/
A6: Gold | B6: Brucejack | C6: https://www.mining-technology.com/marketdata/five-largest-gold-mines-canada/
A7: Nickel | B7: Raglan | C7: https://www.mining-technology.com/marketdata/five-largest-nickel-mines-canada/
A8: Nickel | B8: Sudbury area | C8: https://www.mining-technology.com/marketdata/five-largest-nickel-mines-canada/
A9: Nickel | B9: Voisey's Bay | C9: https://www.mining-technology.com/marketdata/five-largest-nickel-mines-canada/
A10: Nickel | B10: Coleman | C10: https://www.mining-technology.com/marketdata/five-largest-nickel-mines-canada/
A11: Nickel | B11: Nunavik Nickel | C11: https://www.mining-technology.com/marketdata/five-largest-nickel-mines-canada/
A12: Copper | B12: Highland Valley | C12: https://www.mining-technology.com/marketdata/five-largest-copper-mines-canada/
... A16: Copper | B16: Kidd Creek | C16: https://www.mining-technology.com/marketdata/five-largest-copper-mines-canada/

Sheet Arch_refineries
A1: Product | B1: Site | C1: Owner | D1: Sofia_LCI | E1: Archetype | F1: Main inputs | G1: Main outputs | H1: Downstream / Notes | I1: Details | J1: LCI_mapping
A2: Cu | B2: Horne Smelter (QC) | C2: Glencore | D2: Pyrometallurgical treatment of sulfide ores | E2: Cu pyrometallurgy (smelter) | F2: Cu conc., e-scrap | G2: Cu anodes (99.1%) | H2: Sent to CCR for electro-refining; slimes to PM recovery. (Glencore Canada) | I2: Casting 99.1% Cu anodes. Anodes are shipped to CCR for electro-refining | J2: Use Cu pyromet→anode inventory; include off-gas capture/SO₂; allocate/by-account for PM-rich anode slime headed to CCR.
A3: Cu | B3: CCR (QC) | C3: Glencore | E3: Cu electro-refining | F3: Cu anodes | G3: Cu cathodes (99.99%), slimes (Au/Ag/Se/Te) | H3: PM recovery on-site; integrated with Horne. (Glencore Canada) | I3: Anode dissolution → Cu cathode (99.99%) via electro-refining; slimes recovery for Au/Ag/Se/Te, etc | J3: Map to Cu hydromet/electro-refining to cathode; include by-product recovery chain for slimes.
